Workbook
Name Plage_BoissonJus: tbl_BoissonJus!$A$1:$F$181
Name Plage_GauffreCrepe: 'tbl_GaufCre&Dsrt'!$A$1:$F$198
Name Plage_Marocains: 'tbl_Taj&Pla'!$A$1:$F$345
Name Plage_PtiDej: 'tbl_PtDj&Sup'!$A$1:$F$168
Name Plage_Snack: 'tbl_Snk&Ita'!$A$1:$F$300

Sheet Dashboard
B1: Date début | C1: Date fin
B2: 45931 | C2: 45961
B3: Total charges fixes mensuelles | C3: Total CA sur la période | F3: Charges fixes par portion | G3: Charge Fixes par Portion
B4: =SUM(tbl_Charges_Fixes[Montant_Mensuel]) -> 929242 | C4: =IFERROR(SUMIFS(tbl_Ventes[CA ligne], tbl_Ventes[Date], ">="&$B$2, tbl_Ventes[Date], "<="&$C$2),"Vérifier") -> 1242446 | D4: Charges fixes de la période | F4: =IFERROR(SUMIFS(tbl_Ventes[Qté Vendue], tbl_Ventes[Date], ">="&$B$2, tbl_Ventes[Date], "<="&$C$2),0) -> 10787 | G4: =IF(SUMIFS(tbl_Ventes[Qté Vendue], tbl_Ventes[Date], ">="&$B$2, tbl_Ventes[Date], "<="&$C$2)=0, 0, tbl_Charges_Fixes[[#Totals],[Montant_Mensuel]] / SUMIFS(tbl_Ventes[Qté Vendue], tbl_Ventes[Date], ">="&$B$2, tbl_Ventes[Date], "<="&$C$2)) -> 86.144619
B5: Nombre de jours analysés | C5: =MAX(1, $C$2 - $B$2 + 1) -> 31 | D5: =B4 * C5 / 30 -> 960216.73
A7: Total CA | B7: Coût matière total | C7: Marge brute total | D7: % marge brute | E7: Food cost % | F7: Total charges fixes mensuelles | G7: Marge nette après charges
A8: =+$C$4 -> 1242446 | B8: =IFERROR(SUMIFS(tbl_Ventes[Coût matière ligne], tbl_Ventes[Date], ">="&$B$2, tbl_Ventes[Date], "<="&$C$2),"Vérifier") -> 1023679.7 | C8: =IFERROR($A$8- $B$8,"Vérifier") -> 218766.3 | D8: =IFERROR(IF(tbl_Kpi[[#This Row],[Total CA]]=0, 0, tbl_Kpi[[#This Row],[Marge brute total]] / tbl_Kpi[[#This Row],[Total CA]]),"Vérifier") -> 0.17607711 | E8: =IFERROR(IF(tbl_Kpi[[#This Row],[Total CA]]>0, tbl_Kpi[[#This Row],[Coût matière total]]/tbl_Kpi[[#This Row],[Total CA]]),"Vérifier") -> 0.82392289 | F8: =$B$4 -> 929242 | G8: =IFERROR(tbl_Kpi[[#This Row],[Marge brute total]] - tbl_Kpi[[#This Row],[Total charges fixes mensuelles]],"Vérifier") -> -710475.7
A10: Famille | B10: CA Famille | C10: Coût matière Famille | D10: Marge brute famille | E10: Charges globales réparties | F10: Charges spécifiques | G10: Charges totales | H10: Marge nette
A11: Petits déjeuners | B11: =SUMIF(tbl_Ventes[Famille], tbl_Famille[[#This Row],[Famille]], tbl_Ventes[CA ligne]) -> 62640 | C11: =IFERROR(SUMIF(tbl_Ventes[Famille], tbl_Famille[[#This Row],[Famille]], tbl_Ventes[Coût matière ligne]),"Vérifier") -> 28420 | D11: =IFERROR(tbl_Famille[[#This Row],[CA Famille]] - tbl_Famille[[#This Row],[Coût matière Famille]],"Vérifier") -> 34220 | E11: =SUMIF(tbl_Charges_Fixes[Type d’affectation],"Globale",tbl_Charges_Fixes[Montant_Mensuel]) -> 498592 | F11: =IFERROR(SUMIFS(tbl_Charges_Fixes[Montant_Mensuel], tbl_Charges_Fixes[Type d’affectation], "Spécifique", tbl_Charges_Fixes[Famille affectée], tbl_Famille[[#This Row],[Famille]]),"Vérifier") -> 24000 | G11: =IFERROR(tbl_Famille[[#This Row],[Charges globales réparties]] + tbl_Famille[[#This Row],[Charges spécifiques]],"Vérifier") -> 522592 | H11: =IFERROR(tbl_Famille[[#This Row],[Marge brute famille]] - tbl_Famille[[#This Row],[Charges totales]],"Vérifier") -> -488372
A12: Œufs & Omelettes | B12: =SUMIF(tbl_Ventes[Famille], tbl_Famille[[#This Row],[Famille]], tbl_Ventes[CA ligne]) -> 3546 | C12: =IFERROR(SUMIF(tbl_Ventes[Famille], tbl_Famille[[#This Row],[Famille]], tbl_Ventes[Coût matière ligne]),"Vérifier") -> 1616.51 | D12: =IFERROR(tbl_Famille[[#This Row],[CA Famille]] - tbl_Famille[[#This Row],[Coût matière Famille]],"Vérifier") -> 1929.49 | E12: =SUMIF(tbl_Charges_Fixes[Type d’affectation],"Globale",tbl_Charges_Fixes[Montant_Mensuel]) -> 498592 | F12: =IFERROR(SUMIFS(tbl_Charges_Fixes[Montant_Mensuel], tbl_Charges_Fixes[Type d’affectation], "Spécifique", tbl_Charges_Fixes[Famille affectée], tbl_Famille[[#This Row],[Famille]]),"Vérifier") -> 24000 | G12: =IFERROR(tbl_Famille[[#This Row],[Charges globales réparties]] + tbl_Famille[[#This Row],[Charges spécifiques]],"Vérifier") -> 522592 | H12: =IFERROR(tbl_Famille[[#This Row],[Marge brute famille]] - tbl_Famille[[#This Row],[Charges totales]],"Vérifier") -> -520662.51
A13: à la carte | B13: =SUMIF(tbl_Ventes[Famille], tbl_Famille[[#This Row],[Famille]], tbl_Ventes[CA ligne]) -> 9100 | C13: =IFERROR(SUMIF(tbl_Ventes[Famille], tbl_Famille[[#This Row],[Famille]], tbl_Ventes[Coût matière ligne]),"Vérifier") -> 12090 | D13: =IFERROR(tbl_Famille[[#This Row],[CA Famille]] - tbl_Famille[[#This Row],[Coût matière Famille]],"Vérifier") -> -2990 | E13: =SUMIF(tbl_Charges_Fixes[Type d’affectation],"Globale",tbl_Charges_Fixes[Montant_Mensuel]) -> 498592 | F13: =IFERROR(SUMIFS(tbl_Charges_Fixes[Montant_Mensuel], tbl_Charges_Fixes[Type d’affectation], "Spécifique", tbl_Charges_Fixes[Famille affectée], tbl_Famille[[#This Row],[Famille]]),"Vérifier") -> 24000 | G13: =IFERROR(tbl_Famille[[#This Row],[Charges globales réparties]] + tbl_Famille[[#This Row],[Charges spécifiques]],"Vérifier") -> 522592 | H13: =IFERROR(tbl_Famille[[#This Row],[Marge brute famille]] - tbl_Famille[[#This Row],[Charges totales]],"Vérifier") -> -525582
A14: Suppléments | B14: =SUMIF(tbl_Ventes[Famille], tbl_Famille[[#This Row],[Famille]], tbl_Ventes[CA ligne]) -> 4158 | C14: =IFERROR(SUMIF(tbl_Ventes[Famille], tbl_Famille[[#This Row],[Famille]], tbl_Ventes[Coût matière ligne]),"Vérifier") -> 10834 | D14: =IFERROR(tbl_Famille[[#This Row],[CA Famille]] - tbl_Famille[[#This Row],[Coût matière Famille]],"Vérifier") -> -6676 | E14: =SUMIF(tbl_Charges_Fixes[Type d’affectation],"Globale",tbl_Charges_Fixes[Montant_Mensuel]) -> 498592 | F14: =IFERROR(SUMIFS(tbl_Charges_Fixes[Montant_Mensuel], tbl_Charges_Fixes[Type d’affectation], "Spécifique", tbl_Charges_Fixes[Famille affectée], tbl_Famille[[#This Row],[Famille]]),"Vérifier") -> 0 | G14: =IFERROR(tbl_Famille[[#This Row],[Charges globales réparties]] + tbl_Famille[[#This Row],[Charges spécifiques]],"Vérifier") -> 498592 | H14: =IFERROR(tbl_Famille[[#This Row],[Marge brute famille]] - tbl_Famille[[#This Row],[Charges totales]],"Vérifier") -> -505268
A15: Entrées & Salades | B15: =SUMIF(tbl_Ventes[Famille], tbl_Famille[[#This Row],[Famille]], tbl_Ventes[CA ligne]) -> 0 | C15: =IFERROR(SUMIF(tbl_Ventes[Famille], tbl_Famille[[#This Row],[Famille]], tbl_Ventes[Coût matière ligne]),"Vérifier") -> 0 | D15: =IFERROR(tbl_Famille[[#This Row],[CA Famille]] - tbl_Famille[[#This Row],[Coût matière Famille]],"Vérifier") -> 0 | E15: =SUMIF(tbl_Charges_Fixes[Type d’affectation],"Globale",tbl_Charges_Fixes[Montant_Mensuel]) -> 498592 | F15: =IFERROR(SUMIFS(tbl_Charges_Fixes[Montant_Mensuel], tbl_Charges_Fixes[Type d’affectation], "Spécifique", tbl_Charges_Fixes[Famille affectée], tbl_Famille[[#This Row],[Famille]]),"Vérifier") -> 40000 | G15: =IFERROR(tbl_Famille[[#This Row],[Charges globales réparties]] + tbl_Famille[[#This Row],[Charges spécifiques]],"Vérifier") -> 538592 | H15: =IFERROR(tbl_Famille[[#This Row],[Marge brute famille]] - tbl_Famille[[#This Row],[Charges totales]],"Vérifier") -> -538592
A16: Poulet | B16: =SUMIF(tbl_Ventes[Famille], tbl_Famille[[#This Row],[Famille]], tbl_Ventes[CA ligne]) -> 0 | C16: =IFERROR(SUMIF(tbl_Ventes[Famille], tbl_Famille[[#This Row],[Famille]], tbl_Ventes[Coût matière ligne]),"Vérifier") -> 0 | D16: =IFERROR(tbl_Famille[[#This Row],[CA Famille]] - tbl_Famille[[#This Row],[Coût matière Famille]],"Vérifier") -> 0 | E16: =SUMIF(tbl_Charges_Fixes[Type d’affectation],"Globale",tbl_Charges_Fixes[Montant_Mensuel]) -> 498592 | F16: =IFERROR(SUMIFS(tbl_Charges_Fixes[Montant_Mensuel], tbl_Charges_Fixes[Type d’affectation], "Spécifique", tbl_Charges_Fixes[Famille affectée], tbl_Famille[[#This Row],[Famille]]),"Vérifier") -> 24000 | G16: =IFERROR(tbl_Famille[[#This Row],[Charges globales réparties]] + tbl_Famille[[#This Row],[Charges spécifiques]],"Vérifier") -> 522592 | H16: =IFERROR(tbl_Famille[[#This Row],[Marge brute famille]] - tbl_Famille[[#This Row],[Charges totales]],"Vérifier") -> -522592
A17: Boucherie | B17: =SUMIF(tbl_Ventes[Famille], tbl_Famille[[#This Row],[Famille]], tbl_Ventes[CA ligne]) -> 537660 | C17: =IFERROR(SUMIF(tbl_Ventes[Famille], tbl_Famille[[#This Row],[Famille]], tbl_Ventes[Coût matière ligne]),"Vérifier") -> 743000 | D17: =IFERROR(tbl_Famille[[#This Row],[CA Famille]] - tbl_Famille[[#This Row],[Coût matière Famille]],"Vérifier") -> -205340 | E17: =SUMIF(tbl_Charges_Fixes[Type d’affectation],"Globale",tbl_Charges_Fixes[Montant_Mensuel]) -> 498592 | F17: =IFERROR(SUMIFS(tbl_Charges_Fixes[Montant_Mensuel], tbl_Charges_Fixes[Type d’affectation], "Spécifique", tbl_Charges_Fixes[Famille affectée], tbl_Famille[[#This Row],[Famille]]),"Vérifier") -> 6540 | G17: =IFERROR(tbl_Famille[[#This Row],[Charges globales réparties]] + tbl_Famille[[#This Row],[Charges spécifiques]],"Vérifier") -> 505132 | H17: =IFERROR(tbl_Famille[[#This Row],[Marge brute famille]] - tbl_Famille[[#This Row],[Charges totales]],"Vérifier") -> -710472
A18: Poissons & Fruits de mer | B18: =SUMIF(tbl_Ventes[Famille], tbl_Famille[[#This Row],[Famille]], tbl_Ventes[CA ligne]) -> 0 | C18: =IFERROR(SUMIF(tbl_Ventes[Famille], tbl_Famille[[#This Row],[Famille]], tbl_Ventes[Coût matière ligne]),"Vérifier") -> 0 | D18: =IFERROR(tbl_Famille[[#This Row],[CA Famille]] - tbl_Famille[[#This Row],[Coût matière Famille]],"Vérifier") -> 0 | E18: =SUMIF(tbl_Charges_Fixes[Type d’affectation],"Globale",tbl_Charges_Fixes[Montant_Mensuel]) -> 498592 | F18: =IFERROR(SUMIFS(tbl_Charges_Fixes[Montant_Mensuel], tbl_Charges_Fixes[Type d’affectation], "Spécifique", tbl_Charges_Fixes[Famille affectée], tbl_Famille[[#This Row],[Famille]]),"Vérifier") -> 6555 | G18: =IFERROR(tbl_Famille[[#This Row],[Charges globales réparties]] + tbl_Famille[[#This Row],[Charges spécifiques]],"Vérifier") -> 505147 | H18: =IFERROR(tbl_Famille[[#This Row],[Marge brute famille]] - tbl_Famille[[#This Row],[Charges totales]],"Vérifier") -> -505147
A19: Tajines & Coin marocain | B19: =SUMIF(tbl_Ventes[Famille], tbl_Famille[[#This Row],[Famille]], tbl_Ventes[CA ligne]) -> 550200 | C19: =IFERROR(SUMIF(tbl_Ventes[Famille], tbl_Famille[[#This Row],[Famille]], tbl_Ventes[Coût matière ligne]),"Vérifier") -> 191475.98 | D19: =IFERROR(tbl_Famille[[#This Row],[CA Famille]] - tbl_Famille[[#This Row],[Coût matière Famille]],"Vérifier") -> 358724.02 | E19: =SUMIF(tbl_Charges_Fixes[Type d’affectation],"Globale",tbl_Charges_Fixes[Montant_Mensuel]) -> 498592 | F19: =IFERROR(SUMIFS(tbl_Charges_Fixes[Montant_Mensuel], tbl_Charges_Fixes[Type d’affectation], "Spécifique", tbl_Charges_Fixes[Famille affectée], tbl_Famille[[#This Row],[Famille]]),"Vérifier") -> 65555 | G19: =IFERROR(tbl_Famille[[#This Row],[Charges globales réparties]] + tbl_Famille[[#This Row],[Charges spécifiques]],"Vérifier") -> 564147 | H19: =IFERROR(tbl_Famille[[#This Row],[Marge brute famille]] - tbl_Famille[[#This Row],[Charges totales]],"Vérifier") -> -205422.98
A20: Pâtes | B20: =SUMIF(tbl_Ventes[Famille], tbl_Famille[[#This Row],[Famille]], tbl_Ventes[CA ligne]) -> 0 | C20: =IFERROR(SUMIF(tbl_Ventes[Famille], tbl_Famille[[#This Row],[Famille]], tbl_Ventes[Coût matière ligne]),"Vérifier") -> 0 | D20: =IFERROR(tbl_Famille[[#This Row],[CA Famille]] - tbl_Famille[[#This Row],[Coût matière Famille]],"Vérifier") -> 0 | E20: =SUMIF(tbl_Charges_Fixes[Type d’affectation],"Globale",tbl_Charges_Fixes[Montant_Mensuel]) -> 498592 | F20: =IFERROR(SUMIFS(tbl_Charges_Fixes[Montant_Mensuel], tbl_Charges_Fixes[Type d’affectation], "Spécifique", tbl_Charges_Fixes[Famille affectée], tbl_Famille[[#This Row],[Famille]]),"Vérifier") -> 21000 | G20: =IFERROR(tbl_Famille[[#This Row],[Charges globales réparties]] + tbl_Famille[[#This Row],[Charges spécifiques]],"Vérifier") -> 519592 | H20: =IFERROR(tbl_Famille[[#This Row],[Marge brute famille]] - tbl_Famille[[#This Row],[Charges totales]],"Vérifier") -> -519592
A21: Pizzas | B21: =SUMIF(tbl_Ventes[Famille], tbl_Famille[[#This Row],[Famille]], tbl_Ventes[CA ligne]) -> 0 | C21: =IFERROR(SUMIF(tbl_Ventes[Famille], tbl_Famille[[#This Row],[Famille]], tbl_Ventes[Coût matière ligne]),"Vérifier") -> 0 | D21: =IFERROR(tbl_Famille[[#This Row],[CA Famille]] - tbl_Famille[[#This Row],[Coût matière Famille]],"Vérifier") -> 0 | E21: =SUMIF(tbl_Charges_Fixes[Type d’affectation],"Globale",tbl_Charges_Fixes[Montant_Mensuel]) -> 498592 | F21: =IFERROR(SUMIFS(tbl_Charges_Fixes[Montant_Mensuel], tbl_Charges_Fixes[Type d’affectation], "Spécifique", tbl_Charges_Fixes[Famille affectée], tbl_Famille[[#This Row],[Famille]]),"Vérifier") -> 21000 | G21: =IFERROR(tbl_Famille[[#This Row],[Charges globales réparties]] + tbl_Famille[[#This Row],[Charges spécifiques]],"Vérifier") -> 519592 | H21: =IFERROR(tbl_Famille[[#This Row],[Marge brute famille]] - tbl_Famille[[#This Row],[Charges totales]],"Vérifier") -> -519592
A22: Snack | B22: =SUMIF(tbl_Ventes[Famille], tbl_Famille[[#This Row],[Famille]], tbl_Ventes[CA ligne]) -> 0 | C22: =IFERROR(SUMIF(tbl_Ventes[Famille], tbl_Famille[[#This Row],[Famille]], tbl_Ventes[Coût matière ligne]),"Vérifier") -> 0 | D22: =IFERROR(tbl_Famille[[#This Row],[CA Famille]] - tbl_Famille[[#This Row],[Coût matière Famille]],"Vérifier") -> 0 | E22: =SUMIF(tbl_Charges_Fixes[Type d’affectation],"Globale",tbl_Charges_Fixes[Montant_Mensuel]) -> 498592 | F22: =IFERROR(SUMIFS(tbl_Charges_Fixes[Montant_Mensuel], tbl_Charges_Fixes[Type d’affectation], "Spécifique", tbl_Charges_Fixes[Famille affectée], tbl_Famille[[#This Row],[Famille]]),"Vérifier") -> 20000 | G22: =IFERROR(tbl_Famille[[#This Row],[Charges globales réparties]] + tbl_Famille[[#This Row],[Charges spécifiques]],"Vérifier") -> 518592 | H22: =IFERROR(tbl_Famille[[#This Row],[Marge brute famille]] - tbl_Famille[[#This Row],[Charges totales]],"Vérifier") -> -518592
... A29: Boissons froides | B29: =SUMIF(tbl_Ventes[Famille], tbl_Famille[[#This Row],[Famille]], tbl_Ventes[CA ligne]) -> 0 | C29: =IFERROR(SUMIF(tbl_Ventes[Famille], tbl_Famille[[#This Row],[Famille]], tbl_Ventes[Coût matière ligne]),"Vérifier") -> 0 | D29: =IFERROR(tbl_Famille[[#This Row],[CA Famille]] - tbl_Famille[[#This Row],[Coût matière Famille]],"Vérifier") -> 0 | E29: =SUMIF(tbl_Charges_Fixes[Type d’affectation],"Globale",tbl_Charges_Fixes[Montant_Mensuel]) -> 498592 | F29: =IFERROR(SUMIFS(tbl_Charges_Fixes[Montant_Mensuel], tbl_Charges_Fixes[Type d’affectation], "Spécifique", tbl_Charges_Fixes[Famille affectée], tbl_Famille[[#This Row],[Famille]]),"Vérifier") -> 40000 | G29: =IFERROR(tbl_Famille[[#This Row],[Charges globales réparties]] + tbl_Famille[[#This Row],[Charges spécifiques]],"Vérifier") -> 538592 | H29: =IFERROR(tbl_Famille[[#This Row],[Marge brute famille]] - tbl_Famille[[#This Row],[Charges totales]],"Vérifier") -> -538592

Sheet tbl_Ventes
A1: Date | B1: Mois | C1: Produit | D1: Cde_Prdt | E1: Qté Vendue | F1: Prix Menu | G1: CA ligne | H1: CMP_par_portion | I1: Coût matière ligne | J1: Marge ligne | K1: Famille
A2: 45955 | B2: =IFERROR(TEXT(tbl_Ventes[[#This Row],[Date]],"mm-aaaa"),"") -> 10-2025 | C2: Viennoiserie G | D2: =IFERROR( INDEX(tbl_ProduitsRef[Cde_Prdt],MATCH(tbl_Ventes[[#This Row],[Produit]],tbl_ProduitsRef[Produit],0)), "" ) -> SUP005 | E2: 33 | F2: =IFERROR( INDEX(tbl_ProduitsRef[Prix Menu],MATCH(tbl_Ventes[[#This Row],[Produit]],tbl_ProduitsRef[Produit],0)), "" ) -> 9 | G2: =tbl_Ventes[[#This Row],[Qté Vendue]] * IFERROR(_xlfn.XLOOKUP(tbl_Ventes[[#This Row],[Cde_Prdt]], tbl_Produits[Cde_Prdt], tbl_Produits[Prix Menu]), 0) -> 297 | H2: =IFERROR(_xlfn.XLOOKUP(tbl_Ventes[[#This Row],[Cde_Prdt]], tbl_Produits[Cde_Prdt], tbl_Produits[Coût Moyen Portion]), 0) -> 7 | I2: =tbl_Ventes[[#This Row],[Qté Vendue]] * tbl_Ventes[[#This Row],[CMP_par_portion]] -> 231 | J2: =tbl_Ventes[[#This Row],[CA ligne]] - tbl_Ventes[[#This Row],[Coût matière ligne]] -> 66 | K2: =IFERROR(INDEX(tbl_ProduitsRef[Famille], MATCH(tbl_Ventes[[#This Row],[Cde_Prdt]], tbl_Produits[Cde_Prdt], 0)), "") -> Suppléments
A3: 45956 | B3: =IFERROR(TEXT(tbl_Ventes[[#This Row],[Date]],"mm-aaaa"),"") -> 10-2025 | C3: Espagnol | D3: =IFERROR( INDEX(tbl_ProduitsRef[Cde_Prdt],MATCH(tbl_Ventes[[#This Row],[Produit]],tbl_ProduitsRef[Produit],0)), "" ) -> PDJ005 | E3: 350 | F3: =IFERROR( INDEX(tbl_ProduitsRef[Prix Menu],MATCH(tbl_Ventes[[#This Row],[Produit]],tbl_ProduitsRef[Produit],0)), "" ) -> 54 | G3: =tbl_Ventes[[#This Row],[Qté Vendue]] * IFERROR(_xlfn.XLOOKUP(tbl_Ventes[[#This Row],[Cde_Prdt]], tbl_Produits[Cde_Prdt], tbl_Produits[Prix Menu]), 0) -> 18900 | H3: =IFERROR(_xlfn.XLOOKUP(tbl_Ventes[[#This Row],[Cde_Prdt]], tbl_Produits[Cde_Prdt], tbl_Produits[Coût Moyen Portion]), 0) -> 24.5 | I3: =tbl_Ventes[[#This Row],[Qté Vendue]] * tbl_Ventes[[#This Row],[CMP_par_portion]] -> 8575 | J3: =tbl_Ventes[[#This Row],[CA ligne]] - tbl_Ventes[[#This Row],[Coût matière ligne]] -> 10325 | K3: =IFERROR(INDEX(tbl_ProduitsRef[Famille], MATCH(tbl_Ventes[[#This Row],[Cde_Prdt]], tbl_Produits[Cde_Prdt], 0)), "") -> Petits déjeuners
A4: 45957 | B4: =IFERROR(TEXT(tbl_Ventes[[#This Row],[Date]],"mm-aaaa"),"") -> 10-2025 | C4: Merguez (nature, piquant, normal) | D4: =IFERROR( INDEX(tbl_ProduitsRef[Cde_Prdt],MATCH(tbl_Ventes[[#This Row],[Produit]],tbl_ProduitsRef[Produit],0)), "" ) -> VIA010 | E4: 400 | F4: =IFERROR( INDEX(tbl_ProduitsRef[Prix Menu],MATCH(tbl_Ventes[[#This Row],[Produit]],tbl_ProduitsRef[Produit],0)), "" ) -> 180 | G4: =tbl_Ventes[[#This Row],[Qté Vendue]] * IFERROR(_xlfn.XLOOKUP(tbl_Ventes[[#This Row],[Cde_Prdt]], tbl_Produits[Cde_Prdt], tbl_Produits[Prix Menu]), 0) -> 72000 | H4: =IFERROR(_xlfn.XLOOKUP(tbl_Ventes[[#This Row],[Cde_Prdt]], tbl_Produits[Cde_Prdt], tbl_Produits[Coût Moyen Portion]), 0) -> 200 | I4: =tbl_Ventes[[#This Row],[Qté Vendue]] * tbl_Ventes[[#This Row],[CMP_par_portion]] -> 80000 | J4: =tbl_Ventes[[#This Row],[CA ligne]] - tbl_Ventes[[#This Row],[Coût matière ligne]] -> -8000 | K4: =IFERROR(INDEX(tbl_ProduitsRef[Famille], MATCH(tbl_Ventes[[#This Row],[Cde_Prdt]], tbl_Produits[Cde_Prdt], 0)), "") -> Boucherie
A5: 45958 | B5: =IFERROR(TEXT(tbl_Ventes[[#This Row],[Date]],"mm-aaaa"),"") -> 10-2025 | C5: Marroccino | D5: =IFERROR( INDEX(tbl_ProduitsRef[Cde_Prdt],MATCH(tbl_Ventes[[#This Row],[Produit]],tbl_ProduitsRef[Produit],0)), "" ) -> BCH017 | E5: 51 | F5: =IFERROR( INDEX(tbl_ProduitsRef[Prix Menu],MATCH(tbl_Ventes[[#This Row],[Produit]],tbl_ProduitsRef[Produit],0)), "" ) -> 27 | G5: =tbl_Ventes[[#This Row],[Qté Vendue]] * IFERROR(_xlfn.XLOOKUP(tbl_Ventes[[#This Row],[Cde_Prdt]], tbl_Produits[Cde_Prdt], tbl_Produits[Prix Menu]), 0) -> 1377 | H5: =IFERROR(_xlfn.XLOOKUP(tbl_Ventes[[#This Row],[Cde_Prdt]], tbl_Produits[Cde_Prdt], tbl_Produits[Coût Moyen Portion]), 0) -> 19.36 | I5: =tbl_Ventes[[#This Row],[Qté Vendue]] * tbl_Ventes[[#This Row],[CMP_par_portion]] -> 987.36 | J5: =tbl_Ventes[[#This Row],[CA ligne]] - tbl_Ventes[[#This Row],[Coût matière ligne]] -> 389.64 | K5: =IFERROR(INDEX(tbl_ProduitsRef[Famille], MATCH(tbl_Ventes[[#This Row],[Cde_Prdt]], tbl_Produits[Cde_Prdt], 0)), "") -> Boissons chaudes
A6: 45959 | B6: =IFERROR(TEXT(tbl_Ventes[[#This Row],[Date]],"mm-aaaa"),"") -> 10-2025 | C6: Tajine de poulet beldi (raisins/oignons ) 1/2Kg | D6: =IFERROR( INDEX(tbl_ProduitsRef[Cde_Prdt],MATCH(tbl_Ventes[[#This Row],[Produit]],tbl_ProduitsRef[Produit],0)), "" ) -> TAJ005 | E6: 500 | F6: =IFERROR( INDEX(tbl_ProduitsRef[Prix Menu],MATCH(tbl_Ventes[[#This Row],[Produit]],tbl_ProduitsRef[Produit],0)), "" ) -> 105 | G6: =tbl_Ventes[[#This Row],[Qté Vendue]] * IFERROR(_xlfn.XLOOKUP(tbl_Ventes[[#This Row],[Cde_Prdt]], tbl_Produits[Cde_Prdt], tbl_Produits[Prix Menu]), 0) -> 52500 | H6: =IFERROR(_xlfn.XLOOKUP(tbl_Ventes[[#This Row],[Cde_Prdt]], tbl_Produits[Cde_Prdt], tbl_Produits[Coût Moyen Portion]), 0) -> 35.84 | I6: =tbl_Ventes[[#This Row],[Qté Vendue]] * tbl_Ventes[[#This Row],[CMP_par_portion]] -> 17920 | J6: =tbl_Ventes[[#This Row],[CA ligne]] - tbl_Ventes[[#This Row],[Coût matière ligne]] -> 34580 | K6: =IFERROR(INDEX(tbl_ProduitsRef[Famille], MATCH(tbl_Ventes[[#This Row],[Cde_Prdt]], tbl_Produits[Cde_Prdt], 0)), "") -> Tajines & Coin marocain
A7: 45960 | B7: =IFERROR(TEXT(tbl_Ventes[[#This Row],[Date]],"mm-aaaa"),"") -> 10-2025 | C7: Marroccino | D7: =IFERROR( INDEX(tbl_ProduitsRef[Cde_Prdt],MATCH(tbl_Ventes[[#This Row],[Produit]],tbl_ProduitsRef[Produit],0)), "" ) -> BCH017 | E7: 800 | F7: =IFERROR( INDEX(tbl_ProduitsRef[Prix Menu],MATCH(tbl_Ventes[[#This Row],[Produit]],tbl_ProduitsRef[Produit],0)), "" ) -> 27 | G7: =tbl_Ventes[[#This Row],[Qté Vendue]] * IFERROR(_xlfn.XLOOKUP(tbl_Ventes[[#This Row],[Cde_Prdt]], tbl_Produits[Cde_Prdt], tbl_Produits[Prix Menu]), 0) -> 21600 | H7: =IFERROR(_xlfn.XLOOKUP(tbl_Ventes[[#This Row],[Cde_Prdt]], tbl_Produits[Cde_Prdt], tbl_Produits[Coût Moyen Portion]), 0) -> 19.36 | I7: =tbl_Ventes[[#This Row],[Qté Vendue]] * tbl_Ventes[[#This Row],[CMP_par_portion]] -> 15488 | J7: =tbl_Ventes[[#This Row],[CA ligne]] - tbl_Ventes[[#This Row],[Coût matière ligne]] -> 6112 | K7: =IFERROR(INDEX(tbl_ProduitsRef[Famille], MATCH(tbl_Ventes[[#This Row],[Cde_Prdt]], tbl_Produits[Cde_Prdt], 0)), "") -> Boissons chaudes
A8: 45961 | B8: =IFERROR(TEXT(tbl_Ventes[[#This Row],[Date]],"mm-aaaa"),"") -> 10-2025 | C8: Tajine de poulet beldi (raisins/oignons ) 1/2Kg | D8: =IFERROR( INDEX(tbl_ProduitsRef[Cde_Prdt],MATCH(tbl_Ventes[[#This Row],[Produit]],tbl_ProduitsRef[Produit],0)), "" ) -> TAJ005 | E8: 800 | F8: =IFERROR( INDEX(tbl_ProduitsRef[Prix Menu],MATCH(tbl_Ventes[[#This Row],[Produit]],tbl_ProduitsRef[Produit],0)), "" ) -> 105 | G8: =tbl_Ventes[[#This Row],[Qté Vendue]] * IFERROR(_xlfn.XLOOKUP(tbl_Ventes[[#This Row],[Cde_Prdt]], tbl_Produits[Cde_Prdt], tbl_Produits[Prix Menu]), 0) -> 84000 | H8: =IFERROR(_xlfn.XLOOKUP(tbl_Ventes[[#This Row],[Cde_Prdt]], tbl_Produits[Cde_Prdt], tbl_Produits[Coût Moyen Portion]), 0) -> 35.84 | I8: =tbl_Ventes[[#This Row],[Qté Vendue]] * tbl_Ventes[[#This Row],[CMP_par_portion]] -> 28672 | J8: =tbl_Ventes[[#This Row],[CA ligne]] - tbl_Ventes[[#This Row],[Coût matière ligne]] -> 55328 | K8: =IFERROR(INDEX(tbl_ProduitsRef[Famille], MATCH(tbl_Ventes[[#This Row],[Cde_Prdt]], tbl_Produits[Cde_Prdt], 0)), "") -> Tajines & Coin marocain
A9: 45936 | B9: =IFERROR(TEXT(tbl_Ventes[[#This Row],[Date]],"mm-aaaa"),"") -> 10-2025 | C9: Tajine de poulet beldi (citron confit) 1Kg | D9: =IFERROR( INDEX(tbl_ProduitsRef[Cde_Prdt],MATCH(tbl_Ventes[[#This Row],[Produit]],tbl_ProduitsRef[Produit],0)), "" ) -> TAJ008 | E9: 900 | F9: =IFERROR( INDEX(tbl_ProduitsRef[Prix Menu],MATCH(tbl_Ventes[[#This Row],[Produit]],tbl_ProduitsRef[Produit],0)), "" ) -> 210 | G9: =tbl_Ventes[[#This Row],[Qté Vendue]] * IFERROR(_xlfn.XLOOKUP(tbl_Ventes[[#This Row],[Cde_Prdt]], tbl_Produits[Cde_Prdt], tbl_Produits[Prix Menu]), 0) -> 189000 | H9: =IFERROR(_xlfn.XLOOKUP(tbl_Ventes[[#This Row],[Cde_Prdt]], tbl_Produits[Cde_Prdt], tbl_Produits[Coût Moyen Portion]), 0) -> 73.7 | I9: =tbl_Ventes[[#This Row],[Qté Vendue]] * tbl_Ventes[[#This Row],[CMP_par_portion]] -> 66330 | J9: =tbl_Ventes[[#This Row],[CA ligne]] - tbl_Ventes[[#This Row],[Coût matière ligne]] -> 122670 | K9: =IFERROR(INDEX(tbl_ProduitsRef[Famille], MATCH(tbl_Ventes[[#This Row],[Cde_Prdt]], tbl_Produits[Cde_Prdt], 0)), "") -> Tajines & Coin marocain
A10: 45937 | B10: =IFERROR(TEXT(tbl_Ventes[[#This Row],[Date]],"mm-aaaa"),"") -> 10-2025 | C10: Milkshakes Noisette | D10: =IFERROR( INDEX(tbl_ProduitsRef[Cde_Prdt],MATCH(tbl_Ventes[[#This Row],[Produit]],tbl_ProduitsRef[Produit],0)), "" ) -> MKS006 | E10: 80 | F10: =IFERROR( INDEX(tbl_ProduitsRef[Prix Menu],MATCH(tbl_Ventes[[#This Row],[Produit]],tbl_ProduitsRef[Produit],0)), "" ) -> 35 | G10: =tbl_Ventes[[#This Row],[Qté Vendue]] * IFERROR(_xlfn.XLOOKUP(tbl_Ventes[[#This Row],[Cde_Prdt]], tbl_Produits[Cde_Prdt], tbl_Produits[Prix Menu]), 0) -> 2800 | H10: =IFERROR(_xlfn.XLOOKUP(tbl_Ventes[[#This Row],[Cde_Prdt]], tbl_Produits[Cde_Prdt], tbl_Produits[Coût Moyen Portion]), 0) -> 17.3 | I10: =tbl_Ventes[[#This Row],[Qté Vendue]] * tbl_Ventes[[#This Row],[CMP_par_portion]] -> 1384 | J10: =tbl_Ventes[[#This Row],[CA ligne]] - tbl_Ventes[[#This Row],[Coût matière ligne]] -> 1416 | K10: =IFERROR(INDEX(tbl_ProduitsRef[Famille], MATCH(tbl_Ventes[[#This Row],[Cde_Prdt]], tbl_Produits[Cde_Prdt], 0)), "") -> Milkshakes
A11: 45938 | B11: =IFERROR(TEXT(tbl_Ventes[[#This Row],[Date]],"mm-aaaa"),"") -> 10-2025 | C11: Merguez (nature, piquant, normal) | D11: =IFERROR( INDEX(tbl_ProduitsRef[Cde_Prdt],MATCH(tbl_Ventes[[#This Row],[Produit]],tbl_ProduitsRef[Produit],0)), "" ) -> VIA010 | E11: 150 | F11: =IFERROR( INDEX(tbl_ProduitsRef[Prix Menu],MATCH(tbl_Ventes[[#This Row],[Produit]],tbl_ProduitsRef[Produit],0)), "" ) -> 180 | G11: =tbl_Ventes[[#This Row],[Qté Vendue]] * IFERROR(_xlfn.XLOOKUP(tbl_Ventes[[#This Row],[Cde_Prdt]], tbl_Produits[Cde_Prdt], tbl_Produits[Prix Menu]), 0) -> 27000 | H11: =IFERROR(_xlfn.XLOOKUP(tbl_Ventes[[#This Row],[Cde_Prdt]], tbl_Produits[Cde_Prdt], tbl_Produits[Coût Moyen Portion]), 0) -> 200 | I11: =tbl_Ventes[[#This Row],[Qté Vendue]] * tbl_Ventes[[#This Row],[CMP_par_portion]] -> 30000 | J11: =tbl_Ventes[[#This Row],[CA ligne]] - tbl_Ventes[[#This Row],[Coût matière ligne]] -> -3000 | K11: =IFERROR(INDEX(tbl_ProduitsRef[Famille], MATCH(tbl_Ventes[[#This Row],[Cde_Prdt]], tbl_Produits[Cde_Prdt], 0)), "") -> Boucherie
A12: 45939 | B12: =IFERROR(TEXT(tbl_Ventes[[#This Row],[Date]],"mm-aaaa"),"") -> 10-2025 | C12: Entrecôte de veau | D12: =IFERROR( INDEX(tbl_ProduitsRef[Cde_Prdt],MATCH(tbl_Ventes[[#This Row],[Produit]],tbl_ProduitsRef[Produit],0)), "" ) -> VIA006 | E12: 50 | F12: =IFERROR( INDEX(tbl_ProduitsRef[Prix Menu],MATCH(tbl_Ventes[[#This Row],[Produit]],tbl_ProduitsRef[Produit],0)), "" ) -> 190 | G12: =tbl_Ventes[[#This Row],[Qté Vendue]] * IFERROR(_xlfn.XLOOKUP(tbl_Ventes[[#This Row],[Cde_Prdt]], tbl_Produits[Cde_Prdt], tbl_Produits[Prix Menu]), 0) -> 9500 | H12: =IFERROR(_xlfn.XLOOKUP(tbl_Ventes[[#This Row],[Cde_Prdt]], tbl_Produits[Cde_Prdt], tbl_Produits[Coût Moyen Portion]), 0) -> 300 | I12: =tbl_Ventes[[#This Row],[Qté Vendue]] * tbl_Ventes[[#This Row],[CMP_par_portion]] -> 15000 | J12: =tbl_Ventes[[#This Row],[CA ligne]] - tbl_Ventes[[#This Row],[Coût matière ligne]] -> -5500 | K12: =IFERROR(INDEX(tbl_ProduitsRef[Famille], MATCH(tbl_Ventes[[#This Row],[Cde_Prdt]], tbl_Produits[Cde_Prdt], 0)), "") -> Boucherie
A13: 45940 | B13: =IFERROR(TEXT(tbl_Ventes[[#This Row],[Date]],"mm-aaaa"),"") -> 10-2025 | C13: Viennoiserie G | D13: =IFERROR( INDEX(tbl_ProduitsRef[Cde_Prdt],MATCH(tbl_Ventes[[#This Row],[Produit]],tbl_ProduitsRef[Produit],0)), "" ) -> SUP005 | E13: 88 | F13: =IFERROR( INDEX(tbl_ProduitsRef[Prix Menu],MATCH(tbl_Ventes[[#This Row],[Produit]],tbl_ProduitsRef[Produit],0)), "" ) -> 9 | G13: =tbl_Ventes[[#This Row],[Qté Vendue]] * IFERROR(_xlfn.XLOOKUP(tbl_Ventes[[#This Row],[Cde_Prdt]], tbl_Produits[Cde_Prdt], tbl_Produits[Prix Menu]), 0) -> 792 | H13: =IFERROR(_xlfn.XLOOKUP(tbl_Ventes[[#This Row],[Cde_Prdt]], tbl_Produits[Cde_Prdt], tbl_Produits[Coût Moyen Portion]), 0) -> 7 | I13: =tbl_Ventes[[#This Row],[Qté Vendue]] * tbl_Ventes[[#This Row],[CMP_par_portion]] -> 616 | J13: =tbl_Ventes[[#This Row],[CA ligne]] - tbl_Ventes[[#This Row],[Coût matière ligne]] -> 176 | K13: =IFERROR(INDEX(tbl_ProduitsRef[Famille], MATCH(tbl_Ventes[[#This Row],[Cde_Prdt]], tbl_Produits[Cde_Prdt], 0)), "") -> Suppléments
... A16: 45943 | B16: =IFERROR(TEXT(tbl_Ventes[[#This Row],[Date]],"mm-aaaa"),"") -> 10-2025 | C16: Marroccino | D16: =IFERROR( INDEX(tbl_ProduitsRef[Cde_Prdt],MATCH(tbl_Ventes[[#This Row],[Produit]],tbl_ProduitsRef[Produit],0)), "" ) -> BCH017 | E16: 10 | F16: =IFERROR( INDEX(tbl_ProduitsRef[Prix Menu],MATCH(tbl_Ventes[[#This Row],[Produit]],tbl_ProduitsRef[Produit],0)), "" ) -> 27 | G16: =tbl_Ventes[[#This Row],[Qté Vendue]] * IFERROR(_xlfn.XLOOKUP(tbl_Ventes[[#This Row],[Cde_Prdt]], tbl_Produits[Cde_Prdt], tbl_Produits[Prix Menu]), 0) -> 270 | H16: =IFERROR(_xlfn.XLOOKUP(tbl_Ventes[[#This Row],[Cde_Prdt]], tbl_Produits[Cde_Prdt], tbl_Produits[Coût Moyen Portion]), 0) -> 19.36 | I16: =tbl_Ventes[[#This Row],[Qté Vendue]] * tbl_Ventes[[#This Row],[CMP_par_portion]] -> 193.6 | J16: =tbl_Ventes[[#This Row],[CA ligne]] - tbl_Ventes[[#This Row],[Coût matière ligne]] -> 76.4 | K16: =IFERROR(INDEX(tbl_ProduitsRef[Famille], MATCH(tbl_Ventes[[#This Row],[Cde_Prdt]], tbl_Produits[Cde_Prdt], 0)), "") -> Boissons chaudes
A17: 45944 | B17: =IFERROR(TEXT(tbl_Ventes[[#This Row],[Date]],"mm-aaaa"),"") -> 10-2025 | C17: Tajine de poulet beldi (raisins/oignons ) 1/2Kg | D17: =IFERROR( INDEX(tbl_ProduitsRef[Cde_Prdt],MATCH(tbl_Ventes[[#This Row],[Produit]],tbl_ProduitsRef[Produit],0)), "" ) -> TAJ005 | E17: 20 | F17: =IFERROR( INDEX(tbl_ProduitsRef[Prix Menu],MATCH(tbl_Ventes[[#This Row],[Produit]],tbl_ProduitsRef[Produit],0)), "" ) -> 105 | G17: =tbl_Ventes[[#This Row],[Qté Vendue]] * IFERROR(_xlfn.XLOOKUP(tbl_Ventes[[#This Row],[Cde_Prdt]], tbl_Produits[Cde_Prdt], tbl_Produits[Prix Menu]), 0) -> 2100 | H17: =IFERROR(_xlfn.XLOOKUP(tbl_Ventes[[#This Row],[Cde_Prdt]], tbl_Produits[Cde_Prdt], tbl_Produits[Coût Moyen Portion]), 0) -> 35.84 | I17: =tbl_Ventes[[#This Row],[Qté Vendue]] * tbl_Ventes[[#This Row],[CMP_par_portion]] -> 716.8 | J17: =tbl_Ventes[[#This Row],[CA ligne]] - tbl_Ventes[[#This Row],[Coût matière ligne]] -> 1383.2 | K17: =IFERROR(INDEX(tbl_ProduitsRef[Famille], MATCH(tbl_Ventes[[#This Row],[Cde_Prdt]], tbl_Produits[Cde_Prdt], 0)), "") -> Tajines & Coin marocain | O17: Ca Journalier
A18: 45945 | B18: =IFERROR(TEXT(tbl_Ventes[[#This Row],[Date]],"mm-aaaa"),"") -> 10-2025 | C18: Marroccino | D18: =IFERROR( INDEX(tbl_ProduitsRef[Cde_Prdt],MATCH(tbl_Ventes[[#This Row],[Produit]],tbl_ProduitsRef[Produit],0)), "" ) -> BCH017 | E18: 33 | F18: =IFERROR( INDEX(tbl_ProduitsRef[Prix Menu],MATCH(tbl_Ventes[[#This Row],[Produit]],tbl_ProduitsRef[Produit],0)), "" ) -> 27 | G18: =tbl_Ventes[[#This Row],[Qté Vendue]] * IFERROR(_xlfn.XLOOKUP(tbl_Ventes[[#This Row],[Cde_Prdt]], tbl_Produits[Cde_Prdt], tbl_Produits[Prix Menu]), 0) -> 891 | H18: =IFERROR(_xlfn.XLOOKUP(tbl_Ventes[[#This Row],[Cde_Prdt]], tbl_Produits[Cde_Prdt], tbl_Produits[Coût Moyen Portion]), 0) -> 19.36 | I18: =tbl_Ventes[[#This Row],[Qté Vendue]] * tbl_Ventes[[#This Row],[CMP_par_portion]] -> 638.88 | J18: =tbl_Ventes[[#This Row],[CA ligne]] - tbl_Ventes[[#This Row],[Coût matière ligne]] -> 252.12 | K18: =IFERROR(INDEX(tbl_ProduitsRef[Famille], MATCH(tbl_Ventes[[#This Row],[Cde_Prdt]], tbl_Produits[Cde_Prdt], 0)), "") -> Boissons chaudes | O18: =SUMIFS(tbl_Ventes[CA ligne],tbl_Ventes[Date],A2) -> 2922
A19: 45946 | B19: =IFERROR(TEXT(tbl_Ventes[[#This Row],[Date]],"mm-aaaa"),"") -> 10-2025 | C19: Tajine de poulet beldi (raisins/oignons ) 1/2Kg | D19: =IFERROR( INDEX(tbl_ProduitsRef[Cde_Prdt],MATCH(tbl_Ventes[[#This Row],[Produit]],tbl_ProduitsRef[Produit],0)), "" ) -> TAJ005 | E19: 25 | F19: =IFERROR( INDEX(tbl_ProduitsRef[Prix Menu],MATCH(tbl_Ventes[[#This Row],[Produit]],tbl_ProduitsRef[Produit],0)), "" ) -> 105 | G19: =tbl_Ventes[[#This Row],[Qté Vendue]] * IFERROR(_xlfn.XLOOKUP(tbl_Ventes[[#This Row],[Cde_Prdt]], tbl_Produits[Cde_Prdt], tbl_Produits[Prix Menu]), 0) -> 2625 | H19: =IFERROR(_xlfn.XLOOKUP(tbl_Ventes[[#This Row],[Cde_Prdt]], tbl_Produits[Cde_Prdt], tbl_Produits[Coût Moyen Portion]), 0) -> 35.84 | I19: =tbl_Ventes[[#This Row],[Qté Vendue]] * tbl_Ventes[[#This Row],[CMP_par_portion]] -> 896 | J19: =tbl_Ventes[[#This Row],[CA ligne]] - tbl_Ventes[[#This Row],[Coût matière ligne]] -> 1729 | K19: =IFERROR(INDEX(tbl_ProduitsRef[Famille], MATCH(tbl_Ventes[[#This Row],[Cde_Prdt]], tbl_Produits[Cde_Prdt], 0)), "") -> Tajines & Coin marocain | O19: CA Mansuel
A20: 45947 | B20: =IFERROR(TEXT(tbl_Ventes[[#This Row],[Date]],"mm-aaaa"),"") -> 10-2025 | C20: Tajine de poulet beldi (citron confit) 1Kg | D20: =IFERROR( INDEX(tbl_ProduitsRef[Cde_Prdt],MATCH(tbl_Ventes[[#This Row],[Produit]],tbl_ProduitsRef[Produit],0)), "" ) -> TAJ008 | E20: 150 | F20: =IFERROR( INDEX(tbl_ProduitsRef[Prix Menu],MATCH(tbl_Ventes[[#This Row],[Produit]],tbl_ProduitsRef[Produit],0)), "" ) -> 210 | G20: =tbl_Ventes[[#This Row],[Qté Vendue]] * IFERROR(_xlfn.XLOOKUP(tbl_Ventes[[#This Row],[Cde_Prdt]], tbl_Produits[Cde_Prdt], tbl_Produits[Prix Menu]), 0) -> 31500 | H20: =IFERROR(_xlfn.XLOOKUP(tbl_Ventes[[#This Row],[Cde_Prdt]], tbl_Produits[Cde_Prdt], tbl_Produits[Coût Moyen Portion]), 0) -> 73.7 | I20: =tbl_Ventes[[#This Row],[Qté Vendue]] * tbl_Ventes[[#This Row],[CMP_par_portion]] -> 11055 | J20: =tbl_Ventes[[#This Row],[CA ligne]] - tbl_Ventes[[#This Row],[Coût matière ligne]] -> 20445 | K20: =IFERROR(INDEX(tbl_ProduitsRef[Famille], MATCH(tbl_Ventes[[#This Row],[Cde_Prdt]], tbl_Produits[Cde_Prdt], 0)), "") -> Tajines & Coin marocain | O20: =SUMIFS(tbl_Ventes[CA ligne],tbl_Ventes[Mois],"2025-12") -> 0
A21: 45948 | B21: =IFERROR(TEXT(tbl_Ventes[[#This Row],[Date]],"mm-aaaa"),"") -> 10-2025 | C21: Milkshakes Noisette | D21: =IFERROR( INDEX(tbl_ProduitsRef[Cde_Prdt],MATCH(tbl_Ventes[[#This Row],[Produit]],tbl_ProduitsRef[Produit],0)), "" ) -> MKS006 | E21: 30 | F21: =IFERROR( INDEX(tbl_ProduitsRef[Prix Menu],MATCH(tbl_Ventes[[#This Row],[Produit]],tbl_ProduitsRef[Produit],0)), "" ) -> 35 | G21: =tbl_Ventes[[#This Row],[Qté Vendue]] * IFERROR(_xlfn.XLOOKUP(tbl_Ventes[[#This Row],[Cde_Prdt]], tbl_Produits[Cde_Prdt], tbl_Produits[Prix Menu]), 0) -> 1050 | H21: =IFERROR(_xlfn.XLOOKUP(tbl_Ventes[[#This Row],[Cde_Prdt]], tbl_Produits[Cde_Prdt], tbl_Produits[Coût Moyen Portion]), 0) -> 17.3 | I21: =tbl_Ventes[[#This Row],[Qté Vendue]] * tbl_Ventes[[#This Row],[CMP_par_portion]] -> 519 | J21: =tbl_Ventes[[#This Row],[CA ligne]] - tbl_Ventes[[#This Row],[Coût matière ligne]] -> 531 | K21: =IFERROR(INDEX(tbl_ProduitsRef[Famille], MATCH(tbl_Ventes[[#This Row],[Cde_Prdt]], tbl_Produits[Cde_Prdt], 0)), "") -> Milkshakes
A22: 45949 | B22: =IFERROR(TEXT(tbl_Ventes[[#This Row],[Date]],"mm-aaaa"),"") -> 10-2025 | C22: Merguez (nature, piquant, normal) | D22: =IFERROR( INDEX(tbl_ProduitsRef[Cde_Prdt],MATCH(tbl_Ventes[[#This Row],[Produit]],tbl_ProduitsRef[Produit],0)), "" ) -> VIA010 | E22: 78 | F22: =IFERROR( INDEX(tbl_ProduitsRef[Prix Menu],MATCH(tbl_Ventes[[#This Row],[Produit]],tbl_ProduitsRef[Produit],0)), "" ) -> 180 | G22: =tbl_Ventes[[#This Row],[Qté Vendue]] * IFERROR(_xlfn.XLOOKUP(tbl_Ventes[[#This Row],[Cde_Prdt]], tbl_Produits[Cde_Prdt], tbl_Produits[Prix Menu]), 0) -> 14040 | H22: =IFERROR(_xlfn.XLOOKUP(tbl_Ventes[[#This Row],[Cde_Prdt]], tbl_Produits[Cde_Prdt], tbl_Produits[Coût Moyen Portion]), 0) -> 200 | I22: =tbl_Ventes[[#This Row],[Qté Vendue]] * tbl_Ventes[[#This Row],[CMP_par_portion]] -> 15600 | J22: =tbl_Ventes[[#This Row],[CA ligne]] - tbl_Ventes[[#This Row],[Coût matière ligne]] -> -1560 | K22: =IFERROR(INDEX(tbl_ProduitsRef[Famille], MATCH(tbl_Ventes[[#This Row],[Cde_Prdt]], tbl_Produits[Cde_Prdt], 0)), "") -> Boucherie
A23: 45950 | B23: =IFERROR(TEXT(tbl_Ventes[[#This Row],[Date]],"mm-aaaa"),"") -> 10-2025 | C23: Omelette aux crevettes | D23: =IFERROR( INDEX(tbl_ProduitsRef[Cde_Prdt],MATCH(tbl_Ventes[[#This Row],[Produit]],tbl_ProduitsRef[Produit],0)), "" ) -> OME001 | E23: 69 | F23: =IFERROR( INDEX(tbl_ProduitsRef[Prix Menu],MATCH(tbl_Ventes[[#This Row],[Produit]],tbl_ProduitsRef[Produit],0)), "" ) -> 35 | G23: =tbl_Ventes[[#This Row],[Qté Vendue]] * IFERROR(_xlfn.XLOOKUP(tbl_Ventes[[#This Row],[Cde_Prdt]], tbl_Produits[Cde_Prdt], tbl_Produits[Prix Menu]), 0) -> 2415 | H23: =IFERROR(_xlfn.XLOOKUP(tbl_Ventes[[#This Row],[Cde_Prdt]], tbl_Produits[Cde_Prdt], tbl_Produits[Coût Moyen Portion]), 0) -> 9.09 | I23: =tbl_Ventes[[#This Row],[Qté Vendue]] * tbl_Ventes[[#This Row],[CMP_par_portion]] -> 627.21 | J23: =tbl_Ventes[[#This Row],[CA ligne]] - tbl_Ventes[[#This Row],[Coût matière ligne]] -> 1787.79 | K23: =IFERROR(INDEX(tbl_ProduitsRef[Famille], MATCH(tbl_Ventes[[#This Row],[Cde_Prdt]], tbl_Produits[Cde_Prdt], 0)), "") -> Œufs & Omelettes
A24: 45951 | B24: =IFERROR(TEXT(tbl_Ventes[[#This Row],[Date]],"mm-aaaa"),"") -> 10-2025 | C24: Omelette maison | D24: =IFERROR( INDEX(tbl_ProduitsRef[Cde_Prdt],MATCH(tbl_Ventes[[#This Row],[Produit]],tbl_ProduitsRef[Produit],0)), "" ) -> OME003 | E24: 33 | F24: =IFERROR( INDEX(tbl_ProduitsRef[Prix Menu],MATCH(tbl_Ventes[[#This Row],[Produit]],tbl_ProduitsRef[Produit],0)), "" ) -> 22 | G24: =tbl_Ventes[[#This Row],[Qté Vendue]] * IFERROR(_xlfn.XLOOKUP(tbl_Ventes[[#This Row],[Cde_Prdt]], tbl_Produits[Cde_Prdt], tbl_Produits[Prix Menu]), 0) -> 726 | H24: =IFERROR(_xlfn.XLOOKUP(tbl_Ventes[[#This Row],[Cde_Prdt]], tbl_Produits[Cde_Prdt], tbl_Produits[Coût Moyen Portion]), 0) -> 20.81 | I24: =tbl_Ventes[[#This Row],[Qté Vendue]] * tbl_Ventes[[#This Row],[CMP_par_portion]] -> 686.73 | J24: =tbl_Ventes[[#This Row],[CA ligne]] - tbl_Ventes[[#This Row],[Coût matière ligne]] -> 39.27 | K24: =IFERROR(INDEX(tbl_ProduitsRef[Famille], MATCH(tbl_Ventes[[#This Row],[Cde_Prdt]], tbl_Produits[Cde_Prdt], 0)), "") -> Œufs & Omelettes
A25: 45952 | B25: =IFERROR(TEXT(tbl_Ventes[[#This Row],[Date]],"mm-aaaa"),"") -> 10-2025 | C25: Omelette végétarienne | D25: =IFERROR( INDEX(tbl_ProduitsRef[Cde_Prdt],MATCH(tbl_Ventes[[#This Row],[Produit]],tbl_ProduitsRef[Produit],0)), "" ) -> OME004 | E25: 12 | F25: =IFERROR( INDEX(tbl_ProduitsRef[Prix Menu],MATCH(tbl_Ventes[[#This Row],[Produit]],tbl_ProduitsRef[Produit],0)), "" ) -> 20 | G25: =tbl_Ventes[[#This Row],[Qté Vendue]] * IFERROR(_xlfn.XLOOKUP(tbl_Ventes[[#This Row],[Cde_Prdt]], tbl_Produits[Cde_Prdt], tbl_Produits[Prix Menu]), 0) -> 240 | H25: =IFERROR(_xlfn.XLOOKUP(tbl_Ventes[[#This Row],[Cde_Prdt]], tbl_Produits[Cde_Prdt], tbl_Produits[Coût Moyen Portion]), 0) -> 13.49 | I25: =tbl_Ventes[[#This Row],[Qté Vendue]] * tbl_Ventes[[#This Row],[CMP_par_portion]] -> 161.88 | J25: =tbl_Ventes[[#This Row],[CA ligne]] - tbl_Ventes[[#This Row],[Coût matière ligne]] -> 78.12 | K25: =IFERROR(INDEX(tbl_ProduitsRef[Famille], MATCH(tbl_Ventes[[#This Row],[Cde_Prdt]], tbl_Produits[Cde_Prdt], 0)), "") -> Œufs & Omelettes
A26: 45953 | B26: =IFERROR(TEXT(tbl_Ventes[[#This Row],[Date]],"mm-aaaa"),"") -> 10-2025 | C26: Omelette au fromage | D26: =IFERROR( INDEX(tbl_ProduitsRef[Cde_Prdt],MATCH(tbl_Ventes[[#This Row],[Produit]],tbl_ProduitsRef[Produit],0)), "" ) -> OME006 | E26: 11 | F26: =IFERROR( INDEX(tbl_ProduitsRef[Prix Menu],MATCH(tbl_Ventes[[#This Row],[Produit]],tbl_ProduitsRef[Produit],0)), "" ) -> 15 | G26: =tbl_Ventes[[#This Row],[Qté Vendue]] * IFERROR(_xlfn.XLOOKUP(tbl_Ventes[[#This Row],[Cde_Prdt]], tbl_Produits[Cde_Prdt], tbl_Produits[Prix Menu]), 0) -> 165 | H26: =IFERROR(_xlfn.XLOOKUP(tbl_Ventes[[#This Row],[Cde_Prdt]], tbl_Produits[Cde_Prdt], tbl_Produits[Coût Moyen Portion]), 0) -> 12.79 | I26: =tbl_Ventes[[#This Row],[Qté Vendue]] * tbl_Ventes[[#This Row],[CMP_par_portion]] -> 140.69 | J26: =tbl_Ventes[[#This Row],[CA ligne]] - tbl_Ventes[[#This Row],[Coût matière ligne]] -> 24.31 | K26: =IFERROR(INDEX(tbl_ProduitsRef[Famille], MATCH(tbl_Ventes[[#This Row],[Cde_Prdt]], tbl_Produits[Cde_Prdt], 0)), "") -> Œufs & Omelettes
A27: 45954 | B27: =IFERROR(TEXT(tbl_Ventes[[#This Row],[Date]],"mm-aaaa"),"") -> 10-2025 | C27: Marroccino | D27: =IFERROR( INDEX(tbl_ProduitsRef[Cde_Prdt],MATCH(tbl_Ventes[[#This Row],[Produit]],tbl_ProduitsRef[Produit],0)), "" ) -> BCH017 | E27: 10 | F27: =IFERROR( INDEX(tbl_ProduitsRef[Prix Menu],MATCH(tbl_Ventes[[#This Row],[Produit]],tbl_ProduitsRef[Produit],0)), "" ) -> 27 | G27: =tbl_Ventes[[#This Row],[Qté Vendue]] * IFERROR(_xlfn.XLOOKUP(tbl_Ventes[[#This Row],[Cde_Prdt]], tbl_Produits[Cde_Prdt], tbl_Produits[Prix Menu]), 0) -> 270 | H27: =IFERROR(_xlfn.XLOOKUP(tbl_Ventes[[#This Row],[Cde_Prdt]], tbl_Produits[Cde_Prdt], tbl_Produits[Coût Moyen Portion]), 0) -> 19.36 | I27: =tbl_Ventes[[#This Row],[Qté Vendue]] * tbl_Ventes[[#This Row],[CMP_par_portion]] -> 193.6 | J27: =tbl_Ventes[[#This Row],[CA ligne]] - tbl_Ventes[[#This Row],[Coût matière ligne]] -> 76.4 | K27: =IFERROR(INDEX(tbl_ProduitsRef[Famille], MATCH(tbl_Ventes[[#This Row],[Cde_Prdt]], tbl_Produits[Cde_Prdt], 0)), "") -> Boissons chaudes
A28: 45955 | B28: =IFERROR(TEXT(tbl_Ventes[[#This Row],[Date]],"mm-aaaa"),"") -> 10-2025 | C28: Tajine de poulet beldi (raisins/oignons ) 1/2Kg | D28: =IFERROR( INDEX(tbl_ProduitsRef[Cde_Prdt],MATCH(tbl_Ventes[[#This Row],[Produit]],tbl_ProduitsRef[Produit],0)), "" ) -> TAJ005 | E28: 25 | F28: =IFERROR( INDEX(tbl_ProduitsRef[Prix Menu],MATCH(tbl_Ventes[[#This Row],[Produit]],tbl_ProduitsRef[Produit],0)), "" ) -> 105 | G28: =tbl_Ventes[[#This Row],[Qté Vendue]] * IFERROR(_xlfn.XLOOKUP(tbl_Ventes[[#This Row],[Cde_Prdt]], tbl_Produits[Cde_Prdt], tbl_Produits[Prix Menu]), 0) -> 2625 | H28: =IFERROR(_xlfn.XLOOKUP(tbl_Ventes[[#This Row],[Cde_Prdt]], tbl_Produits[Cde_Prdt], tbl_Produits[Coût Moyen Portion]), 0) -> 35.84 | I28: =tbl_Ventes[[#This Row],[Qté Vendue]] * tbl_Ventes[[#This Row],[CMP_par_portion]] -> 896 | J28: =tbl_Ventes[[#This Row],[CA ligne]] - tbl_Ventes[[#This Row],[Coût matière ligne]] -> 1729 | K28: =IFERROR(INDEX(tbl_ProduitsRef[Famille], MATCH(tbl_Ventes[[#This Row],[Cde_Prdt]], tbl_Produits[Cde_Prdt], 0)), "") -> Tajines & Coin marocain
A29: 45956 | B29: =IFERROR(TEXT(tbl_Ventes[[#This Row],[Date]],"mm-aaaa"),"") -> 10-2025 | C29: Marroccino | D29: =IFERROR( INDEX(tbl_ProduitsRef[Cde_Prdt],MATCH(tbl_Ventes[[#This Row],[Produit]],tbl_ProduitsRef[Produit],0)), "" ) -> BCH017 | E29: 30 | F29: =IFERROR( INDEX(tbl_ProduitsRef[Prix Menu],MATCH(tbl_Ventes[[#This Row],[Produit]],tbl_ProduitsRef[Produit],0)), "" ) -> 27 | G29: =tbl_Ventes[[#This Row],[Qté Vendue]] * IFERROR(_xlfn.XLOOKUP(tbl_Ventes[[#This Row],[Cde_Prdt]], tbl_Produits[Cde_Prdt], tbl_Produits[Prix Menu]), 0) -> 810 | H29: =IFERROR(_xlfn.XLOOKUP(tbl_Ventes[[#This Row],[Cde_Prdt]], tbl_Produits[Cde_Prdt], tbl_Produits[Coût Moyen Portion]), 0) -> 19.36 | I29: =tbl_Ventes[[#This Row],[Qté Vendue]] * tbl_Ventes[[#This Row],[CMP_par_portion]] -> 580.8 | J29: =tbl_Ventes[[#This Row],[CA ligne]] - tbl_Ventes[[#This Row],[Coût matière ligne]] -> 229.2 | K29: =IFERROR(INDEX(tbl_ProduitsRef[Famille], MATCH(tbl_Ventes[[#This Row],[Cde_Prdt]], tbl_Produits[Cde_Prdt], 0)), "") -> Boissons chaudes
A30: 45957 | B30: =IFERROR(TEXT(tbl_Ventes[[#This Row],[Date]],"mm-aaaa"),"") -> 10-2025 | C30: Tajine de poulet beldi (raisins/oignons ) 1/2Kg | D30: =IFERROR( INDEX(tbl_ProduitsRef[Cde_Prdt],MATCH(tbl_Ventes[[#This Row],[Produit]],tbl_ProduitsRef[Produit],0)), "" ) -> TAJ005 | E30: 50 | F30: =IFERROR( INDEX(tbl_ProduitsRef[Prix Menu],MATCH(tbl_Ventes[[#This Row],[Produit]],tbl_ProduitsRef[Produit],0)), "" ) -> 105 | G30: =tbl_Ventes[[#This Row],[Qté Vendue]] * IFERROR(_xlfn.XLOOKUP(tbl_Ventes[[#This Row],[Cde_Prdt]], tbl_Produits[Cde_Prdt], tbl_Produits[Prix Menu]), 0) -> 5250 | H30: =IFERROR(_xlfn.XLOOKUP(tbl_Ventes[[#This Row],[Cde_Prdt]], tbl_Produits[Cde_Prdt], tbl_Produits[Coût Moyen Portion]), 0) -> 35.84 | I30: =tbl_Ventes[[#This Row],[Qté Vendue]] * tbl_Ventes[[#This Row],[CMP_par_portion]] -> 1792 | J30: =tbl_Ventes[[#This Row],[CA ligne]] - tbl_Ventes[[#This Row],[Coût matière ligne]] -> 3458 | K30: =IFERROR(INDEX(tbl_ProduitsRef[Famille], MATCH(tbl_Ventes[[#This Row],[Cde_Prdt]], tbl_Produits[Cde_Prdt], 0)), "") -> Tajines & Coin marocain
A31: 45958 | B31: =IFERROR(TEXT(tbl_Ventes[[#This Row],[Date]],"mm-aaaa"),"") -> 10-2025 | C31: Tajine de poulet beldi (citron confit) 1Kg | D31: =IFERROR( INDEX(tbl_ProduitsRef[Cde_Prdt],MATCH(tbl_Ventes[[#This Row],[Produit]],tbl_ProduitsRef[Produit],0)), "" ) -> TAJ008 | E31: 17 | F31: =IFERROR( INDEX(tbl_ProduitsRef[Prix Menu],MATCH(tbl_Ventes[[#This Row],[Produit]],tbl_ProduitsRef[Produit],0)), "" ) -> 210 | G31: =tbl_Ventes[[#This Row],[Qté Vendue]] * IFERROR(_xlfn.XLOOKUP(tbl_Ventes[[#This Row],[Cde_Prdt]], tbl_Produits[Cde_Prdt], tbl_Produits[Prix Menu]), 0) -> 3570 | H31: =IFERROR(_xlfn.XLOOKUP(tbl_Ventes[[#This Row],[Cde_Prdt]], tbl_Produits[Cde_Prdt], tbl_Produits[Coût Moyen Portion]), 0) -> 73.7 | I31: =tbl_Ventes[[#This Row],[Qté Vendue]] * tbl_Ventes[[#This Row],[CMP_par_portion]] -> 1252.9 | J31: =tbl_Ventes[[#This Row],[CA ligne]] - tbl_Ventes[[#This Row],[Coût matière ligne]] -> 2317.1 | K31: =IFERROR(INDEX(tbl_ProduitsRef[Famille], MATCH(tbl_Ventes[[#This Row],[Cde_Prdt]], tbl_Produits[Cde_Prdt], 0)), "") -> Tajines & Coin marocain
A32: 45959 | B32: =IFERROR(TEXT(tbl_Ventes[[#This Row],[Date]],"mm-aaaa"),"") -> 10-2025 | C32: Milkshakes Noisette | D32: =IFERROR( INDEX(tbl_ProduitsRef[Cde_Prdt],MATCH(tbl_Ventes[[#This Row],[Produit]],tbl_ProduitsRef[Produit],0)), "" ) -> MKS006 | E32: 90 | F32: =IFERROR( INDEX(tbl_ProduitsRef[Prix Menu],MATCH(tbl_Ventes[[#This Row],[Produit]],tbl_ProduitsRef[Produit],0)), "" ) -> 35 | G32: =tbl_Ventes[[#This Row],[Qté Vendue]] * IFERROR(_xlfn.XLOOKUP(tbl_Ventes[[#This Row],[Cde_Prdt]], tbl_Produits[Cde_Prdt], tbl_Produits[Prix Menu]), 0) -> 3150 | H32: =IFERROR(_xlfn.XLOOKUP(tbl_Ventes[[#This Row],[Cde_Prdt]], tbl_Produits[Cde_Prdt], tbl_Produits[Coût Moyen Portion]), 0) -> 17.3 | I32: =tbl_Ventes[[#This Row],[Qté Vendue]] * tbl_Ventes[[#This Row],[CMP_par_portion]] -> 1557 | J32: =tbl_Ventes[[#This Row],[CA ligne]] - tbl_Ventes[[#This Row],[Coût matière ligne]] -> 1593 | K32: =IFERROR(INDEX(tbl_ProduitsRef[Famille], MATCH(tbl_Ventes[[#This Row],[Cde_Prdt]], tbl_Produits[Cde_Prdt], 0)), "") -> Milkshakes
... A70: 46016 | B70: =IFERROR(TEXT(tbl_Ventes[[#This Row],[Date]],"mm-aaaa"),"") -> 12-2025 | C70: Amlou amande | D70: =IFERROR( INDEX(tbl_ProduitsRef[Cde_Prdt],MATCH(tbl_Ventes[[#This Row],[Produit]],tbl_ProduitsRef[Produit],0)), "" ) -> SUP002 | E70: 150 | F70: =IFERROR( INDEX(tbl_ProduitsRef[Prix Menu],MATCH(tbl_Ventes[[#This Row],[Produit]],tbl_ProduitsRef[Produit],0)), "" ) -> 12 | G70: =tbl_Ventes[[#This Row],[Qté Vendue]] * IFERROR(_xlfn.XLOOKUP(tbl_Ventes[[#This Row],[Cde_Prdt]], tbl_Produits[Cde_Prdt], tbl_Produits[Prix Menu]), 0) -> 1800 | H70: =IFERROR(_xlfn.XLOOKUP(tbl_Ventes[[#This Row],[Cde_Prdt]], tbl_Produits[Cde_Prdt], tbl_Produits[Coût Moyen Portion]), 0) -> 60 | I70: =tbl_Ventes[[#This Row],[Qté Vendue]] * tbl_Ventes[[#This Row],[CMP_par_portion]] -> 9000 | J70: =tbl_Ventes[[#This Row],[CA ligne]] - tbl_Ventes[[#This Row],[Coût matière ligne]] -> -7200 | K70: =IFERROR(INDEX(tbl_ProduitsRef[Famille], MATCH(tbl_Ventes[[#This Row],[Cde_Prdt]], tbl_Produits[Cde_Prdt], 0)), "") -> Suppléments
B71: =IFERROR(TEXT(tbl_Ventes[[#This Row],[Date]],"mm-aaaa"),"") -> 01-1900 | D71: =IFERROR( INDEX(tbl_ProduitsRef[Cde_Prdt],MATCH(tbl_Ventes[[#This Row],[Produit]],tbl_ProduitsRef[Produit],0)), "" ) | E71: 0 | F71: =IFERROR( INDEX(tbl_ProduitsRef[Prix Menu],MATCH(tbl_Ventes[[#This Row],[Produit]],tbl_ProduitsRef[Produit],0)), "" ) | G71: =tbl_Ventes[[#This Row],[Qté Vendue]] * IFERROR(_xlfn.XLOOKUP(tbl_Ventes[[#This Row],[Cde_Prdt]], tbl_Produits[Cde_Prdt], tbl_Produits[Prix Menu]), 0) -> 0 | H71: =IFERROR(_xlfn.XLOOKUP(tbl_Ventes[[#This Row],[Cde_Prdt]], tbl_Produits[Cde_Prdt], tbl_Produits[Coût Moyen Portion]), 0) -> 0 | I71: =tbl_Ventes[[#This Row],[Qté Vendue]] * tbl_Ventes[[#This Row],[CMP_par_portion]] -> 0 | J71: =tbl_Ventes[[#This Row],[CA ligne]] - tbl_Ventes[[#This Row],[Coût matière ligne]] -> 0 | K71: =IFERROR(INDEX(tbl_ProduitsRef[Famille], MATCH(tbl_Ventes[[#This Row],[Cde_Prdt]], tbl_Produits[Cde_Prdt], 0)), "")
B72: =IFERROR(TEXT(tbl_Ventes[[#This Row],[Date]],"mm-aaaa"),"") -> 01-1900 | D72: =IFERROR( INDEX(tbl_ProduitsRef[Cde_Prdt],MATCH(tbl_Ventes[[#This Row],[Produit]],tbl_ProduitsRef[Produit],0)), "" ) | E72: 0 | F72: =IFERROR( INDEX(tbl_ProduitsRef[Prix Menu],MATCH(tbl_Ventes[[#This Row],[Produit]],tbl_ProduitsRef[Produit],0)), "" ) | G72: =tbl_Ventes[[#This Row],[Qté Vendue]] * IFERROR(_xlfn.XLOOKUP(tbl_Ventes[[#This Row],[Cde_Prdt]], tbl_Produits[Cde_Prdt], tbl_Produits[Prix Menu]), 0) -> 0 | H72: =IFERROR(_xlfn.XLOOKUP(tbl_Ventes[[#This Row],[Cde_Prdt]], tbl_Produits[Cde_Prdt], tbl_Produits[Coût Moyen Portion]), 0) -> 0 | I72: =tbl_Ventes[[#This Row],[Qté Vendue]] * tbl_Ventes[[#This Row],[CMP_par_portion]] -> 0 | J72: =tbl_Ventes[[#This Row],[CA ligne]] - tbl_Ventes[[#This Row],[Coût matière ligne]] -> 0 | K72: =IFERROR(INDEX(tbl_ProduitsRef[Famille], MATCH(tbl_Ventes[[#This Row],[Cde_Prdt]], tbl_Produits[Cde_Prdt], 0)), "")
B73: =IFERROR(TEXT(tbl_Ventes[[#This Row],[Date]],"mm-aaaa"),"") -> 01-1900 | D73: =IFERROR( INDEX(tbl_ProduitsRef[Cde_Prdt],MATCH(tbl_Ventes[[#This Row],[Produit]],tbl_ProduitsRef[Produit],0)), "" ) | E73: 0 | F73: =IFERROR( INDEX(tbl_ProduitsRef[Prix Menu],MATCH(tbl_Ventes[[#This Row],[Produit]],tbl_ProduitsRef[Produit],0)), "" ) | G73: =tbl_Ventes[[#This Row],[Qté Vendue]] * IFERROR(_xlfn.XLOOKUP(tbl_Ventes[[#This Row],[Cde_Prdt]], tbl_Produits[Cde_Prdt], tbl_Produits[Prix Menu]), 0) -> 0 | H73: =IFERROR(_xlfn.XLOOKUP(tbl_Ventes[[#This Row],[Cde_Prdt]], tbl_Produits[Cde_Prdt], tbl_Produits[Coût Moyen Portion]), 0) -> 0 | I73: =tbl_Ventes[[#This Row],[Qté Vendue]] * tbl_Ventes[[#This Row],[CMP_par_portion]] -> 0 | J73: =tbl_Ventes[[#This Row],[CA ligne]] - tbl_Ventes[[#This Row],[Coût matière ligne]] -> 0 | K73: =IFERROR(INDEX(tbl_ProduitsRef[Famille], MATCH(tbl_Ventes[[#This Row],[Cde_Prdt]], tbl_Produits[Cde_Prdt], 0)), "")
B74: =IFERROR(TEXT(tbl_Ventes[[#This Row],[Date]],"mm-aaaa"),"") -> 01-1900 | D74: =IFERROR( INDEX(tbl_ProduitsRef[Cde_Prdt],MATCH(tbl_Ventes[[#This Row],[Produit]],tbl_ProduitsRef[Produit],0)), "" ) | E74: 0 | F74: =IFERROR( INDEX(tbl_ProduitsRef[Prix Menu],MATCH(tbl_Ventes[[#This Row],[Produit]],tbl_ProduitsRef[Produit],0)), "" ) | G74: =tbl_Ventes[[#This Row],[Qté Vendue]] * IFERROR(_xlfn.XLOOKUP(tbl_Ventes[[#This Row],[Cde_Prdt]], tbl_Produits[Cde_Prdt], tbl_Produits[Prix Menu]), 0) -> 0 | H74: =IFERROR(_xlfn.XLOOKUP(tbl_Ventes[[#This Row],[Cde_Prdt]], tbl_Produits[Cde_Prdt], tbl_Produits[Coût Moyen Portion]), 0) -> 0 | I74: =tbl_Ventes[[#This Row],[Qté Vendue]] * tbl_Ventes[[#This Row],[CMP_par_portion]] -> 0 | J74: =tbl_Ventes[[#This Row],[CA ligne]] - tbl_Ventes[[#This Row],[Coût matière ligne]] -> 0 | K74: =IFERROR(INDEX(tbl_ProduitsRef[Famille], MATCH(tbl_Ventes[[#This Row],[Cde_Prdt]], tbl_Produits[Cde_Prdt], 0)), "")
B75: =IFERROR(TEXT(tbl_Ventes[[#This Row],[Date]],"mm-aaaa"),"") -> 01-1900 | D75: =IFERROR( INDEX(tbl_ProduitsRef[Cde_Prdt],MATCH(tbl_Ventes[[#This Row],[Produit]],tbl_ProduitsRef[Produit],0)), "" ) | E75: 0 | F75: =IFERROR( INDEX(tbl_ProduitsRef[Prix Menu],MATCH(tbl_Ventes[[#This Row],[Produit]],tbl_ProduitsRef[Produit],0)), "" ) | G75: =tbl_Ventes[[#This Row],[Qté Vendue]] * IFERROR(_xlfn.XLOOKUP(tbl_Ventes[[#This Row],[Cde_Prdt]], tbl_Produits[Cde_Prdt], tbl_Produits[Prix Menu]), 0) -> 0 | H75: =IFERROR(_xlfn.XLOOKUP(tbl_Ventes[[#This Row],[Cde_Prdt]], tbl_Produits[Cde_Prdt], tbl_Produits[Coût Moyen Portion]), 0) -> 0 | I75: =tbl_Ventes[[#This Row],[Qté Vendue]] * tbl_Ventes[[#This Row],[CMP_par_portion]] -> 0 | J75: =tbl_Ventes[[#This Row],[CA ligne]] - tbl_Ventes[[#This Row],[Coût matière ligne]] -> 0 | K75: =IFERROR(INDEX(tbl_ProduitsRef[Famille], MATCH(tbl_Ventes[[#This Row],[Cde_Prdt]], tbl_Produits[Cde_Prdt], 0)), "")
B76: =IFERROR(TEXT(tbl_Ventes[[#This Row],[Date]],"mm-aaaa"),"") -> 01-1900 | D76: =IFERROR( INDEX(tbl_ProduitsRef[Cde_Prdt],MATCH(tbl_Ventes[[#This Row],[Produit]],tbl_ProduitsRef[Produit],0)), "" ) | E76: 0 | F76: =IFERROR( INDEX(tbl_ProduitsRef[Prix Menu],MATCH(tbl_Ventes[[#This Row],[Produit]],tbl_ProduitsRef[Produit],0)), "" ) | G76: =tbl_Ventes[[#This Row],[Qté Vendue]] * IFERROR(_xlfn.XLOOKUP(tbl_Ventes[[#This Row],[Cde_Prdt]], tbl_Produits[Cde_Prdt], tbl_Produits[Prix Menu]), 0) -> 0 | H76: =IFERROR(_xlfn.XLOOKUP(tbl_Ventes[[#This Row],[Cde_Prdt]], tbl_Produits[Cde_Prdt], tbl_Produits[Coût Moyen Portion]), 0) -> 0 | I76: =tbl_Ventes[[#This Row],[Qté Vendue]] * tbl_Ventes[[#This Row],[CMP_par_portion]] -> 0 | J76: =tbl_Ventes[[#This Row],[CA ligne]] - tbl_Ventes[[#This Row],[Coût matière ligne]] -> 0 | K76: =IFERROR(INDEX(tbl_ProduitsRef[Famille], MATCH(tbl_Ventes[[#This Row],[Cde_Prdt]], tbl_Produits[Cde_Prdt], 0)), "")
B77: =IFERROR(TEXT(tbl_Ventes[[#This Row],[Date]],"mm-aaaa"),"") -> 01-1900 | D77: =IFERROR( INDEX(tbl_ProduitsRef[Cde_Prdt],MATCH(tbl_Ventes[[#This Row],[Produit]],tbl_ProduitsRef[Produit],0)), "" ) | E77: 0 | F77: =IFERROR( INDEX(tbl_ProduitsRef[Prix Menu],MATCH(tbl_Ventes[[#This Row],[Produit]],tbl_ProduitsRef[Produit],0)), "" ) | G77: =tbl_Ventes[[#This Row],[Qté Vendue]] * IFERROR(_xlfn.XLOOKUP(tbl_Ventes[[#This Row],[Cde_Prdt]], tbl_Produits[Cde_Prdt], tbl_Produits[Prix Menu]), 0) -> 0 | H77: =IFERROR(_xlfn.XLOOKUP(tbl_Ventes[[#This Row],[Cde_Prdt]], tbl_Produits[Cde_Prdt], tbl_Produits[Coût Moyen Portion]), 0) -> 0 | I77: =tbl_Ventes[[#This Row],[Qté Vendue]] * tbl_Ventes[[#This Row],[CMP_par_portion]] -> 0 | J77: =tbl_Ventes[[#This Row],[CA ligne]] - tbl_Ventes[[#This Row],[Coût matière ligne]] -> 0 | K77: =IFERROR(INDEX(tbl_ProduitsRef[Famille], MATCH(tbl_Ventes[[#This Row],[Cde_Prdt]], tbl_Produits[Cde_Prdt], 0)), "")
B78: =IFERROR(TEXT(tbl_Ventes[[#This Row],[Date]],"mm-aaaa"),"") -> 01-1900 | D78: =IFERROR( INDEX(tbl_ProduitsRef[Cde_Prdt],MATCH(tbl_Ventes[[#This Row],[Produit]],tbl_ProduitsRef[Produit],0)), "" ) | E78: 0 | F78: =IFERROR( INDEX(tbl_ProduitsRef[Prix Menu],MATCH(tbl_Ventes[[#This Row],[Produit]],tbl_ProduitsRef[Produit],0)), "" ) | G78: =tbl_Ventes[[#This Row],[Qté Vendue]] * IFERROR(_xlfn.XLOOKUP(tbl_Ventes[[#This Row],[Cde_Prdt]], tbl_Produits[Cde_Prdt], tbl_Produits[Prix Menu]), 0) -> 0 | H78: =IFERROR(_xlfn.XLOOKUP(tbl_Ventes[[#This Row],[Cde_Prdt]], tbl_Produits[Cde_Prdt], tbl_Produits[Coût Moyen Portion]), 0) -> 0 | I78: =tbl_Ventes[[#This Row],[Qté Vendue]] * tbl_Ventes[[#This Row],[CMP_par_portion]] -> 0 | J78: =tbl_Ventes[[#This Row],[CA ligne]] - tbl_Ventes[[#This Row],[Coût matière ligne]] -> 0 | K78: =IFERROR(INDEX(tbl_ProduitsRef[Famille], MATCH(tbl_Ventes[[#This Row],[Cde_Prdt]], tbl_Produits[Cde_Prdt], 0)), "")
B79: =IFERROR(TEXT(tbl_Ventes[[#This Row],[Date]],"mm-aaaa"),"") -> 01-1900 | D79: =IFERROR( INDEX(tbl_ProduitsRef[Cde_Prdt],MATCH(tbl_Ventes[[#This Row],[Produit]],tbl_ProduitsRef[Produit],0)), "" ) | E79: 0 | F79: =IFERROR( INDEX(tbl_ProduitsRef[Prix Menu],MATCH(tbl_Ventes[[#This Row],[Produit]],tbl_ProduitsRef[Produit],0)), "" ) | G79: =tbl_Ventes[[#This Row],[Qté Vendue]] * IFERROR(_xlfn.XLOOKUP(tbl_Ventes[[#This Row],[Cde_Prdt]], tbl_Produits[Cde_Prdt], tbl_Produits[Prix Menu]), 0) -> 0 | H79: =IFERROR(_xlfn.XLOOKUP(tbl_Ventes[[#This Row],[Cde_Prdt]], tbl_Produits[Cde_Prdt], tbl_Produits[Coût Moyen Portion]), 0) -> 0 | I79: =tbl_Ventes[[#This Row],[Qté Vendue]] * tbl_Ventes[[#This Row],[CMP_par_portion]] -> 0 | J79: =tbl_Ventes[[#This Row],[CA ligne]] - tbl_Ventes[[#This Row],[Coût matière ligne]] -> 0 | K79: =IFERROR(INDEX(tbl_ProduitsRef[Famille], MATCH(tbl_Ventes[[#This Row],[Cde_Prdt]], tbl_Produits[Cde_Prdt], 0)), "")
B80: =IFERROR(TEXT(tbl_Ventes[[#This Row],[Date]],"mm-aaaa"),"") -> 01-1900 | D80: =IFERROR( INDEX(tbl_ProduitsRef[Cde_Prdt],MATCH(tbl_Ventes[[#This Row],[Produit]],tbl_ProduitsRef[Produit],0)), "" ) | E80: 0 | F80: =IFERROR( INDEX(tbl_ProduitsRef[Prix Menu],MATCH(tbl_Ventes[[#This Row],[Produit]],tbl_ProduitsRef[Produit],0)), "" ) | G80: =tbl_Ventes[[#This Row],[Qté Vendue]] * IFERROR(_xlfn.XLOOKUP(tbl_Ventes[[#This Row],[Cde_Prdt]], tbl_Produits[Cde_Prdt], tbl_Produits[Prix Menu]), 0) -> 0 | H80: =IFERROR(_xlfn.XLOOKUP(tbl_Ventes[[#This Row],[Cde_Prdt]], tbl_Produits[Cde_Prdt], tbl_Produits[Coût Moyen Portion]), 0) -> 0 | I80: =tbl_Ventes[[#This Row],[Qté Vendue]] * tbl_Ventes[[#This Row],[CMP_par_portion]] -> 0 | J80: =tbl_Ventes[[#This Row],[CA ligne]] - tbl_Ventes[[#This Row],[Coût matière ligne]] -> 0 | K80: =IFERROR(INDEX(tbl_ProduitsRef[Famille], MATCH(tbl_Ventes[[#This Row],[Cde_Prdt]], tbl_Produits[Cde_Prdt], 0)), "")
B81: =IFERROR(TEXT(tbl_Ventes[[#This Row],[Date]],"mm-aaaa"),"") -> 01-1900 | D81: =IFERROR( INDEX(tbl_ProduitsRef[Cde_Prdt],MATCH(tbl_Ventes[[#This Row],[Produit]],tbl_ProduitsRef[Produit],0)), "" ) | E81: 0 | F81: =IFERROR( INDEX(tbl_ProduitsRef[Prix Menu],MATCH(tbl_Ventes[[#This Row],[Produit]],tbl_ProduitsRef[Produit],0)), "" ) | G81: =tbl_Ventes[[#This Row],[Qté Vendue]] * IFERROR(_xlfn.XLOOKUP(tbl_Ventes[[#This Row],[Cde_Prdt]], tbl_Produits[Cde_Prdt], tbl_Produits[Prix Menu]), 0) -> 0 | H81: =IFERROR(_xlfn.XLOOKUP(tbl_Ventes[[#This Row],[Cde_Prdt]], tbl_Produits[Cde_Prdt], tbl_Produits[Coût Moyen Portion]), 0) -> 0 | I81: =tbl_Ventes[[#This Row],[Qté Vendue]] * tbl_Ventes[[#This Row],[CMP_par_portion]] -> 0 | J81: =tbl_Ventes[[#This Row],[CA ligne]] - tbl_Ventes[[#This Row],[Coût matière ligne]] -> 0 | K81: =IFERROR(INDEX(tbl_ProduitsRef[Famille], MATCH(tbl_Ventes[[#This Row],[Cde_Prdt]], tbl_Produits[Cde_Prdt], 0)), "")
B82: =IFERROR(TEXT(tbl_Ventes[[#This Row],[Date]],"mm-aaaa"),"") -> 01-1900 | D82: =IFERROR( INDEX(tbl_ProduitsRef[Cde_Prdt],MATCH(tbl_Ventes[[#This Row],[Produit]],tbl_ProduitsRef[Produit],0)), "" ) | E82: 0 | F82: =IFERROR( INDEX(tbl_ProduitsRef[Prix Menu],MATCH(tbl_Ventes[[#This Row],[Produit]],tbl_ProduitsRef[Produit],0)), "" ) | G82: =tbl_Ventes[[#This Row],[Qté Vendue]] * IFERROR(_xlfn.XLOOKUP(tbl_Ventes[[#This Row],[Cde_Prdt]], tbl_Produits[Cde_Prdt], tbl_Produits[Prix Menu]), 0) -> 0 | H82: =IFERROR(_xlfn.XLOOKUP(tbl_Ventes[[#This Row],[Cde_Prdt]], tbl_Produits[Cde_Prdt], tbl_Produits[Coût Moyen Portion]), 0) -> 0 | I82: =tbl_Ventes[[#This Row],[Qté Vendue]] * tbl_Ventes[[#This Row],[CMP_par_portion]] -> 0 | J82: =tbl_Ventes[[#This Row],[CA ligne]] - tbl_Ventes[[#This Row],[Coût matière ligne]] -> 0 | K82: =IFERROR(INDEX(tbl_ProduitsRef[Famille], MATCH(tbl_Ventes[[#This Row],[Cde_Prdt]], tbl_Produits[Cde_Prdt], 0)), "")
... B2727: =IFERROR(TEXT(tbl_Ventes[[#This Row],[Date]],"mm-aaaa"),"") -> 01-1900 | D2727: =IFERROR( INDEX(tbl_ProduitsRef[Cde_Prdt],MATCH(tbl_Ventes[[#This Row],[Produit]],tbl_ProduitsRef[Produit],0)), "" ) | E2727: 0 | F2727: =IFERROR( INDEX(tbl_ProduitsRef[Prix Menu],MATCH(tbl_Ventes[[#This Row],[Produit]],tbl_ProduitsRef[Produit],0)), "" ) | G2727: =tbl_Ventes[[#This Row],[Qté Vendue]] * IFERROR(_xlfn.XLOOKUP(tbl_Ventes[[#This Row],[Cde_Prdt]], tbl_Produits[Cde_Prdt], tbl_Produits[Prix Menu]), 0) -> 0 | H2727: =IFERROR(_xlfn.XLOOKUP(tbl_Ventes[[#This Row],[Cde_Prdt]], tbl_Produits[Cde_Prdt], tbl_Produits[Coût Moyen Portion]), 0) -> 0 | I2727: =tbl_Ventes[[#This Row],[Qté Vendue]] * tbl_Ventes[[#This Row],[CMP_par_portion]] -> 0 | J2727: =tbl_Ventes[[#This Row],[CA ligne]] - tbl_Ventes[[#This Row],[Coût matière ligne]] -> 0 | K2727: =IFERROR(INDEX(tbl_ProduitsRef[Famille], MATCH(tbl_Ventes[[#This Row],[Cde_Prdt]], tbl_Produits[Cde_Prdt], 0)), "")
A2728: 45823 | B2728: =IFERROR(TEXT(tbl_Ventes[[#This Row],[Date]],"mm-aaaa"),"") -> 06-2025 | D2728: =IFERROR( INDEX(tbl_ProduitsRef[Cde_Prdt],MATCH(tbl_Ventes[[#This Row],[Produit]],tbl_ProduitsRef[Produit],0)), "" ) | E2728: 0 | F2728: =IFERROR( INDEX(tbl_ProduitsRef[Prix Menu],MATCH(tbl_Ventes[[#This Row],[Produit]],tbl_ProduitsRef[Produit],0)), "" ) | G2728: =tbl_Ventes[[#This Row],[Qté Vendue]] * IFERROR(_xlfn.XLOOKUP(tbl_Ventes[[#This Row],[Cde_Prdt]], tbl_Produits[Cde_Prdt], tbl_Produits[Prix Menu]), 0) -> 0 | H2728: =IFERROR(_xlfn.XLOOKUP(tbl_Ventes[[#This Row],[Cde_Prdt]], tbl_Produits[Cde_Prdt], tbl_Produits[Coût Moyen Portion]), 0) -> 0 | I2728: =tbl_Ventes[[#This Row],[Qté Vendue]] * tbl_Ventes[[#This Row],[CMP_par_portion]] -> 0 | J2728: =tbl_Ventes[[#This Row],[CA ligne]] - tbl_Ventes[[#This Row],[Coût matière ligne]] -> 0 | K2728: =IFERROR(INDEX(tbl_ProduitsRef[Famille], MATCH(tbl_Ventes[[#This Row],[Cde_Prdt]], tbl_Produits[Cde_Prdt], 0)), "")
B2729: =IFERROR(TEXT(tbl_Ventes[[#This Row],[Date]],"mm-aaaa"),"") -> 01-1900 | D2729: =IFERROR( INDEX(tbl_ProduitsRef[Cde_Prdt],MATCH(tbl_Ventes[[#This Row],[Produit]],tbl_ProduitsRef[Produit],0)), "" ) | E2729: 0 | F2729: =IFERROR( INDEX(tbl_ProduitsRef[Prix Menu],MATCH(tbl_Ventes[[#This Row],[Produit]],tbl_ProduitsRef[Produit],0)), "" ) | G2729: =tbl_Ventes[[#This Row],[Qté Vendue]] * IFERROR(_xlfn.XLOOKUP(tbl_Ventes[[#This Row],[Cde_Prdt]], tbl_Produits[Cde_Prdt], tbl_Produits[Prix Menu]), 0) -> 0 | H2729: =IFERROR(_xlfn.XLOOKUP(tbl_Ventes[[#This Row],[Cde_Prdt]], tbl_Produits[Cde_Prdt], tbl_Produits[Coût Moyen Portion]), 0) -> 0 | I2729: =tbl_Ventes[[#This Row],[Qté Vendue]] * tbl_Ventes[[#This Row],[CMP_par_portion]] -> 0 | J2729: =tbl_Ventes[[#This Row],[CA ligne]] - tbl_Ventes[[#This Row],[Coût matière ligne]] -> 0 | K2729: =IFERROR(INDEX(tbl_ProduitsRef[Famille], MATCH(tbl_Ventes[[#This Row],[Cde_Prdt]], tbl_Produits[Cde_Prdt], 0)), "")
B2730: =IFERROR(TEXT(tbl_Ventes[[#This Row],[Date]],"mm-aaaa"),"") -> 01-1900 | D2730: =IFERROR( INDEX(tbl_ProduitsRef[Cde_Prdt],MATCH(tbl_Ventes[[#This Row],[Produit]],tbl_ProduitsRef[Produit],0)), "" ) | E2730: 0 | F2730: =IFERROR( INDEX(tbl_ProduitsRef[Prix Menu],MATCH(tbl_Ventes[[#This Row],[Produit]],tbl_ProduitsRef[Produit],0)), "" ) | G2730: =tbl_Ventes[[#This Row],[Qté Vendue]] * IFERROR(_xlfn.XLOOKUP(tbl_Ventes[[#This Row],[Cde_Prdt]], tbl_Produits[Cde_Prdt], tbl_Produits[Prix Menu]), 0) -> 0 | H2730: =IFERROR(_xlfn.XLOOKUP(tbl_Ventes[[#This Row],[Cde_Prdt]], tbl_Produits[Cde_Prdt], tbl_Produits[Coût Moyen Portion]), 0) -> 0 | I2730: =tbl_Ventes[[#This Row],[Qté Vendue]] * tbl_Ventes[[#This Row],[CMP_par_portion]] -> 0 | J2730: =tbl_Ventes[[#This Row],[CA ligne]] - tbl_Ventes[[#This Row],[Coût matière ligne]] -> 0 | K2730: =IFERROR(INDEX(tbl_ProduitsRef[Famille], MATCH(tbl_Ventes[[#This Row],[Cde_Prdt]], tbl_Produits[Cde_Prdt], 0)), "")
B2731: =IFERROR(TEXT(tbl_Ventes[[#This Row],[Date]],"mm-aaaa"),"") -> 01-1900 | D2731: =IFERROR( INDEX(tbl_ProduitsRef[Cde_Prdt],MATCH(tbl_Ventes[[#This Row],[Produit]],tbl_ProduitsRef[Produit],0)), "" ) | E2731: 0 | F2731: =IFERROR( INDEX(tbl_ProduitsRef[Prix Menu],MATCH(tbl_Ventes[[#This Row],[Produit]],tbl_ProduitsRef[Produit],0)), "" ) | G2731: =tbl_Ventes[[#This Row],[Qté Vendue]] * IFERROR(_xlfn.XLOOKUP(tbl_Ventes[[#This Row],[Cde_Prdt]], tbl_Produits[Cde_Prdt], tbl_Produits[Prix Menu]), 0) -> 0 | H2731: =IFERROR(_xlfn.XLOOKUP(tbl_Ventes[[#This Row],[Cde_Prdt]], tbl_Produits[Cde_Prdt], tbl_Produits[Coût Moyen Portion]), 0) -> 0 | I2731: =tbl_Ventes[[#This Row],[Qté Vendue]] * tbl_Ventes[[#This Row],[CMP_par_portion]] -> 0 | J2731: =tbl_Ventes[[#This Row],[CA ligne]] - tbl_Ventes[[#This Row],[Coût matière ligne]] -> 0 | K2731: =IFERROR(INDEX(tbl_ProduitsRef[Famille], MATCH(tbl_Ventes[[#This Row],[Cde_Prdt]], tbl_Produits[Cde_Prdt], 0)), "")
B2732: =IFERROR(TEXT(tbl_Ventes[[#This Row],[Date]],"mm-aaaa"),"") -> 01-1900 | D2732: =IFERROR( INDEX(tbl_ProduitsRef[Cde_Prdt],MATCH(tbl_Ventes[[#This Row],[Produit]],tbl_ProduitsRef[Produit],0)), "" ) | E2732: 0 | F2732: =IFERROR( INDEX(tbl_ProduitsRef[Prix Menu],MATCH(tbl_Ventes[[#This Row],[Produit]],tbl_ProduitsRef[Produit],0)), "" ) | G2732: =tbl_Ventes[[#This Row],[Qté Vendue]] * IFERROR(_xlfn.XLOOKUP(tbl_Ventes[[#This Row],[Cde_Prdt]], tbl_Produits[Cde_Prdt], tbl_Produits[Prix Menu]), 0) -> 0 | H2732: =IFERROR(_xlfn.XLOOKUP(tbl_Ventes[[#This Row],[Cde_Prdt]], tbl_Produits[Cde_Prdt], tbl_Produits[Coût Moyen Portion]), 0) -> 0 | I2732: =tbl_Ventes[[#This Row],[Qté Vendue]] * tbl_Ventes[[#This Row],[CMP_par_portion]] -> 0 | J2732: =tbl_Ventes[[#This Row],[CA ligne]] - tbl_Ventes[[#This Row],[Coût matière ligne]] -> 0 | K2732: =IFERROR(INDEX(tbl_ProduitsRef[Famille], MATCH(tbl_Ventes[[#This Row],[Cde_Prdt]], tbl_Produits[Cde_Prdt], 0)), "")
B2733: =IFERROR(TEXT(tbl_Ventes[[#This Row],[Date]],"mm-aaaa"),"") -> 01-1900 | D2733: =IFERROR( INDEX(tbl_ProduitsRef[Cde_Prdt],MATCH(tbl_Ventes[[#This Row],[Produit]],tbl_ProduitsRef[Produit],0)), "" ) | E2733: 0 | F2733: =IFERROR( INDEX(tbl_ProduitsRef[Prix Menu],MATCH(tbl_Ventes[[#This Row],[Produit]],tbl_ProduitsRef[Produit],0)), "" ) | G2733: =tbl_Ventes[[#This Row],[Qté Vendue]] * IFERROR(_xlfn.XLOOKUP(tbl_Ventes[[#This Row],[Cde_Prdt]], tbl_Produits[Cde_Prdt], tbl_Produits[Prix Menu]), 0) -> 0 | H2733: =IFERROR(_xlfn.XLOOKUP(tbl_Ventes[[#This Row],[Cde_Prdt]], tbl_Produits[Cde_Prdt], tbl_Produits[Coût Moyen Portion]), 0) -> 0 | I2733: =tbl_Ventes[[#This Row],[Qté Vendue]] * tbl_Ventes[[#This Row],[CMP_par_portion]] -> 0 | J2733: =tbl_Ventes[[#This Row],[CA ligne]] - tbl_Ventes[[#This Row],[Coût matière ligne]] -> 0 | K2733: =IFERROR(INDEX(tbl_ProduitsRef[Famille], MATCH(tbl_Ventes[[#This Row],[Cde_Prdt]], tbl_Produits[Cde_Prdt], 0)), "")
B2734: =IFERROR(TEXT(tbl_Ventes[[#This Row],[Date]],"mm-aaaa"),"") -> 01-1900 | D2734: =IFERROR( INDEX(tbl_ProduitsRef[Cde_Prdt],MATCH(tbl_Ventes[[#This Row],[Produit]],tbl_ProduitsRef[Produit],0)), "" ) | E2734: 0 | F2734: =IFERROR( INDEX(tbl_ProduitsRef[Prix Menu],MATCH(tbl_Ventes[[#This Row],[Produit]],tbl_ProduitsRef[Produit],0)), "" ) | G2734: =tbl_Ventes[[#This Row],[Qté Vendue]] * IFERROR(_xlfn.XLOOKUP(tbl_Ventes[[#This Row],[Cde_Prdt]], tbl_Produits[Cde_Prdt], tbl_Produits[Prix Menu]), 0) -> 0 | H2734: =IFERROR(_xlfn.XLOOKUP(tbl_Ventes[[#This Row],[Cde_Prdt]], tbl_Produits[Cde_Prdt], tbl_Produits[Coût Moyen Portion]), 0) -> 0 | I2734: =tbl_Ventes[[#This Row],[Qté Vendue]] * tbl_Ventes[[#This Row],[CMP_par_portion]] -> 0 | J2734: =tbl_Ventes[[#This Row],[CA ligne]] - tbl_Ventes[[#This Row],[Coût matière ligne]] -> 0 | K2734: =IFERROR(INDEX(tbl_ProduitsRef[Famille], MATCH(tbl_Ventes[[#This Row],[Cde_Prdt]], tbl_Produits[Cde_Prdt], 0)), "")
B2735: =IFERROR(TEXT(tbl_Ventes[[#This Row],[Date]],"mm-aaaa"),"") -> 01-1900 | D2735: =IFERROR( INDEX(tbl_ProduitsRef[Cde_Prdt],MATCH(tbl_Ventes[[#This Row],[Produit]],tbl_ProduitsRef[Produit],0)), "" ) | E2735: 0 | F2735: =IFERROR( INDEX(tbl_ProduitsRef[Prix Menu],MATCH(tbl_Ventes[[#This Row],[Produit]],tbl_ProduitsRef[Produit],0)), "" ) | G2735: =tbl_Ventes[[#This Row],[Qté Vendue]] * IFERROR(_xlfn.XLOOKUP(tbl_Ventes[[#This Row],[Cde_Prdt]], tbl_Produits[Cde_Prdt], tbl_Produits[Prix Menu]), 0) -> 0 | H2735: =IFERROR(_xlfn.XLOOKUP(tbl_Ventes[[#This Row],[Cde_Prdt]], tbl_Produits[Cde_Prdt], tbl_Produits[Coût Moyen Portion]), 0) -> 0 | I2735: =tbl_Ventes[[#This Row],[Qté Vendue]] * tbl_Ventes[[#This Row],[CMP_par_portion]] -> 0 | J2735: =tbl_Ventes[[#This Row],[CA ligne]] - tbl_Ventes[[#This Row],[Coût matière ligne]] -> 0 | K2735: =IFERROR(INDEX(tbl_ProduitsRef[Famille], MATCH(tbl_Ventes[[#This Row],[Cde_Prdt]], tbl_Produits[Cde_Prdt], 0)), "")
B2736: =IFERROR(TEXT(tbl_Ventes[[#This Row],[Date]],"mm-aaaa"),"") -> 01-1900 | D2736: =IFERROR( INDEX(tbl_ProduitsRef[Cde_Prdt],MATCH(tbl_Ventes[[#This Row],[Produit]],tbl_ProduitsRef[Produit],0)), "" ) | E2736: 0 | F2736: =IFERROR( INDEX(tbl_ProduitsRef[Prix Menu],MATCH(tbl_Ventes[[#This Row],[Produit]],tbl_ProduitsRef[Produit],0)), "" ) | G2736: =tbl_Ventes[[#This Row],[Qté Vendue]] * IFERROR(_xlfn.XLOOKUP(tbl_Ventes[[#This Row],[Cde_Prdt]], tbl_Produits[Cde_Prdt], tbl_Produits[Prix Menu]), 0) -> 0 | H2736: =IFERROR(_xlfn.XLOOKUP(tbl_Ventes[[#This Row],[Cde_Prdt]], tbl_Produits[Cde_Prdt], tbl_Produits[Coût Moyen Portion]), 0) -> 0 | I2736: =tbl_Ventes[[#This Row],[Qté Vendue]] * tbl_Ventes[[#This Row],[CMP_par_portion]] -> 0 | J2736: =tbl_Ventes[[#This Row],[CA ligne]] - tbl_Ventes[[#This Row],[Coût matière ligne]] -> 0 | K2736: =IFERROR(INDEX(tbl_ProduitsRef[Famille], MATCH(tbl_Ventes[[#This Row],[Cde_Prdt]], tbl_Produits[Cde_Prdt], 0)), "")
B2737: =IFERROR(TEXT(tbl_Ventes[[#This Row],[Date]],"mm-aaaa"),"") -> 01-1900 | D2737: =IFERROR( INDEX(tbl_ProduitsRef[Cde_Prdt],MATCH(tbl_Ventes[[#This Row],[Produit]],tbl_ProduitsRef[Produit],0)), "" ) | E2737: 0 | F2737: =IFERROR( INDEX(tbl_ProduitsRef[Prix Menu],MATCH(tbl_Ventes[[#This Row],[Produit]],tbl_ProduitsRef[Produit],0)), "" ) | G2737: =tbl_Ventes[[#This Row],[Qté Vendue]] * IFERROR(_xlfn.XLOOKUP(tbl_Ventes[[#This Row],[Cde_Prdt]], tbl_Produits[Cde_Prdt], tbl_Produits[Prix Menu]), 0) -> 0 | H2737: =IFERROR(_xlfn.XLOOKUP(tbl_Ventes[[#This Row],[Cde_Prdt]], tbl_Produits[Cde_Prdt], tbl_Produits[Coût Moyen Portion]), 0) -> 0 | I2737: =tbl_Ventes[[#This Row],[Qté Vendue]] * tbl_Ventes[[#This Row],[CMP_par_portion]] -> 0 | J2737: =tbl_Ventes[[#This Row],[CA ligne]] - tbl_Ventes[[#This Row],[Coût matière ligne]] -> 0 | K2737: =IFERROR(INDEX(tbl_ProduitsRef[Famille], MATCH(tbl_Ventes[[#This Row],[Cde_Prdt]], tbl_Produits[Cde_Prdt], 0)), "")
B2738: =IFERROR(TEXT(tbl_Ventes[[#This Row],[Date]],"mm-aaaa"),"") -> 01-1900 | D2738: =IFERROR( INDEX(tbl_ProduitsRef[Cde_Prdt],MATCH(tbl_Ventes[[#This Row],[Produit]],tbl_ProduitsRef[Produit],0)), "" ) | E2738: 0 | F2738: =IFERROR( INDEX(tbl_ProduitsRef[Prix Menu],MATCH(tbl_Ventes[[#This Row],[Produit]],tbl_ProduitsRef[Produit],0)), "" ) | G2738: =tbl_Ventes[[#This Row],[Qté Vendue]] * IFERROR(_xlfn.XLOOKUP(tbl_Ventes[[#This Row],[Cde_Prdt]], tbl_Produits[Cde_Prdt], tbl_Produits[Prix Menu]), 0) -> 0 | H2738: =IFERROR(_xlfn.XLOOKUP(tbl_Ventes[[#This Row],[Cde_Prdt]], tbl_Produits[Cde_Prdt], tbl_Produits[Coût Moyen Portion]), 0) -> 0 | I2738: =tbl_Ventes[[#This Row],[Qté Vendue]] * tbl_Ventes[[#This Row],[CMP_par_portion]] -> 0 | J2738: =tbl_Ventes[[#This Row],[CA ligne]] - tbl_Ventes[[#This Row],[Coût matière ligne]] -> 0 | K2738: =IFERROR(INDEX(tbl_ProduitsRef[Famille], MATCH(tbl_Ventes[[#This Row],[Cde_Prdt]], tbl_Produits[Cde_Prdt], 0)), "")
B2739: =IFERROR(TEXT(tbl_Ventes[[#This Row],[Date]],"mm-aaaa"),"") -> 01-1900 | D2739: =IFERROR( INDEX(tbl_ProduitsRef[Cde_Prdt],MATCH(tbl_Ventes[[#This Row],[Produit]],tbl_ProduitsRef[Produit],0)), "" ) | E2739: 0 | F2739: =IFERROR( INDEX(tbl_ProduitsRef[Prix Menu],MATCH(tbl_Ventes[[#This Row],[Produit]],tbl_ProduitsRef[Produit],0)), "" ) | G2739: =tbl_Ventes[[#This Row],[Qté Vendue]] * IFERROR(_xlfn.XLOOKUP(tbl_Ventes[[#This Row],[Cde_Prdt]], tbl_Produits[Cde_Prdt], tbl_Produits[Prix Menu]), 0) -> 0 | H2739: =IFERROR(_xlfn.XLOOKUP(tbl_Ventes[[#This Row],[Cde_Prdt]], tbl_Produits[Cde_Prdt], tbl_Produits[Coût Moyen Portion]), 0) -> 0 | I2739: =tbl_Ventes[[#This Row],[Qté Vendue]] * tbl_Ventes[[#This Row],[CMP_par_portion]] -> 0 | J2739: =tbl_Ventes[[#This Row],[CA ligne]] - tbl_Ventes[[#This Row],[Coût matière ligne]] -> 0 | K2739: =IFERROR(INDEX(tbl_ProduitsRef[Famille], MATCH(tbl_Ventes[[#This Row],[Cde_Prdt]], tbl_Produits[Cde_Prdt], 0)), "")
B2740: =IFERROR(TEXT(tbl_Ventes[[#This Row],[Date]],"mm-aaaa"),"") -> 01-1900 | D2740: =IFERROR( INDEX(tbl_ProduitsRef[Cde_Prdt],MATCH(tbl_Ventes[[#This Row],[Produit]],tbl_ProduitsRef[Produit],0)), "" ) | E2740: 0 | F2740: =IFERROR( INDEX(tbl_ProduitsRef[Prix Menu],MATCH(tbl_Ventes[[#This Row],[Produit]],tbl_ProduitsRef[Produit],0)), "" ) | G2740: =tbl_Ventes[[#This Row],[Qté Vendue]] * IFERROR(_xlfn.XLOOKUP(tbl_Ventes[[#This Row],[Cde_Prdt]], tbl_Produits[Cde_Prdt], tbl_Produits[Prix Menu]), 0) -> 0 | H2740: =IFERROR(_xlfn.XLOOKUP(tbl_Ventes[[#This Row],[Cde_Prdt]], tbl_Produits[Cde_Prdt], tbl_Produits[Coût Moyen Portion]), 0) -> 0 | I2740: =tbl_Ventes[[#This Row],[Qté Vendue]] * tbl_Ventes[[#This Row],[CMP_par_portion]] -> 0 | J2740: =tbl_Ventes[[#This Row],[CA ligne]] - tbl_Ventes[[#This Row],[Coût matière ligne]] -> 0 | K2740: =IFERROR(INDEX(tbl_ProduitsRef[Famille], MATCH(tbl_Ventes[[#This Row],[Cde_Prdt]], tbl_Produits[Cde_Prdt], 0)), "")
... B5000: =IFERROR(TEXT(tbl_Ventes[[#This Row],[Date]],"mm-aaaa"),"") -> 01-1900 | D5000: =IFERROR( INDEX(tbl_ProduitsRef[Cde_Prdt],MATCH(tbl_Ventes[[#This Row],[Produit]],tbl_ProduitsRef[Produit],0)), "" ) | E5000: 0 | F5000: =IFERROR( INDEX(tbl_ProduitsRef[Prix Menu],MATCH(tbl_Ventes[[#This Row],[Produit]],tbl_ProduitsRef[Produit],0)), "" ) | G5000: =tbl_Ventes[[#This Row],[Qté Vendue]] * IFERROR(_xlfn.XLOOKUP(tbl_Ventes[[#This Row],[Cde_Prdt]], tbl_Produits[Cde_Prdt], tbl_Produits[Prix Menu]), 0) -> 0 | H5000: =IFERROR(_xlfn.XLOOKUP(tbl_Ventes[[#This Row],[Cde_Prdt]], tbl_Produits[Cde_Prdt], tbl_Produits[Coût Moyen Portion]), 0) -> 0 | I5000: =tbl_Ventes[[#This Row],[Qté Vendue]] * tbl_Ventes[[#This Row],[CMP_par_portion]] -> 0 | J5000: =tbl_Ventes[[#This Row],[CA ligne]] - tbl_Ventes[[#This Row],[Coût matière ligne]] -> 0 | K5000: =IFERROR(INDEX(tbl_ProduitsRef[Famille], MATCH(tbl_Ventes[[#This Row],[Cde_Prdt]], tbl_Produits[Cde_Prdt], 0)), "")

Sheet tbl_Charges_Fixes
A1: ID_Charge | B1: Colonne1 | C1: Libellé | D1: Famille affectée | E1: Montant_Mensuel | F1: Fréquence | G1: Type d’affectation
A2: CHA001 | B2: Occupation | C2: Loyer local | D2: Globale | E2: 200000 | F2: Mensuelle | G2: Globale
A3: CHA002 | B3: Occupation | C3: Assurance local | D3: Globale | E3: 1300 | F3: Mensuelle | G3: Globale
A4: CHA003 | B4: Salaires | C4: Assurance Salariés (AT+Transport) | D4: Globale | E4: 2900 | F4: Mensuelle | G4: Globale
A5: CHA004 | B5: Salaires | C5: Salaires Petits déjeuners | D5: Petits déjeuners | E5: =6*4000 -> 24000 | F5: Mensuelle | G5: Spécifique
A6: CHA005 | B6: Salaires | C6: Salaires Œufs & Omelettes | D6: Œufs & Omelettes | E6: =+E5 -> 24000 | F6: Mensuelle | G6: Spécifique
A7: CHA006 | B7: Salaires | C7: Salaires à la carte | D7: à la carte | E7: =+E6 -> 24000 | F7: Mensuelle | G7: Spécifique
A8: CHA007 | B8: Salaires | C8: Salaires Sérveur | D8: Globale | E8: =60*3000 -> 180000 | F8: Mensuelle | G8: Globale
A9: CHA008 | B9: Salaires | C9: Salaires Entrées & Salades | D9: Entrées & Salades | E9: =8*5000 -> 40000 | F9: Mensuelle | G9: Spécifique
A10: CHA009 | B10: Salaires | C10: Salaires Poulet | D10: Poulet | E10: =4*6000 -> 24000 | F10: Mensuelle | G10: Spécifique
A11: CHA011 | B11: Salaires | C11: Salaires Boucherie | D11: Boucherie | E11: 6540 | F11: Mensuelle | G11: Spécifique
A12: CHA012 | B12: Salaires | C12: Salaires Poissons & Fruits de mer | D12: Poissons & Fruits de mer | E12: 6555 | F12: Mensuelle | G12: Spécifique
A13: CHA013 | B13: Salaires | C13: Salaires Tajines & Coin marocain | D13: Tajines & Coin marocain | E13: 65555 | F13: Mensuelle | G13: Spécifique
A14: CHA014 | B14: Salaires | C14: Salaires Pâtes | D14: Pâtes | E14: 21000 | F14: Mensuelle | G14: Spécifique
A15: CHA015 | B15: Salaires | C15: Salaires Pizzas | D15: Pizzas | E15: 21000 | F15: Mensuelle | G15: Spécifique
A16: CHA016 | B16: Salaires | C16: Salaires Snack | D16: Snack | E16: 20000 | F16: Mensuelle | G16: Spécifique
A17: CHA017 | B17: Salaires | C17: Salaires Glaces & Desserts | D17: Glaces & Desserts | E17: 5000 | F17: Mensuelle | G17: Spécifique
A18: CHA018 | B18: Salaires | C18: Salaires Crêpes & Gaufres | D18: Crêpes & Gaufres | E18: 15000 | F18: Mensuelle | G18: Spécifique
A19: CHA019 | B19: Salaires | C19: Salaires Boissons chaudes | D19: Boissons chaudes | E19: 35000 | F19: Mensuelle | G19: Spécifique
A20: CHA020 | B20: Salaires | C20: Salaires Jus Frais | D20: Jus Frais | E20: 14000 | F20: Mensuelle | G20: Spécifique
A21: CHA021 | B21: Salaires | C21: Salaires Milkshakes | D21: Milkshakes | E21: 35000 | F21: Mensuelle | G21: Spécifique
A22: CHA022 | B22: Salaires | C22: Salaires Smoothies & Coctails | D22: Smoothies & Coctails | E22: 10000 | F22: Mensuelle | G22: Spécifique
A23: CHA023 | B23: Salaires | C23: Salaires Boissons froides | D23: Boissons froides | E23: 40000 | F23: Mensuelle | G23: Spécifique
A24: CHA024 | B24: Salaires | C24: Charges patronales | D24: Globale | E24: =SUM(E6:E10)*12.6% -> 36792 | F24: Mensuelle | G24: Globale
A25: CHA025 | B25: Salaires | C25: Avantages salariés (repas, remises) | D25: Globale | E25: 1200 | F25: Mensuelle | G25: Globale
A26: CHA026 | B26: Salaires | C26: Avantages salariés (repas, remises) | D26: Globale | E26: 1200 | F26: Mensuelle | G26: Globale
A27: CHA027 | B27: Salaires | C27: Avantages salariés (repas, remises) | D27: Globale | E27: 1200 | F27: Mensuelle | G27: Globale
A28: CHA028 | B28: Salaires | C28: Avantages salariés (repas, remises) | D28: Globale | E28: 1200 | F28: Mensuelle | G28: Globale
A29: CHA029 | B29: Energie | C29: Électricité | D29: Globale | E29: 7000 | F29: Mensuelle | G29: Globale
A30: CHA030 | B30: Energie | C30: Gaz / cuisson | D30: Globale | E30: 5000 | F30: Mensuelle | G30: Globale
A31: CHA031 | B31: Eau & Assainissement | C31: Eau | D31: Globale | E31: 2500 | F31: Mensuelle | G31: Globale
A32: CHA032 | B32: Entretien | C32: Maintenance équipements | D32: Globale | E32: 6000 | F32: Mensuelle | G32: Globale
A33: CHA033 | B33: Entretien | C33: Nettoyage & produits entretien | D33: Globale | E33: 25000 | F33: Mensuelle | G33: Globale
A34: CHA034 | B34: Fournitures | C34: Vaisselle jetable & consommables | D34: Globale | E34: 5000 | F34: Mensuelle | G34: Globale
A35: CHA035 | B35: Fournitures | C35: Papeterie, menus, fournitures admin | D35: Globale | E35: 3000 | F35: Mensuelle | G35: Globale
A36: CHA036 | B36: Marketing | C36: Publicité & réseaux sociaux | D36: Globale | E36: 3500 | F36: Mensuelle | G36: Globale
... A43: CHA043 | B43: Divers / Réserve | C43: Provision imprévus / SAV | D43: Globale | E43: 10000 | F43: Mensuelle | G43: Globale
E44: =SUBTOTAL(109,tbl_Charges_Fixes[Montant_Mensuel]) -> 929242
E47: Charge Globale | F47: Charge Spécifique | G47: total des charges globales
E48: =SUMIFS(tbl_Charges_Fixes[Montant_Mensuel], tbl_Charges_Fixes[Type d’affectation], "Globale") -> 498592 | F48: =SUMIFS(tbl_Charges_Fixes[Montant_Mensuel], tbl_Charges_Fixes[Type d’affectation], "Spécifique") -> 430650 | G48: =SUM(E48:F48) -> 929242
G50: =IFERROR(SUMIFS(tbl_Ventes[Qté Vendue], tbl_Ventes[Date], ">="&$B$2, tbl_Ventes[Date], "<="&$C$2),0) -> 0

Sheet tbl_Produits
A1: Cde_Prdt | B1: Produit | C1: Famille | D1: Coût Moyen Portion | E1: Prix Menu | F1: Marge Brute | G1: % Contribution | H1: Scoring | I1: Food cost % | J1: % de Chrg Fixe /Prdt | K1: Marge nette /Prdt | L1: Seuils Tolérés | M1: Charges fixes par portion | T1: =+ChargesFixesPar_Portion[[#Headers],[Charges fixes par portion]] -> Charges fixes par portion
A2: =Référentiels!A2&TEXT(Référentiels!B2,"000") -> PDJ001 | B2: =+tbl_ProduitsRef[[#This Row],[Produit]] -> Norvégien | C2: =IFERROR(INDEX(tbl_ProduitsRef[Famille], MATCH(tbl_Produits[[#This Row],[Cde_Prdt]], tbl_Produits[Cde_Prdt], 0)), "") -> Petits déjeuners | D2: =SUMIF(tbl_Recettes[Cde_Prdt], tbl_Produits[[#This Row],[Cde_Prdt]], tbl_Recettes[Coût Moyen Portion]) -> 45.4 | E2: =IFERROR( INDEX(tbl_ProduitsRef[Prix Menu],MATCH(B2,tbl_ProduitsRef[Produit],0)), "" ) -> 70 | F2: =tbl_Produits[[#This Row],[Prix Menu]] - tbl_Produits[[#This Row],[Coût Moyen Portion]] -> 24.6 | G2: =IF(tbl_Produits[[#This Row],[Prix Menu]]>0, tbl_Produits[[#This Row],[Marge Brute]] / tbl_Produits[[#This Row],[Prix Menu]], 0) -> 0.35142857 | H2: =IFERROR( AVERAGE(G2*10, F2/2), 0) -> 7.9071429 | I2: =IF(tbl_Produits[[#This Row],[Prix Menu]]=0, 0, tbl_Produits[[#This Row],[Coût Moyen Portion]] / tbl_Produits[[#This Row],[Prix Menu]]) -> 0.64857143 | J2: {=IFERROR(IF(Total_portions=0, 0, Charges_fixes_totales_periode / Total_portions),"Vérifier")} -> Vérifier | K2: {=IFERROR(tbl_Produits[[#This Row],[Prix Menu]] - tbl_Produits[[#This Row],[Coût Moyen Portion]] - ChargesFixesPar_Portion[Charges fixes par portion],"Vérifier")} -> -10762.4 | L2: =IF(OR(tbl_Produits[[#This Row],[Food cost % ]]>0.35,tbl_Produits[[#This Row],[% de Chrg Fixe /Prdt]]>0.2),"À améliorer","OK") -> À améliorer | M2: =IFERROR( (SUMIF(tbl_Charges_Fixes[Famille affectée],tbl_Produits[[#This Row],[Famille]],tbl_Charges_Fixes[Montant_Mensuel])) / (SUMIF(tbl_Ventes[Famille],tbl_Produits[[#This Row],[Famille]],tbl_Ventes[Qté Vendue])), 0) -> 20.689655 | T2: {=ChargesFixesPar_Portion[]} -> 10787
A3: =Référentiels!A3&TEXT(Référentiels!B3,"000") -> PDJ002 | B3: =+tbl_ProduitsRef[[#This Row],[Produit]] -> Casserole turque | C3: =IFERROR(INDEX(tbl_ProduitsRef[Famille], MATCH(tbl_Produits[[#This Row],[Cde_Prdt]], tbl_Produits[Cde_Prdt], 0)), "") -> Petits déjeuners | D3: =SUMIF(tbl_Recettes[Cde_Prdt], tbl_Produits[[#This Row],[Cde_Prdt]], tbl_Recettes[Coût Moyen Portion]) -> 44.3 | E3: =IFERROR( INDEX(tbl_ProduitsRef[Prix Menu],MATCH(B3,tbl_ProduitsRef[Produit],0)), "" ) -> 70 | F3: =tbl_Produits[[#This Row],[Prix Menu]] - tbl_Produits[[#This Row],[Coût Moyen Portion]] -> 25.7 | G3: =IF(tbl_Produits[[#This Row],[Prix Menu]]>0, tbl_Produits[[#This Row],[Marge Brute]] / tbl_Produits[[#This Row],[Prix Menu]], 0) -> 0.36714286 | H3: =IFERROR( AVERAGE(G3*10, F3/2), 0) -> 8.2607143 | I3: =IF(tbl_Produits[[#This Row],[Prix Menu]]=0, 0, tbl_Produits[[#This Row],[Coût Moyen Portion]] / tbl_Produits[[#This Row],[Prix Menu]]) -> 0.63285714 | J3: {=IFERROR(IF(Total_portions=0, 0, Charges_fixes_totales_periode / Total_portions),"Vérifier")} -> Vérifier | K3: {=IFERROR(tbl_Produits[[#This Row],[Prix Menu]] - tbl_Produits[[#This Row],[Coût Moyen Portion]] - ChargesFixesPar_Portion[Charges fixes par portion],"Vérifier")} -> -10761.3 | L3: =IF(OR(tbl_Produits[[#This Row],[Food cost % ]]>0.35,tbl_Produits[[#This Row],[% de Chrg Fixe /Prdt]]>0.2),"À améliorer","OK") -> À améliorer | M3: =IFERROR( (SUMIF(tbl_Charges_Fixes[Famille affectée],tbl_Produits[[#This Row],[Famille]],tbl_Charges_Fixes[Montant_Mensuel])) / (SUMIF(tbl_Ventes[Famille],tbl_Produits[[#This Row],[Famille]],tbl_Ventes[Qté Vendue])), 0) -> 20.689655
A4: =Référentiels!A4&TEXT(Référentiels!B4,"000") -> PDJ003 | B4: =+tbl_ProduitsRef[[#This Row],[Produit]] -> Américain | C4: =IFERROR(INDEX(tbl_ProduitsRef[Famille], MATCH(tbl_Produits[[#This Row],[Cde_Prdt]], tbl_Produits[Cde_Prdt], 0)), "") -> Petits déjeuners | D4: =SUMIF(tbl_Recettes[Cde_Prdt], tbl_Produits[[#This Row],[Cde_Prdt]], tbl_Recettes[Coût Moyen Portion]) -> 17.3 | E4: =IFERROR( INDEX(tbl_ProduitsRef[Prix Menu],MATCH(B4,tbl_ProduitsRef[Produit],0)), "" ) -> 60 | F4: =tbl_Produits[[#This Row],[Prix Menu]] - tbl_Produits[[#This Row],[Coût Moyen Portion]] -> 42.7 | G4: =IF(tbl_Produits[[#This Row],[Prix Menu]]>0, tbl_Produits[[#This Row],[Marge Brute]] / tbl_Produits[[#This Row],[Prix Menu]], 0) -> 0.71166667 | H4: =IFERROR( AVERAGE(G4*10, F4/2), 0) -> 14.233333 | I4: =IF(tbl_Produits[[#This Row],[Prix Menu]]=0, 0, tbl_Produits[[#This Row],[Coût Moyen Portion]] / tbl_Produits[[#This Row],[Prix Menu]]) -> 0.28833333 | J4: {=IFERROR(IF(Total_portions=0, 0, Charges_fixes_totales_periode / Total_portions),"Vérifier")} -> Vérifier | K4: {=IFERROR(tbl_Produits[[#This Row],[Prix Menu]] - tbl_Produits[[#This Row],[Coût Moyen Portion]] - ChargesFixesPar_Portion[Charges fixes par portion],"Vérifier")} -> -10744.3 | L4: =IF(OR(tbl_Produits[[#This Row],[Food cost % ]]>0.35,tbl_Produits[[#This Row],[% de Chrg Fixe /Prdt]]>0.2),"À améliorer","OK") -> À améliorer | M4: =IFERROR( (SUMIF(tbl_Charges_Fixes[Famille affectée],tbl_Produits[[#This Row],[Famille]],tbl_Charges_Fixes[Montant_Mensuel])) / (SUMIF(tbl_Ventes[Famille],tbl_Produits[[#This Row],[Famille]],tbl_Ventes[Qté Vendue])), 0) -> 20.689655
A5: =Référentiels!A5&TEXT(Référentiels!B5,"000") -> PDJ004 | B5: =+tbl_ProduitsRef[[#This Row],[Produit]] -> Amsterdam | C5: =IFERROR(INDEX(tbl_ProduitsRef[Famille], MATCH(tbl_Produits[[#This Row],[Cde_Prdt]], tbl_Produits[Cde_Prdt], 0)), "") -> Petits déjeuners | D5: =SUMIF(tbl_Recettes[Cde_Prdt], tbl_Produits[[#This Row],[Cde_Prdt]], tbl_Recettes[Coût Moyen Portion]) -> 23 | E5: =IFERROR( INDEX(tbl_ProduitsRef[Prix Menu],MATCH(B5,tbl_ProduitsRef[Produit],0)), "" ) -> 55 | F5: =tbl_Produits[[#This Row],[Prix Menu]] - tbl_Produits[[#This Row],[Coût Moyen Portion]] -> 32 | G5: =IF(tbl_Produits[[#This Row],[Prix Menu]]>0, tbl_Produits[[#This Row],[Marge Brute]] / tbl_Produits[[#This Row],[Prix Menu]], 0) -> 0.58181818 | H5: =IFERROR( AVERAGE(G5*10, F5/2), 0) -> 10.909091 | I5: =IF(tbl_Produits[[#This Row],[Prix Menu]]=0, 0, tbl_Produits[[#This Row],[Coût Moyen Portion]] / tbl_Produits[[#This Row],[Prix Menu]]) -> 0.41818182 | J5: {=IFERROR(IF(Total_portions=0, 0, Charges_fixes_totales_periode / Total_portions),"Vérifier")} -> Vérifier | K5: {=IFERROR(tbl_Produits[[#This Row],[Prix Menu]] - tbl_Produits[[#This Row],[Coût Moyen Portion]] - ChargesFixesPar_Portion[Charges fixes par portion],"Vérifier")} -> -10755 | L5: =IF(OR(tbl_Produits[[#This Row],[Food cost % ]]>0.35,tbl_Produits[[#This Row],[% de Chrg Fixe /Prdt]]>0.2),"À améliorer","OK") -> À améliorer | M5: =IFERROR( (SUMIF(tbl_Charges_Fixes[Famille affectée],tbl_Produits[[#This Row],[Famille]],tbl_Charges_Fixes[Montant_Mensuel])) / (SUMIF(tbl_Ventes[Famille],tbl_Produits[[#This Row],[Famille]],tbl_Ventes[Qté Vendue])), 0) -> 20.689655
A6: =Référentiels!A6&TEXT(Référentiels!B6,"000") -> PDJ005 | B6: =+tbl_ProduitsRef[[#This Row],[Produit]] -> Espagnol | C6: =IFERROR(INDEX(tbl_ProduitsRef[Famille], MATCH(tbl_Produits[[#This Row],[Cde_Prdt]], tbl_Produits[Cde_Prdt], 0)), "") -> Petits déjeuners | D6: =SUMIF(tbl_Recettes[Cde_Prdt], tbl_Produits[[#This Row],[Cde_Prdt]], tbl_Recettes[Coût Moyen Portion]) -> 24.5 | E6: =IFERROR( INDEX(tbl_ProduitsRef[Prix Menu],MATCH(B6,tbl_ProduitsRef[Produit],0)), "" ) -> 54 | F6: =tbl_Produits[[#This Row],[Prix Menu]] - tbl_Produits[[#This Row],[Coût Moyen Portion]] -> 29.5 | G6: =IF(tbl_Produits[[#This Row],[Prix Menu]]>0, tbl_Produits[[#This Row],[Marge Brute]] / tbl_Produits[[#This Row],[Prix Menu]], 0) -> 0.5462963 | H6: =IFERROR( AVERAGE(G6*10, F6/2), 0) -> 10.106481 | I6: =IF(tbl_Produits[[#This Row],[Prix Menu]]=0, 0, tbl_Produits[[#This Row],[Coût Moyen Portion]] / tbl_Produits[[#This Row],[Prix Menu]]) -> 0.4537037 | J6: {=IFERROR(IF(Total_portions=0, 0, Charges_fixes_totales_periode / Total_portions),"Vérifier")} -> Vérifier | K6: {=IFERROR(tbl_Produits[[#This Row],[Prix Menu]] - tbl_Produits[[#This Row],[Coût Moyen Portion]] - ChargesFixesPar_Portion[Charges fixes par portion],"Vérifier")} -> -10757.5 | L6: =IF(OR(tbl_Produits[[#This Row],[Food cost % ]]>0.35,tbl_Produits[[#This Row],[% de Chrg Fixe /Prdt]]>0.2),"À améliorer","OK") -> À améliorer | M6: =IFERROR( (SUMIF(tbl_Charges_Fixes[Famille affectée],tbl_Produits[[#This Row],[Famille]],tbl_Charges_Fixes[Montant_Mensuel])) / (SUMIF(tbl_Ventes[Famille],tbl_Produits[[#This Row],[Famille]],tbl_Ventes[Qté Vendue])), 0) -> 20.689655
A7: =Référentiels!A7&TEXT(Référentiels!B7,"000") -> PDJ006 | B7: =+tbl_ProduitsRef[[#This Row],[Produit]] -> Berlin | C7: =IFERROR(INDEX(tbl_ProduitsRef[Famille], MATCH(tbl_Produits[[#This Row],[Cde_Prdt]], tbl_Produits[Cde_Prdt], 0)), "") -> Petits déjeuners | D7: =SUMIF(tbl_Recettes[Cde_Prdt], tbl_Produits[[#This Row],[Cde_Prdt]], tbl_Recettes[Coût Moyen Portion]) -> 16.4 | E7: =IFERROR( INDEX(tbl_ProduitsRef[Prix Menu],MATCH(B7,tbl_ProduitsRef[Produit],0)), "" ) -> 52 | F7: =tbl_Produits[[#This Row],[Prix Menu]] - tbl_Produits[[#This Row],[Coût Moyen Portion]] -> 35.6 | G7: =IF(tbl_Produits[[#This Row],[Prix Menu]]>0, tbl_Produits[[#This Row],[Marge Brute]] / tbl_Produits[[#This Row],[Prix Menu]], 0) -> 0.68461538 | H7: =IFERROR( AVERAGE(G7*10, F7/2), 0) -> 12.323077 | I7: =IF(tbl_Produits[[#This Row],[Prix Menu]]=0, 0, tbl_Produits[[#This Row],[Coût Moyen Portion]] / tbl_Produits[[#This Row],[Prix Menu]]) -> 0.31538462 | J7: {=IFERROR(IF(Total_portions=0, 0, Charges_fixes_totales_periode / Total_portions),"Vérifier")} -> Vérifier | K7: {=IFERROR(tbl_Produits[[#This Row],[Prix Menu]] - tbl_Produits[[#This Row],[Coût Moyen Portion]] - ChargesFixesPar_Portion[Charges fixes par portion],"Vérifier")} -> -10751.4 | L7: =IF(OR(tbl_Produits[[#This Row],[Food cost % ]]>0.35,tbl_Produits[[#This Row],[% de Chrg Fixe /Prdt]]>0.2),"À améliorer","OK") -> À améliorer | M7: =IFERROR( (SUMIF(tbl_Charges_Fixes[Famille affectée],tbl_Produits[[#This Row],[Famille]],tbl_Charges_Fixes[Montant_Mensuel])) / (SUMIF(tbl_Ventes[Famille],tbl_Produits[[#This Row],[Famille]],tbl_Ventes[Qté Vendue])), 0) -> 20.689655
A8: =Référentiels!A8&TEXT(Référentiels!B8,"000") -> PDJ007 | B8: =+tbl_ProduitsRef[[#This Row],[Produit]] -> Chamali | C8: =IFERROR(INDEX(tbl_ProduitsRef[Famille], MATCH(tbl_Produits[[#This Row],[Cde_Prdt]], tbl_Produits[Cde_Prdt], 0)), "") -> Petits déjeuners | D8: =SUMIF(tbl_Recettes[Cde_Prdt], tbl_Produits[[#This Row],[Cde_Prdt]], tbl_Recettes[Coût Moyen Portion]) -> 14.8 | E8: =IFERROR( INDEX(tbl_ProduitsRef[Prix Menu],MATCH(B8,tbl_ProduitsRef[Produit],0)), "" ) -> 52 | F8: =tbl_Produits[[#This Row],[Prix Menu]] - tbl_Produits[[#This Row],[Coût Moyen Portion]] -> 37.2 | G8: =IF(tbl_Produits[[#This Row],[Prix Menu]]>0, tbl_Produits[[#This Row],[Marge Brute]] / tbl_Produits[[#This Row],[Prix Menu]], 0) -> 0.71538462 | H8: =IFERROR( AVERAGE(G8*10, F8/2), 0) -> 12.876923 | I8: =IF(tbl_Produits[[#This Row],[Prix Menu]]=0, 0, tbl_Produits[[#This Row],[Coût Moyen Portion]] / tbl_Produits[[#This Row],[Prix Menu]]) -> 0.28461538 | J8: {=IFERROR(IF(Total_portions=0, 0, Charges_fixes_totales_periode / Total_portions),"Vérifier")} -> Vérifier | K8: {=IFERROR(tbl_Produits[[#This Row],[Prix Menu]] - tbl_Produits[[#This Row],[Coût Moyen Portion]] - ChargesFixesPar_Portion[Charges fixes par portion],"Vérifier")} -> -10749.8 | L8: =IF(OR(tbl_Produits[[#This Row],[Food cost % ]]>0.35,tbl_Produits[[#This Row],[% de Chrg Fixe /Prdt]]>0.2),"À améliorer","OK") -> À améliorer | M8: =IFERROR( (SUMIF(tbl_Charges_Fixes[Famille affectée],tbl_Produits[[#This Row],[Famille]],tbl_Charges_Fixes[Montant_Mensuel])) / (SUMIF(tbl_Ventes[Famille],tbl_Produits[[#This Row],[Famille]],tbl_Ventes[Qté Vendue])), 0) -> 20.689655
A9: =Référentiels!A9&TEXT(Référentiels!B9,"000") -> PDJ008 | B9: =+tbl_ProduitsRef[[#This Row],[Produit]] -> Continental | C9: =IFERROR(INDEX(tbl_ProduitsRef[Famille], MATCH(tbl_Produits[[#This Row],[Cde_Prdt]], tbl_Produits[Cde_Prdt], 0)), "") -> Petits déjeuners | D9: =SUMIF(tbl_Recettes[Cde_Prdt], tbl_Produits[[#This Row],[Cde_Prdt]], tbl_Recettes[Coût Moyen Portion]) -> 24.9 | E9: =IFERROR( INDEX(tbl_ProduitsRef[Prix Menu],MATCH(B9,tbl_ProduitsRef[Produit],0)), "" ) -> 48 | F9: =tbl_Produits[[#This Row],[Prix Menu]] - tbl_Produits[[#This Row],[Coût Moyen Portion]] -> 23.1 | G9: =IF(tbl_Produits[[#This Row],[Prix Menu]]>0, tbl_Produits[[#This Row],[Marge Brute]] / tbl_Produits[[#This Row],[Prix Menu]], 0) -> 0.48125 | H9: =IFERROR( AVERAGE(G9*10, F9/2), 0) -> 8.18125 | I9: =IF(tbl_Produits[[#This Row],[Prix Menu]]=0, 0, tbl_Produits[[#This Row],[Coût Moyen Portion]] / tbl_Produits[[#This Row],[Prix Menu]]) -> 0.51875 | J9: {=IFERROR(IF(Total_portions=0, 0, Charges_fixes_totales_periode / Total_portions),"Vérifier")} -> Vérifier | K9: {=IFERROR(tbl_Produits[[#This Row],[Prix Menu]] - tbl_Produits[[#This Row],[Coût Moyen Portion]] - ChargesFixesPar_Portion[Charges fixes par portion],"Vérifier")} -> -10763.9 | L9: =IF(OR(tbl_Produits[[#This Row],[Food cost % ]]>0.35,tbl_Produits[[#This Row],[% de Chrg Fixe /Prdt]]>0.2),"À améliorer","OK") -> À améliorer | M9: =IFERROR( (SUMIF(tbl_Charges_Fixes[Famille affectée],tbl_Produits[[#This Row],[Famille]],tbl_Charges_Fixes[Montant_Mensuel])) / (SUMIF(tbl_Ventes[Famille],tbl_Produits[[#This Row],[Famille]],tbl_Ventes[Qté Vendue])), 0) -> 20.689655
A10: =Référentiels!A10&TEXT(Référentiels!B10,"000") -> PDJ009 | B10: =+tbl_ProduitsRef[[#This Row],[Produit]] -> Traditionnel | C10: =IFERROR(INDEX(tbl_ProduitsRef[Famille], MATCH(tbl_Produits[[#This Row],[Cde_Prdt]], tbl_Produits[Cde_Prdt], 0)), "") -> Petits déjeuners | D10: =SUMIF(tbl_Recettes[Cde_Prdt], tbl_Produits[[#This Row],[Cde_Prdt]], tbl_Recettes[Coût Moyen Portion]) -> 26.3 | E10: =IFERROR( INDEX(tbl_ProduitsRef[Prix Menu],MATCH(B10,tbl_ProduitsRef[Produit],0)), "" ) -> 45 | F10: =tbl_Produits[[#This Row],[Prix Menu]] - tbl_Produits[[#This Row],[Coût Moyen Portion]] -> 18.7 | G10: =IF(tbl_Produits[[#This Row],[Prix Menu]]>0, tbl_Produits[[#This Row],[Marge Brute]] / tbl_Produits[[#This Row],[Prix Menu]], 0) -> 0.41555556 | H10: =IFERROR( AVERAGE(G10*10, F10/2), 0) -> 6.7527778 | I10: =IF(tbl_Produits[[#This Row],[Prix Menu]]=0, 0, tbl_Produits[[#This Row],[Coût Moyen Portion]] / tbl_Produits[[#This Row],[Prix Menu]]) -> 0.58444444 | J10: {=IFERROR(IF(Total_portions=0, 0, Charges_fixes_totales_periode / Total_portions),"Vérifier")} -> Vérifier | K10: {=IFERROR(tbl_Produits[[#This Row],[Prix Menu]] - tbl_Produits[[#This Row],[Coût Moyen Portion]] - ChargesFixesPar_Portion[Charges fixes par portion],"Vérifier")} -> -10768.3 | L10: =IF(OR(tbl_Produits[[#This Row],[Food cost % ]]>0.35,tbl_Produits[[#This Row],[% de Chrg Fixe /Prdt]]>0.2),"À améliorer","OK") -> À améliorer | M10: =IFERROR( (SUMIF(tbl_Charges_Fixes[Famille affectée],tbl_Produits[[#This Row],[Famille]],tbl_Charges_Fixes[Montant_Mensuel])) / (SUMIF(tbl_Ventes[Famille],tbl_Produits[[#This Row],[Famille]],tbl_Ventes[Qté Vendue])), 0) -> 20.689655
A11: =Référentiels!A11&TEXT(Référentiels!B11,"000") -> PDJ010 | B11: =+tbl_ProduitsRef[[#This Row],[Produit]] -> Marocain | C11: =IFERROR(INDEX(tbl_ProduitsRef[Famille], MATCH(tbl_Produits[[#This Row],[Cde_Prdt]], tbl_Produits[Cde_Prdt], 0)), "") -> Petits déjeuners | D11: =SUMIF(tbl_Recettes[Cde_Prdt], tbl_Produits[[#This Row],[Cde_Prdt]], tbl_Recettes[Coût Moyen Portion]) -> 20.9 | E11: =IFERROR( INDEX(tbl_ProduitsRef[Prix Menu],MATCH(B11,tbl_ProduitsRef[Produit],0)), "" ) -> 42 | F11: =tbl_Produits[[#This Row],[Prix Menu]] - tbl_Produits[[#This Row],[Coût Moyen Portion]] -> 21.1 | G11: =IF(tbl_Produits[[#This Row],[Prix Menu]]>0, tbl_Produits[[#This Row],[Marge Brute]] / tbl_Produits[[#This Row],[Prix Menu]], 0) -> 0.50238095 | H11: =IFERROR( AVERAGE(G11*10, F11/2), 0) -> 7.7869048 | I11: =IF(tbl_Produits[[#This Row],[Prix Menu]]=0, 0, tbl_Produits[[#This Row],[Coût Moyen Portion]] / tbl_Produits[[#This Row],[Prix Menu]]) -> 0.49761905 | J11: {=IFERROR(IF(Total_portions=0, 0, Charges_fixes_totales_periode / Total_portions),"Vérifier")} -> Vérifier | K11: {=IFERROR(tbl_Produits[[#This Row],[Prix Menu]] - tbl_Produits[[#This Row],[Coût Moyen Portion]] - ChargesFixesPar_Portion[Charges fixes par portion],"Vérifier")} -> -10765.9 | L11: =IF(OR(tbl_Produits[[#This Row],[Food cost % ]]>0.35,tbl_Produits[[#This Row],[% de Chrg Fixe /Prdt]]>0.2),"À améliorer","OK") -> À améliorer | M11: =IFERROR( (SUMIF(tbl_Charges_Fixes[Famille affectée],tbl_Produits[[#This Row],[Famille]],tbl_Charges_Fixes[Montant_Mensuel])) / (SUMIF(tbl_Ventes[Famille],tbl_Produits[[#This Row],[Famille]],tbl_Ventes[Qté Vendue])), 0) -> 20.689655
A12: =Référentiels!A12&TEXT(Référentiels!B12,"000") -> PDJ011 | B12: =+tbl_ProduitsRef[[#This Row],[Produit]] -> Parisien | C12: =IFERROR(INDEX(tbl_ProduitsRef[Famille], MATCH(tbl_Produits[[#This Row],[Cde_Prdt]], tbl_Produits[Cde_Prdt], 0)), "") -> Petits déjeuners | D12: =SUMIF(tbl_Recettes[Cde_Prdt], tbl_Produits[[#This Row],[Cde_Prdt]], tbl_Recettes[Coût Moyen Portion]) -> 25 | E12: =IFERROR( INDEX(tbl_ProduitsRef[Prix Menu],MATCH(B12,tbl_ProduitsRef[Produit],0)), "" ) -> 40 | F12: =tbl_Produits[[#This Row],[Prix Menu]] - tbl_Produits[[#This Row],[Coût Moyen Portion]] -> 15 | G12: =IF(tbl_Produits[[#This Row],[Prix Menu]]>0, tbl_Produits[[#This Row],[Marge Brute]] / tbl_Produits[[#This Row],[Prix Menu]], 0) -> 0.375 | H12: =IFERROR( AVERAGE(G12*10, F12/2), 0) -> 5.625 | I12: =IF(tbl_Produits[[#This Row],[Prix Menu]]=0, 0, tbl_Produits[[#This Row],[Coût Moyen Portion]] / tbl_Produits[[#This Row],[Prix Menu]]) -> 0.625 | J12: {=IFERROR(IF(Total_portions=0, 0, Charges_fixes_totales_periode / Total_portions),"Vérifier")} -> Vérifier | K12: {=IFERROR(tbl_Produits[[#This Row],[Prix Menu]] - tbl_Produits[[#This Row],[Coût Moyen Portion]] - ChargesFixesPar_Portion[Charges fixes par portion],"Vérifier")} -> -10772 | L12: =IF(OR(tbl_Produits[[#This Row],[Food cost % ]]>0.35,tbl_Produits[[#This Row],[% de Chrg Fixe /Prdt]]>0.2),"À améliorer","OK") -> À améliorer | M12: =IFERROR( (SUMIF(tbl_Charges_Fixes[Famille affectée],tbl_Produits[[#This Row],[Famille]],tbl_Charges_Fixes[Montant_Mensuel])) / (SUMIF(tbl_Ventes[Famille],tbl_Produits[[#This Row],[Famille]],tbl_Ventes[Qté Vendue])), 0) -> 20.689655
A13: =Référentiels!A13&TEXT(Référentiels!B13,"000") -> OME001 | B13: =+tbl_ProduitsRef[[#This Row],[Produit]] -> Omelette aux crevettes | C13: =IFERROR(INDEX(tbl_ProduitsRef[Famille], MATCH(tbl_Produits[[#This Row],[Cde_Prdt]], tbl_Produits[Cde_Prdt], 0)), "") -> Œufs & Omelettes | D13: =SUMIF(tbl_Recettes[Cde_Prdt], tbl_Produits[[#This Row],[Cde_Prdt]], tbl_Recettes[Coût Moyen Portion]) -> 9.09 | E13: =IFERROR( INDEX(tbl_ProduitsRef[Prix Menu],MATCH(B13,tbl_ProduitsRef[Produit],0)), "" ) -> 35 | F13: =tbl_Produits[[#This Row],[Prix Menu]] - tbl_Produits[[#This Row],[Coût Moyen Portion]] -> 25.91 | G13: =IF(tbl_Produits[[#This Row],[Prix Menu]]>0, tbl_Produits[[#This Row],[Marge Brute]] / tbl_Produits[[#This Row],[Prix Menu]], 0) -> 0.74028571 | H13: =IFERROR( AVERAGE(G13*10, F13/2), 0) -> 10.178929 | I13: =IF(tbl_Produits[[#This Row],[Prix Menu]]=0, 0, tbl_Produits[[#This Row],[Coût Moyen Portion]] / tbl_Produits[[#This Row],[Prix Menu]]) -> 0.25971429 | J13: {=IFERROR(IF(Total_portions=0, 0, Charges_fixes_totales_periode / Total_portions),"Vérifier")} -> Vérifier | K13: {=IFERROR(tbl_Produits[[#This Row],[Prix Menu]] - tbl_Produits[[#This Row],[Coût Moyen Portion]] - ChargesFixesPar_Portion[Charges fixes par portion],"Vérifier")} -> -10761.09 | L13: =IF(OR(tbl_Produits[[#This Row],[Food cost % ]]>0.35,tbl_Produits[[#This Row],[% de Chrg Fixe /Prdt]]>0.2),"À améliorer","OK") -> À améliorer | M13: =IFERROR( (SUMIF(tbl_Charges_Fixes[Famille affectée],tbl_Produits[[#This Row],[Famille]],tbl_Charges_Fixes[Montant_Mensuel])) / (SUMIF(tbl_Ventes[Famille],tbl_Produits[[#This Row],[Famille]],tbl_Ventes[Qté Vendue])), 0) -> 192
A14: =Référentiels!A14&TEXT(Référentiels!B14,"000") -> OME002 | B14: =+tbl_ProduitsRef[[#This Row],[Produit]] -> Omelette au fromage et dinde fumée | C14: =IFERROR(INDEX(tbl_ProduitsRef[Famille], MATCH(tbl_Produits[[#This Row],[Cde_Prdt]], tbl_Produits[Cde_Prdt], 0)), "") -> Œufs & Omelettes | D14: =SUMIF(tbl_Recettes[Cde_Prdt], tbl_Produits[[#This Row],[Cde_Prdt]], tbl_Recettes[Coût Moyen Portion]) -> 20.89 | E14: =IFERROR( INDEX(tbl_ProduitsRef[Prix Menu],MATCH(B14,tbl_ProduitsRef[Produit],0)), "" ) -> 25 | F14: =tbl_Produits[[#This Row],[Prix Menu]] - tbl_Produits[[#This Row],[Coût Moyen Portion]] -> 4.11 | G14: =IF(tbl_Produits[[#This Row],[Prix Menu]]>0, tbl_Produits[[#This Row],[Marge Brute]] / tbl_Produits[[#This Row],[Prix Menu]], 0) -> 0.1644 | H14: =IFERROR( AVERAGE(G14*10, F14/2), 0) -> 1.8495 | I14: =IF(tbl_Produits[[#This Row],[Prix Menu]]=0, 0, tbl_Produits[[#This Row],[Coût Moyen Portion]] / tbl_Produits[[#This Row],[Prix Menu]]) -> 0.8356 | J14: {=IFERROR(IF(Total_portions=0, 0, Charges_fixes_totales_periode / Total_portions),"Vérifier")} -> Vérifier | K14: {=IFERROR(tbl_Produits[[#This Row],[Prix Menu]] - tbl_Produits[[#This Row],[Coût Moyen Portion]] - ChargesFixesPar_Portion[Charges fixes par portion],"Vérifier")} -> -10782.89 | L14: =IF(OR(tbl_Produits[[#This Row],[Food cost % ]]>0.35,tbl_Produits[[#This Row],[% de Chrg Fixe /Prdt]]>0.2),"À améliorer","OK") -> À améliorer | M14: =IFERROR( (SUMIF(tbl_Charges_Fixes[Famille affectée],tbl_Produits[[#This Row],[Famille]],tbl_Charges_Fixes[Montant_Mensuel])) / (SUMIF(tbl_Ventes[Famille],tbl_Produits[[#This Row],[Famille]],tbl_Ventes[Qté Vendue])), 0) -> 192
... A276: =Référentiels!A276&TEXT(Référentiels!B276,"000") -> BFR006 | B276: =+tbl_ProduitsRef[[#This Row],[Produit]] -> Soft drinks boisson énergétique | C276: =IFERROR(INDEX(tbl_ProduitsRef[Famille], MATCH(tbl_Produits[[#This Row],[Cde_Prdt]], tbl_Produits[Cde_Prdt], 0)), "") -> Boissons froides | D276: =SUMIF(tbl_Recettes[Cde_Prdt], tbl_Produits[[#This Row],[Cde_Prdt]], tbl_Recettes[Coût Moyen Portion]) -> 14 | E276: =IFERROR( INDEX(tbl_ProduitsRef[Prix Menu],MATCH(B276,tbl_ProduitsRef[Produit],0)), "" ) -> 30 | F276: =tbl_Produits[[#This Row],[Prix Menu]] - tbl_Produits[[#This Row],[Coût Moyen Portion]] -> 16 | G276: =IF(tbl_Produits[[#This Row],[Prix Menu]]>0, tbl_Produits[[#This Row],[Marge Brute]] / tbl_Produits[[#This Row],[Prix Menu]], 0) -> 0.53333333 | H276: =IFERROR( AVERAGE(G276*10, F276/2), 0) -> 6.6666667 | I276: =IF(tbl_Produits[[#This Row],[Prix Menu]]=0, 0, tbl_Produits[[#This Row],[Coût Moyen Portion]] / tbl_Produits[[#This Row],[Prix Menu]]) -> 0.46666667 | J276: {=IFERROR(IF(Total_portions=0, 0, Charges_fixes_totales_periode / Total_portions),"Vérifier")} -> Vérifier | K276: {=IFERROR(tbl_Produits[[#This Row],[Prix Menu]] - tbl_Produits[[#This Row],[Coût Moyen Portion]] - ChargesFixesPar_Portion[Charges fixes par portion],"Vérifier")} -> -10771 | L276: =IF(OR(tbl_Produits[[#This Row],[Food cost % ]]>0.35,tbl_Produits[[#This Row],[% de Chrg Fixe /Prdt]]>0.2),"À améliorer","OK") -> À améliorer | M276: =IFERROR( (SUMIF(tbl_Charges_Fixes[Famille affectée],tbl_Produits[[#This Row],[Famille]],tbl_Charges_Fixes[Montant_Mensuel])) / (SUMIF(tbl_Ventes[Famille],tbl_Produits[[#This Row],[Famille]],tbl_Ventes[Qté Vendue])), 0) -> 0

Sheet tbl_Recettes
A1: Produit | B1: Cde_Prdt | C1: Cde_Ingrdt | D1: Ingrédient | E1: Quantité | F1: Unité | G1: Coût Moyen Portion
A2: Norvégien | B2: PDJ001 | C2: BOU004 | D2: Toast Céréale | E2: 2 | F2: Pièce | G2: =IFERROR(tbl_Recettes[[#This Row],[Quantité]] * IFERROR(_xlfn.XLOOKUP(tbl_Recettes[[#This Row],[Cde_Ingrdt]], tbl_Stock[Cde_Ingrdt], tbl_Stock[CMP effectif]),0),0) -> 2.4
A3: Norvégien | B3: PDJ001 | C3: FRU002 | D3: Guacamole D’Avocat | E3: 50 | F3: g | G3: =IFERROR(tbl_Recettes[[#This Row],[Quantité]] * IFERROR(_xlfn.XLOOKUP(tbl_Recettes[[#This Row],[Cde_Ingrdt]], tbl_Stock[Cde_Ingrdt], tbl_Stock[CMP effectif]),0),0) -> 5
A4: Norvégien | B4: PDJ001 | C4: PRL001 | D4: Oeufs Entiers | E4: 2 | F4: Pièce | G4: =IFERROR(tbl_Recettes[[#This Row],[Quantité]] * IFERROR(_xlfn.XLOOKUP(tbl_Recettes[[#This Row],[Cde_Ingrdt]], tbl_Stock[Cde_Ingrdt], tbl_Stock[CMP effectif]),0),0) -> 1.8
A5: Norvégien | B5: PDJ001 | C5: POI001 | D5: Saumon Fumé | E5: 60 | F5: g | G5: =IFERROR(tbl_Recettes[[#This Row],[Quantité]] * IFERROR(_xlfn.XLOOKUP(tbl_Recettes[[#This Row],[Cde_Ingrdt]], tbl_Stock[Cde_Ingrdt], tbl_Stock[CMP effectif]),0),0) -> 34.2
A6: Norvégien | B6: PDJ001 | C6: PRL005 | D6: Fromage Blanc | E6: 40 | F6: g | G6: =IFERROR(tbl_Recettes[[#This Row],[Quantité]] * IFERROR(_xlfn.XLOOKUP(tbl_Recettes[[#This Row],[Cde_Ingrdt]], tbl_Stock[Cde_Ingrdt], tbl_Stock[CMP effectif]),0),0) -> 2
A7: Casserole turque | B7: PDJ002 | C7: BOU001 | D7: Pain Varie Pistolet | E7: 3 | F7: Pièce | G7: =IFERROR(tbl_Recettes[[#This Row],[Quantité]] * IFERROR(_xlfn.XLOOKUP(tbl_Recettes[[#This Row],[Cde_Ingrdt]], tbl_Stock[Cde_Ingrdt], tbl_Stock[CMP effectif]),0),0) -> 7.5
A8: Casserole turque | B8: PDJ002 | C8: PRL001 | D8: Oeufs Entiers | E8: 2 | F8: Pièce | G8: =IFERROR(tbl_Recettes[[#This Row],[Quantité]] * IFERROR(_xlfn.XLOOKUP(tbl_Recettes[[#This Row],[Cde_Ingrdt]], tbl_Stock[Cde_Ingrdt], tbl_Stock[CMP effectif]),0),0) -> 1.8
A9: Casserole turque | B9: PDJ002 | C9: SOS004 | D9: Sauce Tomate | E9: 60 | F9: ml | G9: =IFERROR(tbl_Recettes[[#This Row],[Quantité]] * IFERROR(_xlfn.XLOOKUP(tbl_Recettes[[#This Row],[Cde_Ingrdt]], tbl_Stock[Cde_Ingrdt], tbl_Stock[CMP effectif]),0),0) -> 9
A10: Casserole turque | B10: PDJ002 | C10: LEG003 | D10: Tomate Cerise | E10: 50 | F10: g | G10: =IFERROR(tbl_Recettes[[#This Row],[Quantité]] * IFERROR(_xlfn.XLOOKUP(tbl_Recettes[[#This Row],[Cde_Ingrdt]], tbl_Stock[Cde_Ingrdt], tbl_Stock[CMP effectif]),0),0) -> 2
A11: Casserole turque | B11: PDJ002 | C11: PRL009 | D11: Fromage Spécial | E11: 40 | F11: g | G11: =IFERROR(tbl_Recettes[[#This Row],[Quantité]] * IFERROR(_xlfn.XLOOKUP(tbl_Recettes[[#This Row],[Cde_Ingrdt]], tbl_Stock[Cde_Ingrdt], tbl_Stock[CMP effectif]),0),0) -> 16
A12: Casserole turque | B12: PDJ002 | C12: VEA001 | D12: Saucisse de Veau | E12: 60 | F12: g | G12: =IFERROR(tbl_Recettes[[#This Row],[Quantité]] * IFERROR(_xlfn.XLOOKUP(tbl_Recettes[[#This Row],[Cde_Ingrdt]], tbl_Stock[Cde_Ingrdt], tbl_Stock[CMP effectif]),0),0) -> 6
A13: Casserole turque | B13: PDJ002 | C13: PRL005 | D13: Fromage Blanc | E13: 40 | F13: g | G13: =IFERROR(tbl_Recettes[[#This Row],[Quantité]] * IFERROR(_xlfn.XLOOKUP(tbl_Recettes[[#This Row],[Cde_Ingrdt]], tbl_Stock[Cde_Ingrdt], tbl_Stock[CMP effectif]),0),0) -> 2
... A976: Soft drinks boisson énergétique | B976: BFR006 | C976: BOI012 | D976: Boisson énergétique | E976: 1 | F976: Pièce | G976: =IFERROR(tbl_Recettes[[#This Row],[Quantité]] * IFERROR(_xlfn.XLOOKUP(tbl_Recettes[[#This Row],[Cde_Ingrdt]], tbl_Stock[Cde_Ingrdt], tbl_Stock[CMP effectif]),0),0) -> 14

Sheet tbl_Stock
A1: Cde_Ingrdt | B1: Ingrédient | C1: Unité | D1: CMP Achat Unitaire | E1: Stock Départ | F1: Valeur stock initiale | G1: Achats Cumulées | H1: Valeur Achat | I1: Stock cuisine | J1: Valeur Stock Global | K1: Quantité totale | L1: CMP effectif | M1: Sortie cumulée | N1: Stock Courant | O1: Seuil critique | P1: Alerte
A2: =IFERROR(VLOOKUP(B2,Référentiels!$M$2:$N$267,2,FALSE),"Ingrédient non trouvé") -> BOU001 | B2: =+tbl_IngrédientsRef[[#This Row],[Ingrédient]] -> Pain Varie Pistolet | C2: =INDEX(tbl_IngrédientsRef[Unité], MATCH(A2, tbl_IngrédientsRef[Cde_Ingrdt],0)) -> Pièce | D2: =IFERROR(INDEX(tbl_IngrédientsRef[[#This Row],[PU_effectif_g/ml]], MATCH(tbl_Stock[[#This Row],[Cde_Ingrdt]], tbl_IngrédientsRef[[#This Row],[Cde_Ingrdt]], 0)), 0) -> 2.5 | E2: 1500 | F2: =tbl_Stock[[#This Row],[Stock Départ]] * INDEX(tbl_IngrédientsRef[Prix/Uni Base], MATCH(tbl_Stock[[#This Row],[Cde_Ingrdt]], tbl_IngrédientsRef[Cde_Ingrdt], 0)) -> 3750 | G2: =SUMIF(tbl_Achats[Cde_Ingrdt],tbl_Stock[[#This Row],[Cde_Ingrdt]],tbl_Achats[Qté d''Achat]) -> 0 | H2: {=SUMPRODUCT((tbl_Achats[Cde_Ingrdt]=tbl_Stock[[#This Row],[Cde_Ingrdt]]) * tbl_Achats[Qté d''Achat] * tbl_Achats[Prix Achat Unitaire])} -> 0 | I2: 250 | J2: =tbl_Stock[[#This Row],[Stock Courant]] * tbl_Stock[[#This Row],[CMP effectif]] -> 2500 | K2: =tbl_Stock[[#This Row],[Stock Départ]] + SUMIF(tbl_Achats[Cde_Ingrdt],tbl_Stock[[#This Row],[Cde_Ingrdt]],tbl_Achats[[#This Row],[Qté d''Achat]]) -> 1500 | L2: =IFERROR((tbl_Stock[[#This Row],[Valeur stock initiale]] + tbl_Stock[[#This Row],[ Valeur Achat]]) / tbl_Stock[[#This Row],[Quantité totale]], 0) -> 2.5 | M2: =SUMIF(tbl_Sorties[[Code ingrédient ]], tbl_Stock[[#This Row],[Cde_Ingrdt]], tbl_Sorties[Qté Sortie]) -> 500 | N2: =tbl_Stock[[#This Row],[Stock Départ]] + tbl_Stock[[#This Row],[Achats Cumulées]] - tbl_Stock[[#This Row],[ Sortie cumulée]] -> 1000 | O2: 1000 | P2: =IF(tbl_Stock[[#This Row],[Stock Courant]] < tbl_Stock[[#This Row],[Seuil critique]], "⚠️ Alerte", "OK") -> OK
A3: =IFERROR(VLOOKUP(B3,Référentiels!$M$2:$N$267,2,FALSE),"Ingrédient non trouvé") -> BOU002 | B3: =+tbl_IngrédientsRef[[#This Row],[Ingrédient]] -> Pain Berger | C3: =INDEX(tbl_IngrédientsRef[Unité], MATCH(A3, tbl_IngrédientsRef[Cde_Ingrdt],0)) -> Pièce | D3: =IFERROR(INDEX(tbl_IngrédientsRef[[#This Row],[PU_effectif_g/ml]], MATCH(tbl_Stock[[#This Row],[Cde_Ingrdt]], tbl_IngrédientsRef[[#This Row],[Cde_Ingrdt]], 0)), 0) -> 1.5 | E3: 1500 | F3: =tbl_Stock[[#This Row],[Stock Départ]] * INDEX(tbl_IngrédientsRef[Prix/Uni Base], MATCH(tbl_Stock[[#This Row],[Cde_Ingrdt]], tbl_IngrédientsRef[Cde_Ingrdt], 0)) -> 2250 | G3: =SUMIF(tbl_Achats[Cde_Ingrdt],tbl_Stock[[#This Row],[Cde_Ingrdt]],tbl_Achats[Qté d''Achat]) -> 0 | H3: {=SUMPRODUCT((tbl_Achats[Cde_Ingrdt]=tbl_Stock[[#This Row],[Cde_Ingrdt]]) * tbl_Achats[Qté d''Achat] * tbl_Achats[Prix Achat Unitaire])} -> 0 | I3: 230 | J3: =tbl_Stock[[#This Row],[Stock Courant]] * tbl_Stock[[#This Row],[CMP effectif]] -> 2250 | K3: =tbl_Stock[[#This Row],[Stock Départ]] + SUMIF(tbl_Achats[Cde_Ingrdt],tbl_Stock[[#This Row],[Cde_Ingrdt]],tbl_Achats[[#This Row],[Qté d''Achat]]) -> 1500 | L3: =IFERROR((tbl_Stock[[#This Row],[Valeur stock initiale]] + tbl_Stock[[#This Row],[ Valeur Achat]]) / tbl_Stock[[#This Row],[Quantité totale]], 0) -> 1.5 | M3: =SUMIF(tbl_Sorties[[Code ingrédient ]], tbl_Stock[[#This Row],[Cde_Ingrdt]], tbl_Sorties[Qté Sortie]) -> 0 | N3: =tbl_Stock[[#This Row],[Stock Départ]] + tbl_Stock[[#This Row],[Achats Cumulées]] - tbl_Stock[[#This Row],[ Sortie cumulée]] -> 1500 | O3: 80000 | P3: =IF(tbl_Stock[[#This Row],[Stock Courant]] < tbl_Stock[[#This Row],[Seuil critique]], "⚠️ Alerte", "OK") -> ⚠️ Alerte
A4: =IFERROR(VLOOKUP(B4,Référentiels!$M$2:$N$267,2,FALSE),"Ingrédient non trouvé") -> BOU003 | B4: =+tbl_IngrédientsRef[[#This Row],[Ingrédient]] -> Pain Grillé | C4: =INDEX(tbl_IngrédientsRef[Unité], MATCH(A4, tbl_IngrédientsRef[Cde_Ingrdt],0)) -> Pièce | D4: =IFERROR(INDEX(tbl_IngrédientsRef[[#This Row],[PU_effectif_g/ml]], MATCH(tbl_Stock[[#This Row],[Cde_Ingrdt]], tbl_IngrédientsRef[[#This Row],[Cde_Ingrdt]], 0)), 0) -> 2 | E4: 1500 | F4: =tbl_Stock[[#This Row],[Stock Départ]] * INDEX(tbl_IngrédientsRef[Prix/Uni Base], MATCH(tbl_Stock[[#This Row],[Cde_Ingrdt]], tbl_IngrédientsRef[Cde_Ingrdt], 0)) -> 3000 | G4: =SUMIF(tbl_Achats[Cde_Ingrdt],tbl_Stock[[#This Row],[Cde_Ingrdt]],tbl_Achats[Qté d''Achat]) -> 0 | H4: {=SUMPRODUCT((tbl_Achats[Cde_Ingrdt]=tbl_Stock[[#This Row],[Cde_Ingrdt]]) * tbl_Achats[Qté d''Achat] * tbl_Achats[Prix Achat Unitaire])} -> 0 | I4: 300 | J4: =tbl_Stock[[#This Row],[Stock Courant]] * tbl_Stock[[#This Row],[CMP effectif]] -> 3000 | K4: =tbl_Stock[[#This Row],[Stock Départ]] + SUMIF(tbl_Achats[Cde_Ingrdt],tbl_Stock[[#This Row],[Cde_Ingrdt]],tbl_Achats[[#This Row],[Qté d''Achat]]) -> 1500 | L4: =IFERROR((tbl_Stock[[#This Row],[Valeur stock initiale]] + tbl_Stock[[#This Row],[ Valeur Achat]]) / tbl_Stock[[#This Row],[Quantité totale]], 0) -> 2 | M4: =SUMIF(tbl_Sorties[[Code ingrédient ]], tbl_Stock[[#This Row],[Cde_Ingrdt]], tbl_Sorties[Qté Sortie]) -> 0 | N4: =tbl_Stock[[#This Row],[Stock Départ]] + tbl_Stock[[#This Row],[Achats Cumulées]] - tbl_Stock[[#This Row],[ Sortie cumulée]] -> 1500 | O4: 100 | P4: =IF(tbl_Stock[[#This Row],[Stock Courant]] < tbl_Stock[[#This Row],[Seuil critique]], "⚠️ Alerte", "OK") -> OK
A5: =IFERROR(VLOOKUP(B5,Référentiels!$M$2:$N$267,2,FALSE),"Ingrédient non trouvé") -> BOU004 | B5: =+tbl_IngrédientsRef[[#This Row],[Ingrédient]] -> Toast Céréale | C5: =INDEX(tbl_IngrédientsRef[Unité], MATCH(A5, tbl_IngrédientsRef[Cde_Ingrdt],0)) -> Pièce | D5: =IFERROR(INDEX(tbl_IngrédientsRef[[#This Row],[PU_effectif_g/ml]], MATCH(tbl_Stock[[#This Row],[Cde_Ingrdt]], tbl_IngrédientsRef[[#This Row],[Cde_Ingrdt]], 0)), 0) -> 1.2 | E5: 1500 | F5: =tbl_Stock[[#This Row],[Stock Départ]] * INDEX(tbl_IngrédientsRef[Prix/Uni Base], MATCH(tbl_Stock[[#This Row],[Cde_Ingrdt]], tbl_IngrédientsRef[Cde_Ingrdt], 0)) -> 1800 | G5: =SUMIF(tbl_Achats[Cde_Ingrdt],tbl_Stock[[#This Row],[Cde_Ingrdt]],tbl_Achats[Qté d''Achat]) -> 0 | H5: {=SUMPRODUCT((tbl_Achats[Cde_Ingrdt]=tbl_Stock[[#This Row],[Cde_Ingrdt]]) * tbl_Achats[Qté d''Achat] * tbl_Achats[Prix Achat Unitaire])} -> 0 | I5: 340 | J5: =tbl_Stock[[#This Row],[Stock Courant]] * tbl_Stock[[#This Row],[CMP effectif]] -> 1788 | K5: =tbl_Stock[[#This Row],[Stock Départ]] + SUMIF(tbl_Achats[Cde_Ingrdt],tbl_Stock[[#This Row],[Cde_Ingrdt]],tbl_Achats[[#This Row],[Qté d''Achat]]) -> 1500 | L5: =IFERROR((tbl_Stock[[#This Row],[Valeur stock initiale]] + tbl_Stock[[#This Row],[ Valeur Achat]]) / tbl_Stock[[#This Row],[Quantité totale]], 0) -> 1.2 | M5: =SUMIF(tbl_Sorties[[Code ingrédient ]], tbl_Stock[[#This Row],[Cde_Ingrdt]], tbl_Sorties[Qté Sortie]) -> 10 | N5: =tbl_Stock[[#This Row],[Stock Départ]] + tbl_Stock[[#This Row],[Achats Cumulées]] - tbl_Stock[[#This Row],[ Sortie cumulée]] -> 1490 | O5: 100 | P5: =IF(tbl_Stock[[#This Row],[Stock Courant]] < tbl_Stock[[#This Row],[Seuil critique]], "⚠️ Alerte", "OK") -> OK
A6: =IFERROR(VLOOKUP(B6,Référentiels!$M$2:$N$267,2,FALSE),"Ingrédient non trouvé") -> BOU005 | B6: =+tbl_IngrédientsRef[[#This Row],[Ingrédient]] -> Croissant | C6: =INDEX(tbl_IngrédientsRef[Unité], MATCH(A6, tbl_IngrédientsRef[Cde_Ingrdt],0)) -> Pièce | D6: =IFERROR(INDEX(tbl_IngrédientsRef[[#This Row],[PU_effectif_g/ml]], MATCH(tbl_Stock[[#This Row],[Cde_Ingrdt]], tbl_IngrédientsRef[[#This Row],[Cde_Ingrdt]], 0)), 0) -> 4 | E6: 1500 | F6: =tbl_Stock[[#This Row],[Stock Départ]] * INDEX(tbl_IngrédientsRef[Prix/Uni Base], MATCH(tbl_Stock[[#This Row],[Cde_Ingrdt]], tbl_IngrédientsRef[Cde_Ingrdt], 0)) -> 6000 | G6: =SUMIF(tbl_Achats[Cde_Ingrdt],tbl_Stock[[#This Row],[Cde_Ingrdt]],tbl_Achats[Qté d''Achat]) -> 0 | H6: {=SUMPRODUCT((tbl_Achats[Cde_Ingrdt]=tbl_Stock[[#This Row],[Cde_Ingrdt]]) * tbl_Achats[Qté d''Achat] * tbl_Achats[Prix Achat Unitaire])} -> 0 | I6: 250 | J6: =tbl_Stock[[#This Row],[Stock Courant]] * tbl_Stock[[#This Row],[CMP effectif]] -> 6000 | K6: =tbl_Stock[[#This Row],[Stock Départ]] + SUMIF(tbl_Achats[Cde_Ingrdt],tbl_Stock[[#This Row],[Cde_Ingrdt]],tbl_Achats[[#This Row],[Qté d''Achat]]) -> 1500 | L6: =IFERROR((tbl_Stock[[#This Row],[Valeur stock initiale]] + tbl_Stock[[#This Row],[ Valeur Achat]]) / tbl_Stock[[#This Row],[Quantité totale]], 0) -> 4 | M6: =SUMIF(tbl_Sorties[[Code ingrédient ]], tbl_Stock[[#This Row],[Cde_Ingrdt]], tbl_Sorties[Qté Sortie]) -> 0 | N6: =tbl_Stock[[#This Row],[Stock Départ]] + tbl_Stock[[#This Row],[Achats Cumulées]] - tbl_Stock[[#This Row],[ Sortie cumulée]] -> 1500 | O6: 100 | P6: =IF(tbl_Stock[[#This Row],[Stock Courant]] < tbl_Stock[[#This Row],[Seuil critique]], "⚠️ Alerte", "OK") -> OK
A7: =IFERROR(VLOOKUP(B7,Référentiels!$M$2:$N$267,2,FALSE),"Ingrédient non trouvé") -> BOU006 | B7: =+tbl_IngrédientsRef[[#This Row],[Ingrédient]] -> Pain Au Chocolat P | C7: =INDEX(tbl_IngrédientsRef[Unité], MATCH(A7, tbl_IngrédientsRef[Cde_Ingrdt],0)) -> Pièce | D7: =IFERROR(INDEX(tbl_IngrédientsRef[[#This Row],[PU_effectif_g/ml]], MATCH(tbl_Stock[[#This Row],[Cde_Ingrdt]], tbl_IngrédientsRef[[#This Row],[Cde_Ingrdt]], 0)), 0) -> 3 | E7: 1500 | F7: =tbl_Stock[[#This Row],[Stock Départ]] * INDEX(tbl_IngrédientsRef[Prix/Uni Base], MATCH(tbl_Stock[[#This Row],[Cde_Ingrdt]], tbl_IngrédientsRef[Cde_Ingrdt], 0)) -> 4500 | G7: =SUMIF(tbl_Achats[Cde_Ingrdt],tbl_Stock[[#This Row],[Cde_Ingrdt]],tbl_Achats[Qté d''Achat]) -> 0 | H7: {=SUMPRODUCT((tbl_Achats[Cde_Ingrdt]=tbl_Stock[[#This Row],[Cde_Ingrdt]]) * tbl_Achats[Qté d''Achat] * tbl_Achats[Prix Achat Unitaire])} -> 0 | I7: 230 | J7: =tbl_Stock[[#This Row],[Stock Courant]] * tbl_Stock[[#This Row],[CMP effectif]] -> 4500 | K7: =tbl_Stock[[#This Row],[Stock Départ]] + SUMIF(tbl_Achats[Cde_Ingrdt],tbl_Stock[[#This Row],[Cde_Ingrdt]],tbl_Achats[[#This Row],[Qté d''Achat]]) -> 1500 | L7: =IFERROR((tbl_Stock[[#This Row],[Valeur stock initiale]] + tbl_Stock[[#This Row],[ Valeur Achat]]) / tbl_Stock[[#This Row],[Quantité totale]], 0) -> 3 | M7: =SUMIF(tbl_Sorties[[Code ingrédient ]], tbl_Stock[[#This Row],[Cde_Ingrdt]], tbl_Sorties[Qté Sortie]) -> 0 | N7: =tbl_Stock[[#This Row],[Stock Départ]] + tbl_Stock[[#This Row],[Achats Cumulées]] - tbl_Stock[[#This Row],[ Sortie cumulée]] -> 1500 | O7: 100 | P7: =IF(tbl_Stock[[#This Row],[Stock Courant]] < tbl_Stock[[#This Row],[Seuil critique]], "⚠️ Alerte", "OK") -> OK
A8: =IFERROR(VLOOKUP(B8,Référentiels!$M$2:$N$267,2,FALSE),"Ingrédient non trouvé") -> BOU007 | B8: =+tbl_IngrédientsRef[[#This Row],[Ingrédient]] -> Pain Au Chocolat G | C8: =INDEX(tbl_IngrédientsRef[Unité], MATCH(A8, tbl_IngrédientsRef[Cde_Ingrdt],0)) -> Pièce | D8: =IFERROR(INDEX(tbl_IngrédientsRef[[#This Row],[PU_effectif_g/ml]], MATCH(tbl_Stock[[#This Row],[Cde_Ingrdt]], tbl_IngrédientsRef[[#This Row],[Cde_Ingrdt]], 0)), 0) -> 7 | E8: 1500 | F8: =tbl_Stock[[#This Row],[Stock Départ]] * INDEX(tbl_IngrédientsRef[Prix/Uni Base], MATCH(tbl_Stock[[#This Row],[Cde_Ingrdt]], tbl_IngrédientsRef[Cde_Ingrdt], 0)) -> 10500 | G8: =SUMIF(tbl_Achats[Cde_Ingrdt],tbl_Stock[[#This Row],[Cde_Ingrdt]],tbl_Achats[Qté d''Achat]) -> 0 | H8: {=SUMPRODUCT((tbl_Achats[Cde_Ingrdt]=tbl_Stock[[#This Row],[Cde_Ingrdt]]) * tbl_Achats[Qté d''Achat] * tbl_Achats[Prix Achat Unitaire])} -> 0 | I8: 300 | J8: =tbl_Stock[[#This Row],[Stock Courant]] * tbl_Stock[[#This Row],[CMP effectif]] -> 10500 | K8: =tbl_Stock[[#This Row],[Stock Départ]] + SUMIF(tbl_Achats[Cde_Ingrdt],tbl_Stock[[#This Row],[Cde_Ingrdt]],tbl_Achats[[#This Row],[Qté d''Achat]]) -> 1500 | L8: =IFERROR((tbl_Stock[[#This Row],[Valeur stock initiale]] + tbl_Stock[[#This Row],[ Valeur Achat]]) / tbl_Stock[[#This Row],[Quantité totale]], 0) -> 7 | M8: =SUMIF(tbl_Sorties[[Code ingrédient ]], tbl_Stock[[#This Row],[Cde_Ingrdt]], tbl_Sorties[Qté Sortie]) -> 0 | N8: =tbl_Stock[[#This Row],[Stock Départ]] + tbl_Stock[[#This Row],[Achats Cumulées]] - tbl_Stock[[#This Row],[ Sortie cumulée]] -> 1500 | O8: 100 | P8: =IF(tbl_Stock[[#This Row],[Stock Courant]] < tbl_Stock[[#This Row],[Seuil critique]], "⚠️ Alerte", "OK") -> OK
A9: =IFERROR(VLOOKUP(B9,Référentiels!$M$2:$N$267,2,FALSE),"Ingrédient non trouvé") -> BOU008 | B9: =+tbl_IngrédientsRef[[#This Row],[Ingrédient]] -> Rghifa | C9: =INDEX(tbl_IngrédientsRef[Unité], MATCH(A9, tbl_IngrédientsRef[Cde_Ingrdt],0)) -> Pièce | D9: =IFERROR(INDEX(tbl_IngrédientsRef[[#This Row],[PU_effectif_g/ml]], MATCH(tbl_Stock[[#This Row],[Cde_Ingrdt]], tbl_IngrédientsRef[[#This Row],[Cde_Ingrdt]], 0)), 0) -> 2 | E9: 1500 | F9: =tbl_Stock[[#This Row],[Stock Départ]] * INDEX(tbl_IngrédientsRef[Prix/Uni Base], MATCH(tbl_Stock[[#This Row],[Cde_Ingrdt]], tbl_IngrédientsRef[Cde_Ingrdt], 0)) -> 3000 | G9: =SUMIF(tbl_Achats[Cde_Ingrdt],tbl_Stock[[#This Row],[Cde_Ingrdt]],tbl_Achats[Qté d''Achat]) -> 0 | H9: {=SUMPRODUCT((tbl_Achats[Cde_Ingrdt]=tbl_Stock[[#This Row],[Cde_Ingrdt]]) * tbl_Achats[Qté d''Achat] * tbl_Achats[Prix Achat Unitaire])} -> 0 | I9: 340 | J9: =tbl_Stock[[#This Row],[Stock Courant]] * tbl_Stock[[#This Row],[CMP effectif]] -> 3000 | K9: =tbl_Stock[[#This Row],[Stock Départ]] + SUMIF(tbl_Achats[Cde_Ingrdt],tbl_Stock[[#This Row],[Cde_Ingrdt]],tbl_Achats[[#This Row],[Qté d''Achat]]) -> 1500 | L9: =IFERROR((tbl_Stock[[#This Row],[Valeur stock initiale]] + tbl_Stock[[#This Row],[ Valeur Achat]]) / tbl_Stock[[#This Row],[Quantité totale]], 0) -> 2 | M9: =SUMIF(tbl_Sorties[[Code ingrédient ]], tbl_Stock[[#This Row],[Cde_Ingrdt]], tbl_Sorties[Qté Sortie]) -> 0 | N9: =tbl_Stock[[#This Row],[Stock Départ]] + tbl_Stock[[#This Row],[Achats Cumulées]] - tbl_Stock[[#This Row],[ Sortie cumulée]] -> 1500 | O9: 100 | P9: =IF(tbl_Stock[[#This Row],[Stock Courant]] < tbl_Stock[[#This Row],[Seuil critique]], "⚠️ Alerte", "OK") -> OK
A10: =IFERROR(VLOOKUP(B10,Référentiels!$M$2:$N$267,2,FALSE),"Ingrédient non trouvé") -> BOU009 | B10: =+tbl_IngrédientsRef[[#This Row],[Ingrédient]] -> Harcha | C10: =INDEX(tbl_IngrédientsRef[Unité], MATCH(A10, tbl_IngrédientsRef[Cde_Ingrdt],0)) -> Pièce | D10: =IFERROR(INDEX(tbl_IngrédientsRef[[#This Row],[PU_effectif_g/ml]], MATCH(tbl_Stock[[#This Row],[Cde_Ingrdt]], tbl_IngrédientsRef[[#This Row],[Cde_Ingrdt]], 0)), 0) -> 2 | E10: 1500 | F10: =tbl_Stock[[#This Row],[Stock Départ]] * INDEX(tbl_IngrédientsRef[Prix/Uni Base], MATCH(tbl_Stock[[#This Row],[Cde_Ingrdt]], tbl_IngrédientsRef[Cde_Ingrdt], 0)) -> 3000 | G10: =SUMIF(tbl_Achats[Cde_Ingrdt],tbl_Stock[[#This Row],[Cde_Ingrdt]],tbl_Achats[Qté d''Achat]) -> 0 | H10: {=SUMPRODUCT((tbl_Achats[Cde_Ingrdt]=tbl_Stock[[#This Row],[Cde_Ingrdt]]) * tbl_Achats[Qté d''Achat] * tbl_Achats[Prix Achat Unitaire])} -> 0 | I10: 250 | J10: =tbl_Stock[[#This Row],[Stock Courant]] * tbl_Stock[[#This Row],[CMP effectif]] -> 3000 | K10: =tbl_Stock[[#This Row],[Stock Départ]] + SUMIF(tbl_Achats[Cde_Ingrdt],tbl_Stock[[#This Row],[Cde_Ingrdt]],tbl_Achats[[#This Row],[Qté d''Achat]]) -> 1500 | L10: =IFERROR((tbl_Stock[[#This Row],[Valeur stock initiale]] + tbl_Stock[[#This Row],[ Valeur Achat]]) / tbl_Stock[[#This Row],[Quantité totale]], 0) -> 2 | M10: =SUMIF(tbl_Sorties[[Code ingrédient ]], tbl_Stock[[#This Row],[Cde_Ingrdt]], tbl_Sorties[Qté Sortie]) -> 0 | N10: =tbl_Stock[[#This Row],[Stock Départ]] + tbl_Stock[[#This Row],[Achats Cumulées]] - tbl_Stock[[#This Row],[ Sortie cumulée]] -> 1500 | O10: 100 | P10: =IF(tbl_Stock[[#This Row],[Stock Courant]] < tbl_Stock[[#This Row],[Seuil critique]], "⚠️ Alerte", "OK") -> OK
A11: =IFERROR(VLOOKUP(B11,Référentiels!$M$2:$N$267,2,FALSE),"Ingrédient non trouvé") -> BOU010 | B11: =+tbl_IngrédientsRef[[#This Row],[Ingrédient]] -> Baghrire | C11: =INDEX(tbl_IngrédientsRef[Unité], MATCH(A11, tbl_IngrédientsRef[Cde_Ingrdt],0)) -> Pièce | D11: =IFERROR(INDEX(tbl_IngrédientsRef[[#This Row],[PU_effectif_g/ml]], MATCH(tbl_Stock[[#This Row],[Cde_Ingrdt]], tbl_IngrédientsRef[[#This Row],[Cde_Ingrdt]], 0)), 0) -> 2 | E11: 1500 | F11: =tbl_Stock[[#This Row],[Stock Départ]] * INDEX(tbl_IngrédientsRef[Prix/Uni Base], MATCH(tbl_Stock[[#This Row],[Cde_Ingrdt]], tbl_IngrédientsRef[Cde_Ingrdt], 0)) -> 3000 | G11: =SUMIF(tbl_Achats[Cde_Ingrdt],tbl_Stock[[#This Row],[Cde_Ingrdt]],tbl_Achats[Qté d''Achat]) -> 0 | H11: {=SUMPRODUCT((tbl_Achats[Cde_Ingrdt]=tbl_Stock[[#This Row],[Cde_Ingrdt]]) * tbl_Achats[Qté d''Achat] * tbl_Achats[Prix Achat Unitaire])} -> 0 | I11: 230 | J11: =tbl_Stock[[#This Row],[Stock Courant]] * tbl_Stock[[#This Row],[CMP effectif]] -> 3000 | K11: =tbl_Stock[[#This Row],[Stock Départ]] + SUMIF(tbl_Achats[Cde_Ingrdt],tbl_Stock[[#This Row],[Cde_Ingrdt]],tbl_Achats[[#This Row],[Qté d''Achat]]) -> 1500 | L11: =IFERROR((tbl_Stock[[#This Row],[Valeur stock initiale]] + tbl_Stock[[#This Row],[ Valeur Achat]]) / tbl_Stock[[#This Row],[Quantité totale]], 0) -> 2 | M11: =SUMIF(tbl_Sorties[[Code ingrédient ]], tbl_Stock[[#This Row],[Cde_Ingrdt]], tbl_Sorties[Qté Sortie]) -> 0 | N11: =tbl_Stock[[#This Row],[Stock Départ]] + tbl_Stock[[#This Row],[Achats Cumulées]] - tbl_Stock[[#This Row],[ Sortie cumulée]] -> 1500 | O11: 100 | P11: =IF(tbl_Stock[[#This Row],[Stock Courant]] < tbl_Stock[[#This Row],[Seuil critique]], "⚠️ Alerte", "OK") -> OK
A12: =IFERROR(VLOOKUP(B12,Référentiels!$M$2:$N$267,2,FALSE),"Ingrédient non trouvé") -> BOU011 | B12: =+tbl_IngrédientsRef[[#This Row],[Ingrédient]] -> Pizza Base | C12: =INDEX(tbl_IngrédientsRef[Unité], MATCH(A12, tbl_IngrédientsRef[Cde_Ingrdt],0)) -> Pièce | D12: =IFERROR(INDEX(tbl_IngrédientsRef[[#This Row],[PU_effectif_g/ml]], MATCH(tbl_Stock[[#This Row],[Cde_Ingrdt]], tbl_IngrédientsRef[[#This Row],[Cde_Ingrdt]], 0)), 0) -> 5 | E12: 1500 | F12: =tbl_Stock[[#This Row],[Stock Départ]] * INDEX(tbl_IngrédientsRef[Prix/Uni Base], MATCH(tbl_Stock[[#This Row],[Cde_Ingrdt]], tbl_IngrédientsRef[Cde_Ingrdt], 0)) -> 7500 | G12: =SUMIF(tbl_Achats[Cde_Ingrdt],tbl_Stock[[#This Row],[Cde_Ingrdt]],tbl_Achats[Qté d''Achat]) -> 0 | H12: {=SUMPRODUCT((tbl_Achats[Cde_Ingrdt]=tbl_Stock[[#This Row],[Cde_Ingrdt]]) * tbl_Achats[Qté d''Achat] * tbl_Achats[Prix Achat Unitaire])} -> 0 | I12: 300 | J12: =tbl_Stock[[#This Row],[Stock Courant]] * tbl_Stock[[#This Row],[CMP effectif]] -> 7500 | K12: =tbl_Stock[[#This Row],[Stock Départ]] + SUMIF(tbl_Achats[Cde_Ingrdt],tbl_Stock[[#This Row],[Cde_Ingrdt]],tbl_Achats[[#This Row],[Qté d''Achat]]) -> 1500 | L12: =IFERROR((tbl_Stock[[#This Row],[Valeur stock initiale]] + tbl_Stock[[#This Row],[ Valeur Achat]]) / tbl_Stock[[#This Row],[Quantité totale]], 0) -> 5 | M12: =SUMIF(tbl_Sorties[[Code ingrédient ]], tbl_Stock[[#This Row],[Cde_Ingrdt]], tbl_Sorties[Qté Sortie]) -> 0 | N12: =tbl_Stock[[#This Row],[Stock Départ]] + tbl_Stock[[#This Row],[Achats Cumulées]] - tbl_Stock[[#This Row],[ Sortie cumulée]] -> 1500 | O12: 100 | P12: =IF(tbl_Stock[[#This Row],[Stock Courant]] < tbl_Stock[[#This Row],[Seuil critique]], "⚠️ Alerte", "OK") -> OK
A13: =IFERROR(VLOOKUP(B13,Référentiels!$M$2:$N$267,2,FALSE),"Ingrédient non trouvé") -> BOU012 | B13: =+tbl_IngrédientsRef[[#This Row],[Ingrédient]] -> Croûtons | C13: =INDEX(tbl_IngrédientsRef[Unité], MATCH(A13, tbl_IngrédientsRef[Cde_Ingrdt],0)) -> g | D13: =IFERROR(INDEX(tbl_IngrédientsRef[[#This Row],[PU_effectif_g/ml]], MATCH(tbl_Stock[[#This Row],[Cde_Ingrdt]], tbl_IngrédientsRef[[#This Row],[Cde_Ingrdt]], 0)), 0) -> 0.2 | E13: 1500 | F13: =tbl_Stock[[#This Row],[Stock Départ]] * INDEX(tbl_IngrédientsRef[Prix/Uni Base], MATCH(tbl_Stock[[#This Row],[Cde_Ingrdt]], tbl_IngrédientsRef[Cde_Ingrdt], 0)) -> 300 | G13: =SUMIF(tbl_Achats[Cde_Ingrdt],tbl_Stock[[#This Row],[Cde_Ingrdt]],tbl_Achats[Qté d''Achat]) -> 0 | H13: {=SUMPRODUCT((tbl_Achats[Cde_Ingrdt]=tbl_Stock[[#This Row],[Cde_Ingrdt]]) * tbl_Achats[Qté d''Achat] * tbl_Achats[Prix Achat Unitaire])} -> 0 | I13: 340 | J13: =tbl_Stock[[#This Row],[Stock Courant]] * tbl_Stock[[#This Row],[CMP effectif]] -> 300 | K13: =tbl_Stock[[#This Row],[Stock Départ]] + SUMIF(tbl_Achats[Cde_Ingrdt],tbl_Stock[[#This Row],[Cde_Ingrdt]],tbl_Achats[[#This Row],[Qté d''Achat]]) -> 1500 | L13: =IFERROR((tbl_Stock[[#This Row],[Valeur stock initiale]] + tbl_Stock[[#This Row],[ Valeur Achat]]) / tbl_Stock[[#This Row],[Quantité totale]], 0) -> 0.2 | M13: =SUMIF(tbl_Sorties[[Code ingrédient ]], tbl_Stock[[#This Row],[Cde_Ingrdt]], tbl_Sorties[Qté Sortie]) -> 0 | N13: =tbl_Stock[[#This Row],[Stock Départ]] + tbl_Stock[[#This Row],[Achats Cumulées]] - tbl_Stock[[#This Row],[ Sortie cumulée]] -> 1500 | O13: 100 | P13: =IF(tbl_Stock[[#This Row],[Stock Courant]] < tbl_Stock[[#This Row],[Seuil critique]], "⚠️ Alerte", "OK") -> OK
... A267: =IFERROR(VLOOKUP(B267,Référentiels!$M$2:$N$267,2,FALSE),"Ingrédient non trouvé") -> BOI014 | B267: =+tbl_IngrédientsRef[[#This Row],[Ingrédient]] -> Thé Chamali | C267: =INDEX(tbl_IngrédientsRef[Unité], MATCH(A267, tbl_IngrédientsRef[Cde_Ingrdt],0)) -> Pièce | D267: =IFERROR(INDEX(tbl_IngrédientsRef[[#This Row],[PU_effectif_g/ml]], MATCH(tbl_Stock[[#This Row],[Cde_Ingrdt]], tbl_IngrédientsRef[[#This Row],[Cde_Ingrdt]], 0)), 0) -> 1 | E267: 1500 | F267: =tbl_Stock[[#This Row],[Stock Départ]] * INDEX(tbl_IngrédientsRef[Prix/Uni Base], MATCH(tbl_Stock[[#This Row],[Cde_Ingrdt]], tbl_IngrédientsRef[Cde_Ingrdt], 0)) -> 1500 | G267: =SUMIF(tbl_Achats[Cde_Ingrdt],tbl_Stock[[#This Row],[Cde_Ingrdt]],tbl_Achats[Qté d''Achat]) -> 0 | H267: {=SUMPRODUCT((tbl_Achats[Cde_Ingrdt]=tbl_Stock[[#This Row],[Cde_Ingrdt]]) * tbl_Achats[Qté d''Achat] * tbl_Achats[Prix Achat Unitaire])} -> 0 | I267: 340 | J267: =tbl_Stock[[#This Row],[Stock Courant]] * tbl_Stock[[#This Row],[CMP effectif]] -> 1500 | K267: =tbl_Stock[[#This Row],[Stock Départ]] + SUMIF(tbl_Achats[Cde_Ingrdt],tbl_Stock[[#This Row],[Cde_Ingrdt]],tbl_Achats[[#This Row],[Qté d''Achat]]) -> 1500 | L267: =IFERROR((tbl_Stock[[#This Row],[Valeur stock initiale]] + tbl_Stock[[#This Row],[ Valeur Achat]]) / tbl_Stock[[#This Row],[Quantité totale]], 0) -> 1 | M267: =SUMIF(tbl_Sorties[[Code ingrédient ]], tbl_Stock[[#This Row],[Cde_Ingrdt]], tbl_Sorties[Qté Sortie]) -> 0 | N267: =tbl_Stock[[#This Row],[Stock Départ]] + tbl_Stock[[#This Row],[Achats Cumulées]] - tbl_Stock[[#This Row],[ Sortie cumulée]] -> 1500 | O267: 100 | P267: =IF(tbl_Stock[[#This Row],[Stock Courant]] < tbl_Stock[[#This Row],[Seuil critique]], "⚠️ Alerte", "OK") -> OK

Sheet tbl_Achats
A1: Date | B1: Réf Achat / N° BL | C1: Fournisseur | D1: Cde_Ingrdt | E1: Nom Ingrédient | F1: Qté d'Achat | G1: Unité d'Achat | H1: Prix Achat Unitaire | I1: Valeur Ligne
D2: =IFERROR(VLOOKUP(E2,Référentiels!$M$2:$N$267,2,FALSE),"Ingrédient non trouvé") -> BOU001 | E2: Pain Varie Pistolet | F2: 0 | G2: Pièce | H2: 0 | I2: =IFERROR(tbl_Achats[[#This Row],[Qté d''Achat]] * tbl_Achats[[#This Row],[Prix Achat Unitaire]], 0) -> 0
D3: =IFERROR(VLOOKUP(E3,Référentiels!$M$2:$N$267,2,FALSE),"Ingrédient non trouvé") -> BOU001 | E3: Pain Varie Pistolet | F3: 0 | G3: Pièce | H3: 0 | I3: =IFERROR(tbl_Achats[[#This Row],[Qté d''Achat]] * tbl_Achats[[#This Row],[Prix Achat Unitaire]], 0) -> 0 | R3: g
D4: =IFERROR(VLOOKUP(E4,Référentiels!$M$2:$N$267,2,FALSE),"Ingrédient non trouvé") -> FRU004 | E4: Banane | F4: 0 | G4: Kg | H4: 0 | I4: =IFERROR(tbl_Achats[[#This Row],[Qté d''Achat]] * tbl_Achats[[#This Row],[Prix Achat Unitaire]], 0) -> 0 | R4: ml
D5: =IFERROR(VLOOKUP(E5,Référentiels!$M$2:$N$267,2,FALSE),"Ingrédient non trouvé") -> FRU004 | E5: Banane | F5: 0 | G5: Kg | H5: 0 | I5: =IFERROR(tbl_Achats[[#This Row],[Qté d''Achat]] * tbl_Achats[[#This Row],[Prix Achat Unitaire]], 0) -> 0 | R5: Kg
D6: =IFERROR(VLOOKUP(E6,Référentiels!$M$2:$N$267,2,FALSE),"Ingrédient non trouvé") -> BOI008 | E6: Eau Minérale 1,5L | F6: 0 | G6: Pièce | H6: 0 | I6: =IFERROR(tbl_Achats[[#This Row],[Qté d''Achat]] * tbl_Achats[[#This Row],[Prix Achat Unitaire]], 0) -> 0 | R6: L
D7: =IFERROR(VLOOKUP(E7,Référentiels!$M$2:$N$267,2,FALSE),"Ingrédient non trouvé") -> BOI009 | E7: Eau Minérale 50Cl | F7: 0 | G7: Pièce | H7: 0 | I7: =IFERROR(tbl_Achats[[#This Row],[Qté d''Achat]] * tbl_Achats[[#This Row],[Prix Achat Unitaire]], 0) -> 0 | R7: Pièce
D8: =IFERROR(VLOOKUP(E8,Référentiels!$M$2:$N$267,2,FALSE),"Ingrédient non trouvé") -> BOI010 | E8: Eau Minérale 33Cl | F8: 0 | G8: Pièce | H8: 0 | I8: =IFERROR(tbl_Achats[[#This Row],[Qté d''Achat]] * tbl_Achats[[#This Row],[Prix Achat Unitaire]], 0) -> 0
D9: =IFERROR(VLOOKUP(E9,Référentiels!$M$2:$N$267,2,FALSE),"Ingrédient non trouvé") -> BOU004 | E9: Toast Céréale | F9: 0 | G9: Pièce | H9: 0 | I9: =IFERROR(tbl_Achats[[#This Row],[Qté d''Achat]] * tbl_Achats[[#This Row],[Prix Achat Unitaire]], 0) -> 0
D10: =IFERROR(VLOOKUP(E10,Référentiels!$M$2:$N$267,2,FALSE),"Ingrédient non trouvé") -> BOU003 | E10: Pain Grillé | I10: =IFERROR(tbl_Achats[[#This Row],[Qté d''Achat]] * tbl_Achats[[#This Row],[Prix Achat Unitaire]], 0) -> 0
D11: =IFERROR(VLOOKUP(E11,Référentiels!$M$2:$N$267,2,FALSE),"Ingrédient non trouvé") -> BOE007 | E11: Emincé De Viande | I11: =IFERROR(tbl_Achats[[#This Row],[Qté d''Achat]] * tbl_Achats[[#This Row],[Prix Achat Unitaire]], 0) -> 0
D12: =IFERROR(VLOOKUP(E12,Référentiels!$M$2:$N$267,2,FALSE),"Ingrédient non trouvé") -> BOU004 | E12: Toast Céréale | I12: =IFERROR(tbl_Achats[[#This Row],[Qté d''Achat]] * tbl_Achats[[#This Row],[Prix Achat Unitaire]], 0) -> 0
D13: =IFERROR(VLOOKUP(E13,Référentiels!$M$2:$N$267,2,FALSE),"Ingrédient non trouvé") -> Ingrédient non trouvé | I13: =IFERROR(tbl_Achats[[#This Row],[Qté d''Achat]] * tbl_Achats[[#This Row],[Prix Achat Unitaire]], 0) -> 0
D14: =IFERROR(VLOOKUP(E14,Référentiels!$M$2:$N$267,2,FALSE),"Ingrédient non trouvé") -> Ingrédient non trouvé | I14: =IFERROR(tbl_Achats[[#This Row],[Qté d''Achat]] * tbl_Achats[[#This Row],[Prix Achat Unitaire]], 0) -> 0
D15: =IFERROR(VLOOKUP(E15,Référentiels!$M$2:$N$267,2,FALSE),"Ingrédient non trouvé") -> Ingrédient non trouvé | I15: =IFERROR(tbl_Achats[[#This Row],[Qté d''Achat]] * tbl_Achats[[#This Row],[Prix Achat Unitaire]], 0) -> 0
D16: =IFERROR(VLOOKUP(E16,Référentiels!$M$2:$N$267,2,FALSE),"Ingrédient non trouvé") -> Ingrédient non trouvé | I16: =IFERROR(tbl_Achats[[#This Row],[Qté d''Achat]] * tbl_Achats[[#This Row],[Prix Achat Unitaire]], 0) -> 0
D17: =IFERROR(VLOOKUP(E17,Référentiels!$M$2:$N$267,2,FALSE),"Ingrédient non trouvé") -> Ingrédient non trouvé | I17: =IFERROR(tbl_Achats[[#This Row],[Qté d''Achat]] * tbl_Achats[[#This Row],[Prix Achat Unitaire]], 0) -> 0
D18: =IFERROR(VLOOKUP(E18,Référentiels!$M$2:$N$267,2,FALSE),"Ingrédient non trouvé") -> Ingrédient non trouvé | I18: =IFERROR(tbl_Achats[[#This Row],[Qté d''Achat]] * tbl_Achats[[#This Row],[Prix Achat Unitaire]], 0) -> 0
D19: =IFERROR(VLOOKUP(E19,Référentiels!$M$2:$N$267,2,FALSE),"Ingrédient non trouvé") -> Ingrédient non trouvé | I19: =IFERROR(tbl_Achats[[#This Row],[Qté d''Achat]] * tbl_Achats[[#This Row],[Prix Achat Unitaire]], 0) -> 0
D20: =IFERROR(VLOOKUP(E20,Référentiels!$M$2:$N$267,2,FALSE),"Ingrédient non trouvé") -> Ingrédient non trouvé | I20: =IFERROR(tbl_Achats[[#This Row],[Qté d''Achat]] * tbl_Achats[[#This Row],[Prix Achat Unitaire]], 0) -> 0
D21: =IFERROR(VLOOKUP(E21,Référentiels!$M$2:$N$267,2,FALSE),"Ingrédient non trouvé") -> Ingrédient non trouvé | I21: =IFERROR(tbl_Achats[[#This Row],[Qté d''Achat]] * tbl_Achats[[#This Row],[Prix Achat Unitaire]], 0) -> 0
D22: =IFERROR(VLOOKUP(E22,Référentiels!$M$2:$N$267,2,FALSE),"Ingrédient non trouvé") -> Ingrédient non trouvé | I22: =IFERROR(tbl_Achats[[#This Row],[Qté d''Achat]] * tbl_Achats[[#This Row],[Prix Achat Unitaire]], 0) -> 0
D23: =IFERROR(VLOOKUP(E23,Référentiels!$M$2:$N$267,2,FALSE),"Ingrédient non trouvé") -> Ingrédient non trouvé | I23: =IFERROR(tbl_Achats[[#This Row],[Qté d''Achat]] * tbl_Achats[[#This Row],[Prix Achat Unitaire]], 0) -> 0
D24: =IFERROR(VLOOKUP(E24,Référentiels!$M$2:$N$267,2,FALSE),"Ingrédient non trouvé") -> Ingrédient non trouvé | I24: =IFERROR(tbl_Achats[[#This Row],[Qté d''Achat]] * tbl_Achats[[#This Row],[Prix Achat Unitaire]], 0) -> 0
... D620: =IFERROR(VLOOKUP(E620,Référentiels!$M$2:$N$267,2,FALSE),"Ingrédient non trouvé") -> Ingrédient non trouvé | I620: =IFERROR(tbl_Achats[[#This Row],[Qté d''Achat]] * tbl_Achats[[#This Row],[Prix Achat Unitaire]], 0) -> 0

Sheet tbl_Sorties
A1: Code ingrédient | B1: Nom ingredient | C1: Qté Sortie | D1: Unité
A2: =IFERROR(VLOOKUP(B2,Référentiels!$M$2:$N$267,2,FALSE),"") -> BOU004 | B2: Toast Céréale | C2: 10 | D2: =INDEX(tbl_IngrédientsRef[Unité], MATCH(A2, tbl_IngrédientsRef[Cde_Ingrdt],0)) -> Pièce
A3: =IFERROR(VLOOKUP(B3,Référentiels!$M$2:$N$267,2,FALSE),"") -> BOU001 | B3: Pain Varie Pistolet | C3: 500 | D3: =INDEX(tbl_IngrédientsRef[Unité], MATCH(A3, tbl_IngrédientsRef[Cde_Ingrdt],0)) -> Pièce
A4: =IFERROR(VLOOKUP(B4,Référentiels!$M$2:$N$267,2,FALSE),"") -> FEC006 | B4: Ebly | C4: 500 | D4: =INDEX(tbl_IngrédientsRef[Unité], MATCH(A4, tbl_IngrédientsRef[Cde_Ingrdt],0)) -> g
A5: =IFERROR(VLOOKUP(B5,Référentiels!$M$2:$N$267,2,FALSE),"") -> BOI009 | B5: Eau Minérale 50Cl | C5: 60 | D5: =INDEX(tbl_IngrédientsRef[Unité], MATCH(A5, tbl_IngrédientsRef[Cde_Ingrdt],0)) -> Pièce
A6: =IFERROR(VLOOKUP(B6,Référentiels!$M$2:$N$267,2,FALSE),"") -> BOI008 | B6: Eau Minérale 1,5L | C6: 100 | D6: =INDEX(tbl_IngrédientsRef[Unité], MATCH(A6, tbl_IngrédientsRef[Cde_Ingrdt],0)) -> Pièce
A7: =IFERROR(VLOOKUP(B7,Référentiels!$M$2:$N$267,2,FALSE),"") -> BOE001 | B7: Viande Hachée Nature | C7: 365 | D7: =INDEX(tbl_IngrédientsRef[Unité], MATCH(A7, tbl_IngrédientsRef[Cde_Ingrdt],0)) -> g
A8: =IFERROR(VLOOKUP(B8,Référentiels!$M$2:$N$267,2,FALSE),"") -> VOL007 | B8: Saucisse Poulet | C8: 246 | D8: =INDEX(tbl_IngrédientsRef[Unité], MATCH(A8, tbl_IngrédientsRef[Cde_Ingrdt],0)) -> g
A9: =IFERROR(VLOOKUP(B9,Référentiels!$M$2:$N$267,2,FALSE),"") -> AGN004 | B9: Côtelettes D'Agneau | C9: 55 | D9: =INDEX(tbl_IngrédientsRef[Unité], MATCH(A9, tbl_IngrédientsRef[Cde_Ingrdt],0)) -> g
A10: =IFERROR(VLOOKUP(B10,Référentiels!$M$2:$N$267,2,FALSE),"") -> BOU006 | B10: Pain Au Chocolat P | D10: =INDEX(tbl_IngrédientsRef[Unité], MATCH(A10, tbl_IngrédientsRef[Cde_Ingrdt],0)) -> Pièce
A11: =IFERROR(VLOOKUP(B11,Référentiels!$M$2:$N$267,2,FALSE),"") -> BOU010 | B11: Baghrire | D11: =INDEX(tbl_IngrédientsRef[Unité], MATCH(A11, tbl_IngrédientsRef[Cde_Ingrdt],0)) -> Pièce
A12: =IFERROR(VLOOKUP(B12,Référentiels!$M$2:$N$267,2,FALSE),"") -> BOE006 | B12: Pepperoni | D12: =INDEX(tbl_IngrédientsRef[Unité], MATCH(A12, tbl_IngrédientsRef[Cde_Ingrdt],0)) -> g
A13: =IFERROR(VLOOKUP(B13,Référentiels!$M$2:$N$267,2,FALSE),"") -> VEA007 | B13: Rumsteak Veau | D13: =INDEX(tbl_IngrédientsRef[Unité], MATCH(A13, tbl_IngrédientsRef[Cde_Ingrdt],0)) -> g
A14: =IFERROR(VLOOKUP(B14,Référentiels!$M$2:$N$267,2,FALSE),"") | D14: =INDEX(tbl_IngrédientsRef[Unité], MATCH(A14, tbl_IngrédientsRef[Cde_Ingrdt],0)) -> #N/A
A15: =IFERROR(VLOOKUP(B15,Référentiels!$M$2:$N$267,2,FALSE),"") | D15: =INDEX(tbl_IngrédientsRef[Unité], MATCH(A15, tbl_IngrédientsRef[Cde_Ingrdt],0)) -> #N/A
A16: =IFERROR(VLOOKUP(B16,Référentiels!$M$2:$N$267,2,FALSE),"") | D16: =INDEX(tbl_IngrédientsRef[Unité], MATCH(A16, tbl_IngrédientsRef[Cde_Ingrdt],0)) -> #N/A
A17: =IFERROR(VLOOKUP(B17,Référentiels!$M$2:$N$267,2,FALSE),"") | D17: =INDEX(tbl_IngrédientsRef[Unité], MATCH(A17, tbl_IngrédientsRef[Cde_Ingrdt],0)) -> #N/A
A18: =IFERROR(VLOOKUP(B18,Référentiels!$M$2:$N$267,2,FALSE),"") | D18: =INDEX(tbl_IngrédientsRef[Unité], MATCH(A18, tbl_IngrédientsRef[Cde_Ingrdt],0)) -> #N/A
A19: =IFERROR(VLOOKUP(B19,Référentiels!$M$2:$N$267,2,FALSE),"") | D19: =INDEX(tbl_IngrédientsRef[Unité], MATCH(A19, tbl_IngrédientsRef[Cde_Ingrdt],0)) -> #N/A
A20: =IFERROR(VLOOKUP(B20,Référentiels!$M$2:$N$267,2,FALSE),"") | D20: =INDEX(tbl_IngrédientsRef[Unité], MATCH(A20, tbl_IngrédientsRef[Cde_Ingrdt],0)) -> #N/A
A21: =IFERROR(VLOOKUP(B21,Référentiels!$M$2:$N$267,2,FALSE),"") | D21: =INDEX(tbl_IngrédientsRef[Unité], MATCH(A21, tbl_IngrédientsRef[Cde_Ingrdt],0)) -> #N/A
A22: =IFERROR(VLOOKUP(B22,Référentiels!$M$2:$N$267,2,FALSE),"") | D22: =INDEX(tbl_IngrédientsRef[Unité], MATCH(A22, tbl_IngrédientsRef[Cde_Ingrdt],0)) -> #N/A
A23: =IFERROR(VLOOKUP(B23,Référentiels!$M$2:$N$267,2,FALSE),"") | D23: =INDEX(tbl_IngrédientsRef[Unité], MATCH(A23, tbl_IngrédientsRef[Cde_Ingrdt],0)) -> #N/A
A24: =IFERROR(VLOOKUP(B24,Référentiels!$M$2:$N$267,2,FALSE),"") | D24: =INDEX(tbl_IngrédientsRef[Unité], MATCH(A24, tbl_IngrédientsRef[Cde_Ingrdt],0)) -> #N/A
A25: =IFERROR(VLOOKUP(B25,Référentiels!$M$2:$N$267,2,FALSE),"") | D25: =INDEX(tbl_IngrédientsRef[Unité], MATCH(A25, tbl_IngrédientsRef[Cde_Ingrdt],0)) -> #N/A
... A500: =IFERROR(VLOOKUP(B500,Référentiels!$M$2:$N$267,2,FALSE),"") | D500: =INDEX(tbl_IngrédientsRef[Unité], MATCH(A500, tbl_IngrédientsRef[Cde_Ingrdt],0)) -> #N/A

Sheet Référentiels
A1: Racine_Prdts | B1: Séries | D1: Racine_Ingrdts | E1: Séries | G1: Cde_Prdt | H1: Produit | I1: Famille | J1: Prix Menu | K1: Coût Matière | M1: Ingrédient | N1: Cde_Ingrdt | O1: Catégorie | P1: Prix/Uni Base | Q1: Unité | R1: Prix Au kg ou L | S1: PU_effectif_g/ml
A2: =IF(tbl_ProduitsRef[[#This Row],[Famille]]="Petits déjeuners","PDJ", IF(tbl_ProduitsRef[[#This Row],[Famille]]="À la carte","OND", IF(tbl_ProduitsRef[[#This Row],[Famille]]="Œufs & Omelettes","OME", IF(tbl_ProduitsRef[[#This Row],[Famille]]="Suppléments","SUP", IF(tbl_ProduitsRef[[#This Row],[Famille]]="Glaces & Desserts","DES", IF(tbl_ProduitsRef[[#This Row],[Famille]]="Crêpes & Gaufres","CRP", IF(tbl_ProduitsRef[[#This Row],[Famille]]="Boissons chaudes","BCH", IF(tbl_ProduitsRef[[#This Row],[Famille]]="Smoothies & Coctails","SmCk", IF(tbl_ProduitsRef[[#This Row],[Famille]]="Boissons froides","BFR", IF(tbl_ProduitsRef[[#This Row],[Famille]]="Milkshakes","MKS", IF(tbl_ProduitsRef[[#This Row],[Famille]]="Jus Frais","JUS", IF(tbl_ProduitsRef[[#This Row],[Famille]]="Poulet","PUL", IF(tbl_ProduitsRef[[#This Row],[Famille]]="Boucherie","VIA", IF(tbl_ProduitsRef[[#This Row],[Famille]]="Poissons & Fruits de mer","POI", IF(tbl_ProduitsRef[[#This Row],[Famille]]="Pâtes","PAT", IF(tbl_ProduitsRef[[#This Row],[Famille]]="Pizzas","PIZ", IF(tbl_ProduitsRef[[#This Row],[Famille]]="Entrées & Salades","ENT", IF(tbl_ProduitsRef[[#This Row],[Famille]]="Snack","SNK", IF(tbl_ProduitsRef[[#This Row],[Famille]]="Tajines & Coin marocain","TAJ"))))))))))))))))))) -> PDJ | B2: =COUNTIF(A$2:$A2,A2) -> 1 | D2: =IF(tbl_IngrédientsRef[[#This Row],[Catégorie]]="Boulangerie","BOU", IF(tbl_IngrédientsRef[[#This Row],[Catégorie]]="Féculents","FEC", IF(tbl_IngrédientsRef[[#This Row],[Catégorie]]="Préparations","PRP", IF(tbl_IngrédientsRef[[#This Row],[Catégorie]]="Viande Spécial","VSP", IF(tbl_IngrédientsRef[[#This Row],[Catégorie]]="Pâtes","PST", IF(tbl_IngrédientsRef[[#This Row],[Catégorie]]="Viande De Volaille","VOL", IF(tbl_IngrédientsRef[[#This Row],[Catégorie]]="Viande De Boeuf","BOE", IF(tbl_IngrédientsRef[[#This Row],[Catégorie]]="Viande d'Agneau","AGN", IF(tbl_IngrédientsRef[[#This Row],[Catégorie]]="Viande De Veau","VEA", IF(tbl_IngrédientsRef[[#This Row],[Catégorie]]="Charcuterie","CHA", IF(tbl_IngrédientsRef[[#This Row],[Catégorie]]="Poissons","POI", IF(tbl_IngrédientsRef[[#This Row],[Catégorie]]="Fruits de mer","FDM", IF(tbl_IngrédientsRef[[#This Row],[Catégorie]]="Produits laitiers","PRL", IF(tbl_IngrédientsRef[[#This Row],[Catégorie]]="Légumes","LEG", IF(tbl_IngrédientsRef[[#This Row],[Catégorie]]="Fruits frais","FRU", IF(tbl_IngrédientsRef[[#This Row],[Catégorie]]="Épicerie","EPI", IF(tbl_IngrédientsRef[[#This Row],[Catégorie]]="Produits Sucrés","PSU", IF(tbl_IngrédientsRef[[#This Row],[Catégorie]]="Condiments","CDM", IF(tbl_IngrédientsRef[[#This Row],[Catégorie]]="Sauces","SOS", IF(tbl_IngrédientsRef[[#This Row],[Catégorie]]="Glaces","GLA", IF(tbl_IngrédientsRef[[#This Row],[Catégorie]]="Desserts","DES", IF(tbl_IngrédientsRef[[#This Row],[Catégorie]]="Boissons chaudes & froides","BOI", "⚠️ Catégorie inconnue")))))))))))))))))))))) -> BOU | E2: =COUNTIF($D$2:D2,D2) -> 1 | G2: =Référentiels!A2&TEXT(Référentiels!B2,"000") -> PDJ001 | H2: Norvégien | I2: Petits déjeuners | J2: 70 | K2: =IFERROR( SUMIFS(#REF!,#REF!, tbl_ProduitsRef[[#This Row],[Cde_Prdt]]), 0) -> 0 | M2: Pain Varie Pistolet | N2: =Référentiels!D2&TEXT(Référentiels!E2,"000") -> BOU001 | O2: Boulangerie | P2: 2.5 | Q2: Pièce | R2: =IFERROR( IF(tbl_IngrédientsRef[[#This Row],[Unité]]="g", (tbl_IngrédientsRef[[#This Row],[PU_effectif_g/ml]]*1000), IF(tbl_IngrédientsRef[[#This Row],[Unité]]="ml", tbl_IngrédientsRef[[#This Row],[PU_effectif_g/ml]]*1000, IF(tbl_IngrédientsRef[[#This Row],[Unité]]="pièce", tbl_IngrédientsRef[[#This Row],[PU_effectif_g/ml]], tbl_IngrédientsRef[[#This Row],[PU_effectif_g/ml]] ) ) ), 0) -> 2.5 | S2: =IF(tbl_IngrédientsRef[[#This Row],[Unité]]="kg", tbl_IngrédientsRef[[#This Row],[Prix Au kg ou L]]/1000, IF(tbl_IngrédientsRef[[#This Row],[Unité]]="L", tbl_IngrédientsRef[[#This Row],[Prix Au kg ou L]]/1000, tbl_IngrédientsRef[[#This Row],[Prix/Uni Base]])) -> 2.5
A3: =IF(tbl_ProduitsRef[[#This Row],[Famille]]="Petits déjeuners","PDJ", IF(tbl_ProduitsRef[[#This Row],[Famille]]="À la carte","OND", IF(tbl_ProduitsRef[[#This Row],[Famille]]="Œufs & Omelettes","OME", IF(tbl_ProduitsRef[[#This Row],[Famille]]="Suppléments","SUP", IF(tbl_ProduitsRef[[#This Row],[Famille]]="Glaces & Desserts","DES", IF(tbl_ProduitsRef[[#This Row],[Famille]]="Crêpes & Gaufres","CRP", IF(tbl_ProduitsRef[[#This Row],[Famille]]="Boissons chaudes","BCH", IF(tbl_ProduitsRef[[#This Row],[Famille]]="Smoothies & Coctails","SmCk", IF(tbl_ProduitsRef[[#This Row],[Famille]]="Boissons froides","BFR", IF(tbl_ProduitsRef[[#This Row],[Famille]]="Milkshakes","MKS", IF(tbl_ProduitsRef[[#This Row],[Famille]]="Jus Frais","JUS", IF(tbl_ProduitsRef[[#This Row],[Famille]]="Poulet","PUL", IF(tbl_ProduitsRef[[#This Row],[Famille]]="Boucherie","VIA", IF(tbl_ProduitsRef[[#This Row],[Famille]]="Poissons & Fruits de mer","POI", IF(tbl_ProduitsRef[[#This Row],[Famille]]="Pâtes","PAT", IF(tbl_ProduitsRef[[#This Row],[Famille]]="Pizzas","PIZ", IF(tbl_ProduitsRef[[#This Row],[Famille]]="Entrées & Salades","ENT", IF(tbl_ProduitsRef[[#This Row],[Famille]]="Snack","SNK", IF(tbl_ProduitsRef[[#This Row],[Famille]]="Tajines & Coin marocain","TAJ"))))))))))))))))))) -> PDJ | B3: =COUNTIF(A$2:$A3,A3) -> 2 | D3: =IF(tbl_IngrédientsRef[[#This Row],[Catégorie]]="Boulangerie","BOU", IF(tbl_IngrédientsRef[[#This Row],[Catégorie]]="Féculents","FEC", IF(tbl_IngrédientsRef[[#This Row],[Catégorie]]="Préparations","PRP", IF(tbl_IngrédientsRef[[#This Row],[Catégorie]]="Viande Spécial","VSP", IF(tbl_IngrédientsRef[[#This Row],[Catégorie]]="Pâtes","PST", IF(tbl_IngrédientsRef[[#This Row],[Catégorie]]="Viande De Volaille","VOL", IF(tbl_IngrédientsRef[[#This Row],[Catégorie]]="Viande De Boeuf","BOE", IF(tbl_IngrédientsRef[[#This Row],[Catégorie]]="Viande d'Agneau","AGN", IF(tbl_IngrédientsRef[[#This Row],[Catégorie]]="Viande De Veau","VEA", IF(tbl_IngrédientsRef[[#This Row],[Catégorie]]="Charcuterie","CHA", IF(tbl_IngrédientsRef[[#This Row],[Catégorie]]="Poissons","POI", IF(tbl_IngrédientsRef[[#This Row],[Catégorie]]="Fruits de mer","FDM", IF(tbl_IngrédientsRef[[#This Row],[Catégorie]]="Produits laitiers","PRL", IF(tbl_IngrédientsRef[[#This Row],[Catégorie]]="Légumes","LEG", IF(tbl_IngrédientsRef[[#This Row],[Catégorie]]="Fruits frais","FRU", IF(tbl_IngrédientsRef[[#This Row],[Catégorie]]="Épicerie","EPI", IF(tbl_IngrédientsRef[[#This Row],[Catégorie]]="Produits Sucrés","PSU", IF(tbl_IngrédientsRef[[#This Row],[Catégorie]]="Condiments","CDM", IF(tbl_IngrédientsRef[[#This Row],[Catégorie]]="Sauces","SOS", IF(tbl_IngrédientsRef[[#This Row],[Catégorie]]="Glaces","GLA", IF(tbl_IngrédientsRef[[#This Row],[Catégorie]]="Desserts","DES", IF(tbl_IngrédientsRef[[#This Row],[Catégorie]]="Boissons chaudes & froides","BOI", "⚠️ Catégorie inconnue")))))))))))))))))))))) -> BOU | E3: =COUNTIF($D$2:D3,D3) -> 2 | G3: =Référentiels!A3&TEXT(Référentiels!B3,"000") -> PDJ002 | H3: Casserole turque | I3: Petits déjeuners | J3: 70 | K3: =IFERROR( SUMIFS(#REF!,#REF!, tbl_ProduitsRef[[#This Row],[Cde_Prdt]]), 0) -> 0 | M3: Pain Berger | N3: =Référentiels!D3&TEXT(Référentiels!E3,"000") -> BOU002 | O3: Boulangerie | P3: 1.5 | Q3: Pièce | R3: =IFERROR( IF(tbl_IngrédientsRef[[#This Row],[Unité]]="g", (tbl_IngrédientsRef[[#This Row],[PU_effectif_g/ml]]*1000), IF(tbl_IngrédientsRef[[#This Row],[Unité]]="ml", tbl_IngrédientsRef[[#This Row],[PU_effectif_g/ml]]*1000, IF(tbl_IngrédientsRef[[#This Row],[Unité]]="pièce", tbl_IngrédientsRef[[#This Row],[PU_effectif_g/ml]], tbl_IngrédientsRef[[#This Row],[PU_effectif_g/ml]] ) ) ), 0) -> 1.5 | S3: =IF(tbl_IngrédientsRef[[#This Row],[Unité]]="kg", tbl_IngrédientsRef[[#This Row],[Prix Au kg ou L]]/1000, IF(tbl_IngrédientsRef[[#This Row],[Unité]]="L", tbl_IngrédientsRef[[#This Row],[Prix Au kg ou L]]/1000, tbl_IngrédientsRef[[#This Row],[Prix/Uni Base]])) -> 1.5
A4: =IF(tbl_ProduitsRef[[#This Row],[Famille]]="Petits déjeuners","PDJ", IF(tbl_ProduitsRef[[#This Row],[Famille]]="À la carte","OND", IF(tbl_ProduitsRef[[#This Row],[Famille]]="Œufs & Omelettes","OME", IF(tbl_ProduitsRef[[#This Row],[Famille]]="Suppléments","SUP", IF(tbl_ProduitsRef[[#This Row],[Famille]]="Glaces & Desserts","DES", IF(tbl_ProduitsRef[[#This Row],[Famille]]="Crêpes & Gaufres","CRP", IF(tbl_ProduitsRef[[#This Row],[Famille]]="Boissons chaudes","BCH", IF(tbl_ProduitsRef[[#This Row],[Famille]]="Smoothies & Coctails","SmCk", IF(tbl_ProduitsRef[[#This Row],[Famille]]="Boissons froides","BFR", IF(tbl_ProduitsRef[[#This Row],[Famille]]="Milkshakes","MKS", IF(tbl_ProduitsRef[[#This Row],[Famille]]="Jus Frais","JUS", IF(tbl_ProduitsRef[[#This Row],[Famille]]="Poulet","PUL", IF(tbl_ProduitsRef[[#This Row],[Famille]]="Boucherie","VIA", IF(tbl_ProduitsRef[[#This Row],[Famille]]="Poissons & Fruits de mer","POI", IF(tbl_ProduitsRef[[#This Row],[Famille]]="Pâtes","PAT", IF(tbl_ProduitsRef[[#This Row],[Famille]]="Pizzas","PIZ", IF(tbl_ProduitsRef[[#This Row],[Famille]]="Entrées & Salades","ENT", IF(tbl_ProduitsRef[[#This Row],[Famille]]="Snack","SNK", IF(tbl_ProduitsRef[[#This Row],[Famille]]="Tajines & Coin marocain","TAJ"))))))))))))))))))) -> PDJ | B4: =COUNTIF(A$2:$A4,A4) -> 3 | D4: =IF(tbl_IngrédientsRef[[#This Row],[Catégorie]]="Boulangerie","BOU", IF(tbl_IngrédientsRef[[#This Row],[Catégorie]]="Féculents","FEC", IF(tbl_IngrédientsRef[[#This Row],[Catégorie]]="Préparations","PRP", IF(tbl_IngrédientsRef[[#This Row],[Catégorie]]="Viande Spécial","VSP", IF(tbl_IngrédientsRef[[#This Row],[Catégorie]]="Pâtes","PST", IF(tbl_IngrédientsRef[[#This Row],[Catégorie]]="Viande De Volaille","VOL", IF(tbl_IngrédientsRef[[#This Row],[Catégorie]]="Viande De Boeuf","BOE", IF(tbl_IngrédientsRef[[#This Row],[Catégorie]]="Viande d'Agneau","AGN", IF(tbl_IngrédientsRef[[#This Row],[Catégorie]]="Viande De Veau","VEA", IF(tbl_IngrédientsRef[[#This Row],[Catégorie]]="Charcuterie","CHA", IF(tbl_IngrédientsRef[[#This Row],[Catégorie]]="Poissons","POI", IF(tbl_IngrédientsRef[[#This Row],[Catégorie]]="Fruits de mer","FDM", IF(tbl_IngrédientsRef[[#This Row],[Catégorie]]="Produits laitiers","PRL", IF(tbl_IngrédientsRef[[#This Row],[Catégorie]]="Légumes","LEG", IF(tbl_IngrédientsRef[[#This Row],[Catégorie]]="Fruits frais","FRU", IF(tbl_IngrédientsRef[[#This Row],[Catégorie]]="Épicerie","EPI", IF(tbl_IngrédientsRef[[#This Row],[Catégorie]]="Produits Sucrés","PSU", IF(tbl_IngrédientsRef[[#This Row],[Catégorie]]="Condiments","CDM", IF(tbl_IngrédientsRef[[#This Row],[Catégorie]]="Sauces","SOS", IF(tbl_IngrédientsRef[[#This Row],[Catégorie]]="Glaces","GLA", IF(tbl_IngrédientsRef[[#This Row],[Catégorie]]="Desserts","DES", IF(tbl_IngrédientsRef[[#This Row],[Catégorie]]="Boissons chaudes & froides","BOI", "⚠️ Catégorie inconnue")))))))))))))))))))))) -> BOU | E4: =COUNTIF($D$2:D4,D4) -> 3 | G4: =Référentiels!A4&TEXT(Référentiels!B4,"000") -> PDJ003 | H4: Américain | I4: Petits déjeuners | J4: 60 | K4: =IFERROR( SUMIFS(#REF!,#REF!, tbl_ProduitsRef[[#This Row],[Cde_Prdt]]), 0) -> 0 | M4: Pain Grillé | N4: =Référentiels!D4&TEXT(Référentiels!E4,"000") -> BOU003 | O4: Boulangerie | P4: 2 | Q4: Pièce | R4: =IFERROR( IF(tbl_IngrédientsRef[[#This Row],[Unité]]="g", (tbl_IngrédientsRef[[#This Row],[PU_effectif_g/ml]]*1000), IF(tbl_IngrédientsRef[[#This Row],[Unité]]="ml", tbl_IngrédientsRef[[#This Row],[PU_effectif_g/ml]]*1000, IF(tbl_IngrédientsRef[[#This Row],[Unité]]="pièce", tbl_IngrédientsRef[[#This Row],[PU_effectif_g/ml]], tbl_IngrédientsRef[[#This Row],[PU_effectif_g/ml]] ) ) ), 0) -> 2 | S4: =IF(tbl_IngrédientsRef[[#This Row],[Unité]]="kg", tbl_IngrédientsRef[[#This Row],[Prix Au kg ou L]]/1000, IF(tbl_IngrédientsRef[[#This Row],[Unité]]="L", tbl_IngrédientsRef[[#This Row],[Prix Au kg ou L]]/1000, tbl_IngrédientsRef[[#This Row],[Prix/Uni Base]])) -> 2
A5: =IF(tbl_ProduitsRef[[#This Row],[Famille]]="Petits déjeuners","PDJ", IF(tbl_ProduitsRef[[#This Row],[Famille]]="À la carte","OND", IF(tbl_ProduitsRef[[#This Row],[Famille]]="Œufs & Omelettes","OME", IF(tbl_ProduitsRef[[#This Row],[Famille]]="Suppléments","SUP", IF(tbl_ProduitsRef[[#This Row],[Famille]]="Glaces & Desserts","DES", IF(tbl_ProduitsRef[[#This Row],[Famille]]="Crêpes & Gaufres","CRP", IF(tbl_ProduitsRef[[#This Row],[Famille]]="Boissons chaudes","BCH", IF(tbl_ProduitsRef[[#This Row],[Famille]]="Smoothies & Coctails","SmCk", IF(tbl_ProduitsRef[[#This Row],[Famille]]="Boissons froides","BFR", IF(tbl_ProduitsRef[[#This Row],[Famille]]="Milkshakes","MKS", IF(tbl_ProduitsRef[[#This Row],[Famille]]="Jus Frais","JUS", IF(tbl_ProduitsRef[[#This Row],[Famille]]="Poulet","PUL", IF(tbl_ProduitsRef[[#This Row],[Famille]]="Boucherie","VIA", IF(tbl_ProduitsRef[[#This Row],[Famille]]="Poissons & Fruits de mer","POI", IF(tbl_ProduitsRef[[#This Row],[Famille]]="Pâtes","PAT", IF(tbl_ProduitsRef[[#This Row],[Famille]]="Pizzas","PIZ", IF(tbl_ProduitsRef[[#This Row],[Famille]]="Entrées & Salades","ENT", IF(tbl_ProduitsRef[[#This Row],[Famille]]="Snack","SNK", IF(tbl_ProduitsRef[[#This Row],[Famille]]="Tajines & Coin marocain","TAJ"))))))))))))))))))) -> PDJ | B5: =COUNTIF(A$2:$A5,A5) -> 4 | D5: =IF(tbl_IngrédientsRef[[#This Row],[Catégorie]]="Boulangerie","BOU", IF(tbl_IngrédientsRef[[#This Row],[Catégorie]]="Féculents","FEC", IF(tbl_IngrédientsRef[[#This Row],[Catégorie]]="Préparations","PRP", IF(tbl_IngrédientsRef[[#This Row],[Catégorie]]="Viande Spécial","VSP", IF(tbl_IngrédientsRef[[#This Row],[Catégorie]]="Pâtes","PST", IF(tbl_IngrédientsRef[[#This Row],[Catégorie]]="Viande De Volaille","VOL", IF(tbl_IngrédientsRef[[#This Row],[Catégorie]]="Viande De Boeuf","BOE", IF(tbl_IngrédientsRef[[#This Row],[Catégorie]]="Viande d'Agneau","AGN", IF(tbl_IngrédientsRef[[#This Row],[Catégorie]]="Viande De Veau","VEA", IF(tbl_IngrédientsRef[[#This Row],[Catégorie]]="Charcuterie","CHA", IF(tbl_IngrédientsRef[[#This Row],[Catégorie]]="Poissons","POI", IF(tbl_IngrédientsRef[[#This Row],[Catégorie]]="Fruits de mer","FDM", IF(tbl_IngrédientsRef[[#This Row],[Catégorie]]="Produits laitiers","PRL", IF(tbl_IngrédientsRef[[#This Row],[Catégorie]]="Légumes","LEG", IF(tbl_IngrédientsRef[[#This Row],[Catégorie]]="Fruits frais","FRU", IF(tbl_IngrédientsRef[[#This Row],[Catégorie]]="Épicerie","EPI", IF(tbl_IngrédientsRef[[#This Row],[Catégorie]]="Produits Sucrés","PSU", IF(tbl_IngrédientsRef[[#This Row],[Catégorie]]="Condiments","CDM", IF(tbl_IngrédientsRef[[#This Row],[Catégorie]]="Sauces","SOS", IF(tbl_IngrédientsRef[[#This Row],[Catégorie]]="Glaces","GLA", IF(tbl_IngrédientsRef[[#This Row],[Catégorie]]="Desserts","DES", IF(tbl_IngrédientsRef[[#This Row],[Catégorie]]="Boissons chaudes & froides","BOI", "⚠️ Catégorie inconnue")))))))))))))))))))))) -> BOU | E5: =COUNTIF($D$2:D5,D5) -> 4 | G5: =Référentiels!A5&TEXT(Référentiels!B5,"000") -> PDJ004 | H5: Amsterdam | I5: Petits déjeuners | J5: 55 | K5: =IFERROR( SUMIFS(#REF!,#REF!, tbl_ProduitsRef[[#This Row],[Cde_Prdt]]), 0) -> 0 | M5: Toast Céréale | N5: =Référentiels!D5&TEXT(Référentiels!E5,"000") -> BOU004 | O5: Boulangerie | P5: 1.2 | Q5: Pièce | R5: =IFERROR( IF(tbl_IngrédientsRef[[#This Row],[Unité]]="g", (tbl_IngrédientsRef[[#This Row],[PU_effectif_g/ml]]*1000), IF(tbl_IngrédientsRef[[#This Row],[Unité]]="ml", tbl_IngrédientsRef[[#This Row],[PU_effectif_g/ml]]*1000, IF(tbl_IngrédientsRef[[#This Row],[Unité]]="pièce", tbl_IngrédientsRef[[#This Row],[PU_effectif_g/ml]], tbl_IngrédientsRef[[#This Row],[PU_effectif_g/ml]] ) ) ), 0) -> 1.2 | S5: =IF(tbl_IngrédientsRef[[#This Row],[Unité]]="kg", tbl_IngrédientsRef[[#This Row],[Prix Au kg ou L]]/1000, IF(tbl_IngrédientsRef[[#This Row],[Unité]]="L", tbl_IngrédientsRef[[#This Row],[Prix Au kg ou L]]/1000, tbl_IngrédientsRef[[#This Row],[Prix/Uni Base]])) -> 1.2
A6: =IF(tbl_ProduitsRef[[#This Row],[Famille]]="Petits déjeuners","PDJ", IF(tbl_ProduitsRef[[#This Row],[Famille]]="À la carte","OND", IF(tbl_ProduitsRef[[#This Row],[Famille]]="Œufs & Omelettes","OME", IF(tbl_ProduitsRef[[#This Row],[Famille]]="Suppléments","SUP", IF(tbl_ProduitsRef[[#This Row],[Famille]]="Glaces & Desserts","DES", IF(tbl_ProduitsRef[[#This Row],[Famille]]="Crêpes & Gaufres","CRP", IF(tbl_ProduitsRef[[#This Row],[Famille]]="Boissons chaudes","BCH", IF(tbl_ProduitsRef[[#This Row],[Famille]]="Smoothies & Coctails","SmCk", IF(tbl_ProduitsRef[[#This Row],[Famille]]="Boissons froides","BFR", IF(tbl_ProduitsRef[[#This Row],[Famille]]="Milkshakes","MKS", IF(tbl_ProduitsRef[[#This Row],[Famille]]="Jus Frais","JUS", IF(tbl_ProduitsRef[[#This Row],[Famille]]="Poulet","PUL", IF(tbl_ProduitsRef[[#This Row],[Famille]]="Boucherie","VIA", IF(tbl_ProduitsRef[[#This Row],[Famille]]="Poissons & Fruits de mer","POI", IF(tbl_ProduitsRef[[#This Row],[Famille]]="Pâtes","PAT", IF(tbl_ProduitsRef[[#This Row],[Famille]]="Pizzas","PIZ", IF(tbl_ProduitsRef[[#This Row],[Famille]]="Entrées & Salades","ENT", IF(tbl_ProduitsRef[[#This Row],[Famille]]="Snack","SNK", IF(tbl_ProduitsRef[[#This Row],[Famille]]="Tajines & Coin marocain","TAJ"))))))))))))))))))) -> PDJ | B6: =COUNTIF(A$2:$A6,A6) -> 5 | D6: =IF(tbl_IngrédientsRef[[#This Row],[Catégorie]]="Boulangerie","BOU", IF(tbl_IngrédientsRef[[#This Row],[Catégorie]]="Féculents","FEC", IF(tbl_IngrédientsRef[[#This Row],[Catégorie]]="Préparations","PRP", IF(tbl_IngrédientsRef[[#This Row],[Catégorie]]="Viande Spécial","VSP", IF(tbl_IngrédientsRef[[#This Row],[Catégorie]]="Pâtes","PST", IF(tbl_IngrédientsRef[[#This Row],[Catégorie]]="Viande De Volaille","VOL", IF(tbl_IngrédientsRef[[#This Row],[Catégorie]]="Viande De Boeuf","BOE", IF(tbl_IngrédientsRef[[#This Row],[Catégorie]]="Viande d'Agneau","AGN", IF(tbl_IngrédientsRef[[#This Row],[Catégorie]]="Viande De Veau","VEA", IF(tbl_IngrédientsRef[[#This Row],[Catégorie]]="Charcuterie","CHA", IF(tbl_IngrédientsRef[[#This Row],[Catégorie]]="Poissons","POI", IF(tbl_IngrédientsRef[[#This Row],[Catégorie]]="Fruits de mer","FDM", IF(tbl_IngrédientsRef[[#This Row],[Catégorie]]="Produits laitiers","PRL", IF(tbl_IngrédientsRef[[#This Row],[Catégorie]]="Légumes","LEG", IF(tbl_IngrédientsRef[[#This Row],[Catégorie]]="Fruits frais","FRU", IF(tbl_IngrédientsRef[[#This Row],[Catégorie]]="Épicerie","EPI", IF(tbl_IngrédientsRef[[#This Row],[Catégorie]]="Produits Sucrés","PSU", IF(tbl_IngrédientsRef[[#This Row],[Catégorie]]="Condiments","CDM", IF(tbl_IngrédientsRef[[#This Row],[Catégorie]]="Sauces","SOS", IF(tbl_IngrédientsRef[[#This Row],[Catégorie]]="Glaces","GLA", IF(tbl_IngrédientsRef[[#This Row],[Catégorie]]="Desserts","DES", IF(tbl_IngrédientsRef[[#This Row],[Catégorie]]="Boissons chaudes & froides","BOI", "⚠️ Catégorie inconnue")))))))))))))))))))))) -> BOU | E6: =COUNTIF($D$2:D6,D6) -> 5 | G6: =Référentiels!A6&TEXT(Référentiels!B6,"000") -> PDJ005 | H6: Espagnol | I6: Petits déjeuners | J6: 54 | K6: =IFERROR( SUMIFS(#REF!,#REF!, tbl_ProduitsRef[[#This Row],[Cde_Prdt]]), 0) -> 0 | M6: Croissant | N6: =Référentiels!D6&TEXT(Référentiels!E6,"000") -> BOU005 | O6: Boulangerie | P6: 4 | Q6: Pièce | R6: =IFERROR( IF(tbl_IngrédientsRef[[#This Row],[Unité]]="g", (tbl_IngrédientsRef[[#This Row],[PU_effectif_g/ml]]*1000), IF(tbl_IngrédientsRef[[#This Row],[Unité]]="ml", tbl_IngrédientsRef[[#This Row],[PU_effectif_g/ml]]*1000, IF(tbl_IngrédientsRef[[#This Row],[Unité]]="pièce", tbl_IngrédientsRef[[#This Row],[PU_effectif_g/ml]], tbl_IngrédientsRef[[#This Row],[PU_effectif_g/ml]] ) ) ), 0) -> 4 | S6: =IF(tbl_IngrédientsRef[[#This Row],[Unité]]="kg", tbl_IngrédientsRef[[#This Row],[Prix Au kg ou L]]/1000, IF(tbl_IngrédientsRef[[#This Row],[Unité]]="L", tbl_IngrédientsRef[[#This Row],[Prix Au kg ou L]]/1000, tbl_IngrédientsRef[[#This Row],[Prix/Uni Base]])) -> 4
A7: =IF(tbl_ProduitsRef[[#This Row],[Famille]]="Petits déjeuners","PDJ", IF(tbl_ProduitsRef[[#This Row],[Famille]]="À la carte","OND", IF(tbl_ProduitsRef[[#This Row],[Famille]]="Œufs & Omelettes","OME", IF(tbl_ProduitsRef[[#This Row],[Famille]]="Suppléments","SUP", IF(tbl_ProduitsRef[[#This Row],[Famille]]="Glaces & Desserts","DES", IF(tbl_ProduitsRef[[#This Row],[Famille]]="Crêpes & Gaufres","CRP", IF(tbl_ProduitsRef[[#This Row],[Famille]]="Boissons chaudes","BCH", IF(tbl_ProduitsRef[[#This Row],[Famille]]="Smoothies & Coctails","SmCk", IF(tbl_ProduitsRef[[#This Row],[Famille]]="Boissons froides","BFR", IF(tbl_ProduitsRef[[#This Row],[Famille]]="Milkshakes","MKS", IF(tbl_ProduitsRef[[#This Row],[Famille]]="Jus Frais","JUS", IF(tbl_ProduitsRef[[#This Row],[Famille]]="Poulet","PUL", IF(tbl_ProduitsRef[[#This Row],[Famille]]="Boucherie","VIA", IF(tbl_ProduitsRef[[#This Row],[Famille]]="Poissons & Fruits de mer","POI", IF(tbl_ProduitsRef[[#This Row],[Famille]]="Pâtes","PAT", IF(tbl_ProduitsRef[[#This Row],[Famille]]="Pizzas","PIZ", IF(tbl_ProduitsRef[[#This Row],[Famille]]="Entrées & Salades","ENT", IF(tbl_ProduitsRef[[#This Row],[Famille]]="Snack","SNK", IF(tbl_ProduitsRef[[#This Row],[Famille]]="Tajines & Coin marocain","TAJ"))))))))))))))))))) -> PDJ | B7: =COUNTIF(A$2:$A7,A7) -> 6 | D7: =IF(tbl_IngrédientsRef[[#This Row],[Catégorie]]="Boulangerie","BOU", IF(tbl_IngrédientsRef[[#This Row],[Catégorie]]="Féculents","FEC", IF(tbl_IngrédientsRef[[#This Row],[Catégorie]]="Préparations","PRP", IF(tbl_IngrédientsRef[[#This Row],[Catégorie]]="Viande Spécial","VSP", IF(tbl_IngrédientsRef[[#This Row],[Catégorie]]="Pâtes","PST", IF(tbl_IngrédientsRef[[#This Row],[Catégorie]]="Viande De Volaille","VOL", IF(tbl_IngrédientsRef[[#This Row],[Catégorie]]="Viande De Boeuf","BOE", IF(tbl_IngrédientsRef[[#This Row],[Catégorie]]="Viande d'Agneau","AGN", IF(tbl_IngrédientsRef[[#This Row],[Catégorie]]="Viande De Veau","VEA", IF(tbl_IngrédientsRef[[#This Row],[Catégorie]]="Charcuterie","CHA", IF(tbl_IngrédientsRef[[#This Row],[Catégorie]]="Poissons","POI", IF(tbl_IngrédientsRef[[#This Row],[Catégorie]]="Fruits de mer","FDM", IF(tbl_IngrédientsRef[[#This Row],[Catégorie]]="Produits laitiers","PRL", IF(tbl_IngrédientsRef[[#This Row],[Catégorie]]="Légumes","LEG", IF(tbl_IngrédientsRef[[#This Row],[Catégorie]]="Fruits frais","FRU", IF(tbl_IngrédientsRef[[#This Row],[Catégorie]]="Épicerie","EPI", IF(tbl_IngrédientsRef[[#This Row],[Catégorie]]="Produits Sucrés","PSU", IF(tbl_IngrédientsRef[[#This Row],[Catégorie]]="Condiments","CDM", IF(tbl_IngrédientsRef[[#This Row],[Catégorie]]="Sauces","SOS", IF(tbl_IngrédientsRef[[#This Row],[Catégorie]]="Glaces","GLA", IF(tbl_IngrédientsRef[[#This Row],[Catégorie]]="Desserts","DES", IF(tbl_IngrédientsRef[[#This Row],[Catégorie]]="Boissons chaudes & froides","BOI", "⚠️ Catégorie inconnue")))))))))))))))))))))) -> BOU | E7: =COUNTIF($D$2:D7,D7) -> 6 | G7: =Référentiels!A7&TEXT(Référentiels!B7,"000") -> PDJ006 | H7: Berlin | I7: Petits déjeuners | J7: 52 | K7: =IFERROR( SUMIFS(#REF!,#REF!, tbl_ProduitsRef[[#This Row],[Cde_Prdt]]), 0) -> 0 | M7: Pain Au Chocolat P | N7: =Référentiels!D7&TEXT(Référentiels!E7,"000") -> BOU006 | O7: Boulangerie | P7: 3 | Q7: Pièce | R7: =IFERROR( IF(tbl_IngrédientsRef[[#This Row],[Unité]]="g", (tbl_IngrédientsRef[[#This Row],[PU_effectif_g/ml]]*1000), IF(tbl_IngrédientsRef[[#This Row],[Unité]]="ml", tbl_IngrédientsRef[[#This Row],[PU_effectif_g/ml]]*1000, IF(tbl_IngrédientsRef[[#This Row],[Unité]]="pièce", tbl_IngrédientsRef[[#This Row],[PU_effectif_g/ml]], tbl_IngrédientsRef[[#This Row],[PU_effectif_g/ml]] ) ) ), 0) -> 3 | S7: =IF(tbl_IngrédientsRef[[#This Row],[Unité]]="kg", tbl_IngrédientsRef[[#This Row],[Prix Au kg ou L]]/1000, IF(tbl_IngrédientsRef[[#This Row],[Unité]]="L", tbl_IngrédientsRef[[#This Row],[Prix Au kg ou L]]/1000, tbl_IngrédientsRef[[#This Row],[Prix/Uni Base]])) -> 3
A8: =IF(tbl_ProduitsRef[[#This Row],[Famille]]="Petits déjeuners","PDJ", IF(tbl_ProduitsRef[[#This Row],[Famille]]="À la carte","OND", IF(tbl_ProduitsRef[[#This Row],[Famille]]="Œufs & Omelettes","OME", IF(tbl_ProduitsRef[[#This Row],[Famille]]="Suppléments","SUP", IF(tbl_ProduitsRef[[#This Row],[Famille]]="Glaces & Desserts","DES", IF(tbl_ProduitsRef[[#This Row],[Famille]]="Crêpes & Gaufres","CRP", IF(tbl_ProduitsRef[[#This Row],[Famille]]="Boissons chaudes","BCH", IF(tbl_ProduitsRef[[#This Row],[Famille]]="Smoothies & Coctails","SmCk", IF(tbl_ProduitsRef[[#This Row],[Famille]]="Boissons froides","BFR", IF(tbl_ProduitsRef[[#This Row],[Famille]]="Milkshakes","MKS", IF(tbl_ProduitsRef[[#This Row],[Famille]]="Jus Frais","JUS", IF(tbl_ProduitsRef[[#This Row],[Famille]]="Poulet","PUL", IF(tbl_ProduitsRef[[#This Row],[Famille]]="Boucherie","VIA", IF(tbl_ProduitsRef[[#This Row],[Famille]]="Poissons & Fruits de mer","POI", IF(tbl_ProduitsRef[[#This Row],[Famille]]="Pâtes","PAT", IF(tbl_ProduitsRef[[#This Row],[Famille]]="Pizzas","PIZ", IF(tbl_ProduitsRef[[#This Row],[Famille]]="Entrées & Salades","ENT", IF(tbl_ProduitsRef[[#This Row],[Famille]]="Snack","SNK", IF(tbl_ProduitsRef[[#This Row],[Famille]]="Tajines & Coin marocain","TAJ"))))))))))))))))))) -> PDJ | B8: =COUNTIF(A$2:$A8,A8) -> 7 | D8: =IF(tbl_IngrédientsRef[[#This Row],[Catégorie]]="Boulangerie","BOU", IF(tbl_IngrédientsRef[[#This Row],[Catégorie]]="Féculents","FEC", IF(tbl_IngrédientsRef[[#This Row],[Catégorie]]="Préparations","PRP", IF(tbl_IngrédientsRef[[#This Row],[Catégorie]]="Viande Spécial","VSP", IF(tbl_IngrédientsRef[[#This Row],[Catégorie]]="Pâtes","PST", IF(tbl_IngrédientsRef[[#This Row],[Catégorie]]="Viande De Volaille","VOL", IF(tbl_IngrédientsRef[[#This Row],[Catégorie]]="Viande De Boeuf","BOE", IF(tbl_IngrédientsRef[[#This Row],[Catégorie]]="Viande d'Agneau","AGN", IF(tbl_IngrédientsRef[[#This Row],[Catégorie]]="Viande De Veau","VEA", IF(tbl_IngrédientsRef[[#This Row],[Catégorie]]="Charcuterie","CHA", IF(tbl_IngrédientsRef[[#This Row],[Catégorie]]="Poissons","POI", IF(tbl_IngrédientsRef[[#This Row],[Catégorie]]="Fruits de mer","FDM", IF(tbl_IngrédientsRef[[#This Row],[Catégorie]]="Produits laitiers","PRL", IF(tbl_IngrédientsRef[[#This Row],[Catégorie]]="Légumes","LEG", IF(tbl_IngrédientsRef[[#This Row],[Catégorie]]="Fruits frais","FRU", IF(tbl_IngrédientsRef[[#This Row],[Catégorie]]="Épicerie","EPI", IF(tbl_IngrédientsRef[[#This Row],[Catégorie]]="Produits Sucrés","PSU", IF(tbl_IngrédientsRef[[#This Row],[Catégorie]]="Condiments","CDM", IF(tbl_IngrédientsRef[[#This Row],[Catégorie]]="Sauces","SOS", IF(tbl_IngrédientsRef[[#This Row],[Catégorie]]="Glaces","GLA", IF(tbl_IngrédientsRef[[#This Row],[Catégorie]]="Desserts","DES", IF(tbl_IngrédientsRef[[#This Row],[Catégorie]]="Boissons chaudes & froides","BOI", "⚠️ Catégorie inconnue")))))))))))))))))))))) -> BOU | E8: =COUNTIF($D$2:D8,D8) -> 7 | G8: =Référentiels!A8&TEXT(Référentiels!B8,"000") -> PDJ007 | H8: Chamali | I8: Petits déjeuners | J8: 52 | K8: =IFERROR( SUMIFS(#REF!,#REF!, tbl_ProduitsRef[[#This Row],[Cde_Prdt]]), 0) -> 0 | M8: Pain Au Chocolat G | N8: =Référentiels!D8&TEXT(Référentiels!E8,"000") -> BOU007 | O8: Boulangerie | P8: 7 | Q8: Pièce | R8: =IFERROR( IF(tbl_IngrédientsRef[[#This Row],[Unité]]="g", (tbl_IngrédientsRef[[#This Row],[PU_effectif_g/ml]]*1000), IF(tbl_IngrédientsRef[[#This Row],[Unité]]="ml", tbl_IngrédientsRef[[#This Row],[PU_effectif_g/ml]]*1000, IF(tbl_IngrédientsRef[[#This Row],[Unité]]="pièce", tbl_IngrédientsRef[[#This Row],[PU_effectif_g/ml]], tbl_IngrédientsRef[[#This Row],[PU_effectif_g/ml]] ) ) ), 0) -> 7 | S8: =IF(tbl_IngrédientsRef[[#This Row],[Unité]]="kg", tbl_IngrédientsRef[[#This Row],[Prix Au kg ou L]]/1000, IF(tbl_IngrédientsRef[[#This Row],[Unité]]="L", tbl_IngrédientsRef[[#This Row],[Prix Au kg ou L]]/1000, tbl_IngrédientsRef[[#This Row],[Prix/Uni Base]])) -> 7
A9: =IF(tbl_ProduitsRef[[#This Row],[Famille]]="Petits déjeuners","PDJ", IF(tbl_ProduitsRef[[#This Row],[Famille]]="À la carte","OND", IF(tbl_ProduitsRef[[#This Row],[Famille]]="Œufs & Omelettes","OME", IF(tbl_ProduitsRef[[#This Row],[Famille]]="Suppléments","SUP", IF(tbl_ProduitsRef[[#This Row],[Famille]]="Glaces & Desserts","DES", IF(tbl_ProduitsRef[[#This Row],[Famille]]="Crêpes & Gaufres","CRP", IF(tbl_ProduitsRef[[#This Row],[Famille]]="Boissons chaudes","BCH", IF(tbl_ProduitsRef[[#This Row],[Famille]]="Smoothies & Coctails","SmCk", IF(tbl_ProduitsRef[[#This Row],[Famille]]="Boissons froides","BFR", IF(tbl_ProduitsRef[[#This Row],[Famille]]="Milkshakes","MKS", IF(tbl_ProduitsRef[[#This Row],[Famille]]="Jus Frais","JUS", IF(tbl_ProduitsRef[[#This Row],[Famille]]="Poulet","PUL", IF(tbl_ProduitsRef[[#This Row],[Famille]]="Boucherie","VIA", IF(tbl_ProduitsRef[[#This Row],[Famille]]="Poissons & Fruits de mer","POI", IF(tbl_ProduitsRef[[#This Row],[Famille]]="Pâtes","PAT", IF(tbl_ProduitsRef[[#This Row],[Famille]]="Pizzas","PIZ", IF(tbl_ProduitsRef[[#This Row],[Famille]]="Entrées & Salades","ENT", IF(tbl_ProduitsRef[[#This Row],[Famille]]="Snack","SNK", IF(tbl_ProduitsRef[[#This Row],[Famille]]="Tajines & Coin marocain","TAJ"))))))))))))))))))) -> PDJ | B9: =COUNTIF(A$2:$A9,A9) -> 8 | D9: =IF(tbl_IngrédientsRef[[#This Row],[Catégorie]]="Boulangerie","BOU", IF(tbl_IngrédientsRef[[#This Row],[Catégorie]]="Féculents","FEC", IF(tbl_IngrédientsRef[[#This Row],[Catégorie]]="Préparations","PRP", IF(tbl_IngrédientsRef[[#This Row],[Catégorie]]="Viande Spécial","VSP", IF(tbl_IngrédientsRef[[#This Row],[Catégorie]]="Pâtes","PST", IF(tbl_IngrédientsRef[[#This Row],[Catégorie]]="Viande De Volaille","VOL", IF(tbl_IngrédientsRef[[#This Row],[Catégorie]]="Viande De Boeuf","BOE", IF(tbl_IngrédientsRef[[#This Row],[Catégorie]]="Viande d'Agneau","AGN", IF(tbl_IngrédientsRef[[#This Row],[Catégorie]]="Viande De Veau","VEA", IF(tbl_IngrédientsRef[[#This Row],[Catégorie]]="Charcuterie","CHA", IF(tbl_IngrédientsRef[[#This Row],[Catégorie]]="Poissons","POI", IF(tbl_IngrédientsRef[[#This Row],[Catégorie]]="Fruits de mer","FDM", IF(tbl_IngrédientsRef[[#This Row],[Catégorie]]="Produits laitiers","PRL", IF(tbl_IngrédientsRef[[#This Row],[Catégorie]]="Légumes","LEG", IF(tbl_IngrédientsRef[[#This Row],[Catégorie]]="Fruits frais","FRU", IF(tbl_IngrédientsRef[[#This Row],[Catégorie]]="Épicerie","EPI", IF(tbl_IngrédientsRef[[#This Row],[Catégorie]]="Produits Sucrés","PSU", IF(tbl_IngrédientsRef[[#This Row],[Catégorie]]="Condiments","CDM", IF(tbl_IngrédientsRef[[#This Row],[Catégorie]]="Sauces","SOS", IF(tbl_IngrédientsRef[[#This Row],[Catégorie]]="Glaces","GLA", IF(tbl_IngrédientsRef[[#This Row],[Catégorie]]="Desserts","DES", IF(tbl_IngrédientsRef[[#This Row],[Catégorie]]="Boissons chaudes & froides","BOI", "⚠️ Catégorie inconnue")))))))))))))))))))))) -> BOU | E9: =COUNTIF($D$2:D9,D9) -> 8 | G9: =Référentiels!A9&TEXT(Référentiels!B9,"000") -> PDJ008 | H9: Continental | I9: Petits déjeuners | J9: 48 | K9: =IFERROR( SUMIFS(#REF!,#REF!, tbl_ProduitsRef[[#This Row],[Cde_Prdt]]), 0) -> 0 | M9: Rghifa | N9: =Référentiels!D9&TEXT(Référentiels!E9,"000") -> BOU008 | O9: Boulangerie | P9: 2 | Q9: Pièce | R9: =IFERROR( IF(tbl_IngrédientsRef[[#This Row],[Unité]]="g", (tbl_IngrédientsRef[[#This Row],[PU_effectif_g/ml]]*1000), IF(tbl_IngrédientsRef[[#This Row],[Unité]]="ml", tbl_IngrédientsRef[[#This Row],[PU_effectif_g/ml]]*1000, IF(tbl_IngrédientsRef[[#This Row],[Unité]]="pièce", tbl_IngrédientsRef[[#This Row],[PU_effectif_g/ml]], tbl_IngrédientsRef[[#This Row],[PU_effectif_g/ml]] ) ) ), 0) -> 2 | S9: =IF(tbl_IngrédientsRef[[#This Row],[Unité]]="kg", tbl_IngrédientsRef[[#This Row],[Prix Au kg ou L]]/1000, IF(tbl_IngrédientsRef[[#This Row],[Unité]]="L", tbl_IngrédientsRef[[#This Row],[Prix Au kg ou L]]/1000, tbl_IngrédientsRef[[#This Row],[Prix/Uni Base]])) -> 2
A10: =IF(tbl_ProduitsRef[[#This Row],[Famille]]="Petits déjeuners","PDJ", IF(tbl_ProduitsRef[[#This Row],[Famille]]="À la carte","OND", IF(tbl_ProduitsRef[[#This Row],[Famille]]="Œufs & Omelettes","OME", IF(tbl_ProduitsRef[[#This Row],[Famille]]="Suppléments","SUP", IF(tbl_ProduitsRef[[#This Row],[Famille]]="Glaces & Desserts","DES", IF(tbl_ProduitsRef[[#This Row],[Famille]]="Crêpes & Gaufres","CRP", IF(tbl_ProduitsRef[[#This Row],[Famille]]="Boissons chaudes","BCH", IF(tbl_ProduitsRef[[#This Row],[Famille]]="Smoothies & Coctails","SmCk", IF(tbl_ProduitsRef[[#This Row],[Famille]]="Boissons froides","BFR", IF(tbl_ProduitsRef[[#This Row],[Famille]]="Milkshakes","MKS", IF(tbl_ProduitsRef[[#This Row],[Famille]]="Jus Frais","JUS", IF(tbl_ProduitsRef[[#This Row],[Famille]]="Poulet","PUL", IF(tbl_ProduitsRef[[#This Row],[Famille]]="Boucherie","VIA", IF(tbl_ProduitsRef[[#This Row],[Famille]]="Poissons & Fruits de mer","POI", IF(tbl_ProduitsRef[[#This Row],[Famille]]="Pâtes","PAT", IF(tbl_ProduitsRef[[#This Row],[Famille]]="Pizzas","PIZ", IF(tbl_ProduitsRef[[#This Row],[Famille]]="Entrées & Salades","ENT", IF(tbl_ProduitsRef[[#This Row],[Famille]]="Snack","SNK", IF(tbl_ProduitsRef[[#This Row],[Famille]]="Tajines & Coin marocain","TAJ"))))))))))))))))))) -> PDJ | B10: =COUNTIF(A$2:$A10,A10) -> 9 | D10: =IF(tbl_IngrédientsRef[[#This Row],[Catégorie]]="Boulangerie","BOU", IF(tbl_IngrédientsRef[[#This Row],[Catégorie]]="Féculents","FEC", IF(tbl_IngrédientsRef[[#This Row],[Catégorie]]="Préparations","PRP", IF(tbl_IngrédientsRef[[#This Row],[Catégorie]]="Viande Spécial","VSP", IF(tbl_IngrédientsRef[[#This Row],[Catégorie]]="Pâtes","PST", IF(tbl_IngrédientsRef[[#This Row],[Catégorie]]="Viande De Volaille","VOL", IF(tbl_IngrédientsRef[[#This Row],[Catégorie]]="Viande De Boeuf","BOE", IF(tbl_IngrédientsRef[[#This Row],[Catégorie]]="Viande d'Agneau","AGN", IF(tbl_IngrédientsRef[[#This Row],[Catégorie]]="Viande De Veau","VEA", IF(tbl_IngrédientsRef[[#This Row],[Catégorie]]="Charcuterie","CHA", IF(tbl_IngrédientsRef[[#This Row],[Catégorie]]="Poissons","POI", IF(tbl_IngrédientsRef[[#This Row],[Catégorie]]="Fruits de mer","FDM", IF(tbl_IngrédientsRef[[#This Row],[Catégorie]]="Produits laitiers","PRL", IF(tbl_IngrédientsRef[[#This Row],[Catégorie]]="Légumes","LEG", IF(tbl_IngrédientsRef[[#This Row],[Catégorie]]="Fruits frais","FRU", IF(tbl_IngrédientsRef[[#This Row],[Catégorie]]="Épicerie","EPI", IF(tbl_IngrédientsRef[[#This Row],[Catégorie]]="Produits Sucrés","PSU", IF(tbl_IngrédientsRef[[#This Row],[Catégorie]]="Condiments","CDM", IF(tbl_IngrédientsRef[[#This Row],[Catégorie]]="Sauces","SOS", IF(tbl_IngrédientsRef[[#This Row],[Catégorie]]="Glaces","GLA", IF(tbl_IngrédientsRef[[#This Row],[Catégorie]]="Desserts","DES", IF(tbl_IngrédientsRef[[#This Row],[Catégorie]]="Boissons chaudes & froides","BOI", "⚠️ Catégorie inconnue")))))))))))))))))))))) -> BOU | E10: =COUNTIF($D$2:D10,D10) -> 9 | G10: =Référentiels!A10&TEXT(Référentiels!B10,"000") -> PDJ009 | H10: Traditionnel | I10: Petits déjeuners | J10: 45 | K10: =IFERROR( SUMIFS(#REF!,#REF!, tbl_ProduitsRef[[#This Row],[Cde_Prdt]]), 0) -> 0 | M10: Harcha | N10: =Référentiels!D10&TEXT(Référentiels!E10,"000") -> BOU009 | O10: Boulangerie | P10: 2 | Q10: Pièce | R10: =IFERROR( IF(tbl_IngrédientsRef[[#This Row],[Unité]]="g", (tbl_IngrédientsRef[[#This Row],[PU_effectif_g/ml]]*1000), IF(tbl_IngrédientsRef[[#This Row],[Unité]]="ml", tbl_IngrédientsRef[[#This Row],[PU_effectif_g/ml]]*1000, IF(tbl_IngrédientsRef[[#This Row],[Unité]]="pièce", tbl_IngrédientsRef[[#This Row],[PU_effectif_g/ml]], tbl_IngrédientsRef[[#This Row],[PU_effectif_g/ml]] ) ) ), 0) -> 2 | S10: =IF(tbl_IngrédientsRef[[#This Row],[Unité]]="kg", tbl_IngrédientsRef[[#This Row],[Prix Au kg ou L]]/1000, IF(tbl_IngrédientsRef[[#This Row],[Unité]]="L", tbl_IngrédientsRef[[#This Row],[Prix Au kg ou L]]/1000, tbl_IngrédientsRef[[#This Row],[Prix/Uni Base]])) -> 2
A11: =IF(tbl_ProduitsRef[[#This Row],[Famille]]="Petits déjeuners","PDJ", IF(tbl_ProduitsRef[[#This Row],[Famille]]="À la carte","OND", IF(tbl_ProduitsRef[[#This Row],[Famille]]="Œufs & Omelettes","OME", IF(tbl_ProduitsRef[[#This Row],[Famille]]="Suppléments","SUP", IF(tbl_ProduitsRef[[#This Row],[Famille]]="Glaces & Desserts","DES", IF(tbl_ProduitsRef[[#This Row],[Famille]]="Crêpes & Gaufres","CRP", IF(tbl_ProduitsRef[[#This Row],[Famille]]="Boissons chaudes","BCH", IF(tbl_ProduitsRef[[#This Row],[Famille]]="Smoothies & Coctails","SmCk", IF(tbl_ProduitsRef[[#This Row],[Famille]]="Boissons froides","BFR", IF(tbl_ProduitsRef[[#This Row],[Famille]]="Milkshakes","MKS", IF(tbl_ProduitsRef[[#This Row],[Famille]]="Jus Frais","JUS", IF(tbl_ProduitsRef[[#This Row],[Famille]]="Poulet","PUL", IF(tbl_ProduitsRef[[#This Row],[Famille]]="Boucherie","VIA", IF(tbl_ProduitsRef[[#This Row],[Famille]]="Poissons & Fruits de mer","POI", IF(tbl_ProduitsRef[[#This Row],[Famille]]="Pâtes","PAT", IF(tbl_ProduitsRef[[#This Row],[Famille]]="Pizzas","PIZ", IF(tbl_ProduitsRef[[#This Row],[Famille]]="Entrées & Salades","ENT", IF(tbl_ProduitsRef[[#This Row],[Famille]]="Snack","SNK", IF(tbl_ProduitsRef[[#This Row],[Famille]]="Tajines & Coin marocain","TAJ"))))))))))))))))))) -> PDJ | B11: =COUNTIF(A$2:$A11,A11) -> 10 | D11: =IF(tbl_IngrédientsRef[[#This Row],[Catégorie]]="Boulangerie","BOU", IF(tbl_IngrédientsRef[[#This Row],[Catégorie]]="Féculents","FEC", IF(tbl_IngrédientsRef[[#This Row],[Catégorie]]="Préparations","PRP", IF(tbl_IngrédientsRef[[#This Row],[Catégorie]]="Viande Spécial","VSP", IF(tbl_IngrédientsRef[[#This Row],[Catégorie]]="Pâtes","PST", IF(tbl_IngrédientsRef[[#This Row],[Catégorie]]="Viande De Volaille","VOL", IF(tbl_IngrédientsRef[[#This Row],[Catégorie]]="Viande De Boeuf","BOE", IF(tbl_IngrédientsRef[[#This Row],[Catégorie]]="Viande d'Agneau","AGN", IF(tbl_IngrédientsRef[[#This Row],[Catégorie]]="Viande De Veau","VEA", IF(tbl_IngrédientsRef[[#This Row],[Catégorie]]="Charcuterie","CHA", IF(tbl_IngrédientsRef[[#This Row],[Catégorie]]="Poissons","POI", IF(tbl_IngrédientsRef[[#This Row],[Catégorie]]="Fruits de mer","FDM", IF(tbl_IngrédientsRef[[#This Row],[Catégorie]]="Produits laitiers","PRL", IF(tbl_IngrédientsRef[[#This Row],[Catégorie]]="Légumes","LEG", IF(tbl_IngrédientsRef[[#This Row],[Catégorie]]="Fruits frais","FRU", IF(tbl_IngrédientsRef[[#This Row],[Catégorie]]="Épicerie","EPI", IF(tbl_IngrédientsRef[[#This Row],[Catégorie]]="Produits Sucrés","PSU", IF(tbl_IngrédientsRef[[#This Row],[Catégorie]]="Condiments","CDM", IF(tbl_IngrédientsRef[[#This Row],[Catégorie]]="Sauces","SOS", IF(tbl_IngrédientsRef[[#This Row],[Catégorie]]="Glaces","GLA", IF(tbl_IngrédientsRef[[#This Row],[Catégorie]]="Desserts","DES", IF(tbl_IngrédientsRef[[#This Row],[Catégorie]]="Boissons chaudes & froides","BOI", "⚠️ Catégorie inconnue")))))))))))))))))))))) -> BOU | E11: =COUNTIF($D$2:D11,D11) -> 10 | G11: =Référentiels!A11&TEXT(Référentiels!B11,"000") -> PDJ010 | H11: Marocain | I11: Petits déjeuners | J11: 42 | K11: =IFERROR( SUMIFS(#REF!,#REF!, tbl_ProduitsRef[[#This Row],[Cde_Prdt]]), 0) -> 0 | M11: Baghrire | N11: =Référentiels!D11&TEXT(Référentiels!E11,"000") -> BOU010 | O11: Boulangerie | P11: 2 | Q11: Pièce | R11: =IFERROR( IF(tbl_IngrédientsRef[[#This Row],[Unité]]="g", (tbl_IngrédientsRef[[#This Row],[PU_effectif_g/ml]]*1000), IF(tbl_IngrédientsRef[[#This Row],[Unité]]="ml", tbl_IngrédientsRef[[#This Row],[PU_effectif_g/ml]]*1000, IF(tbl_IngrédientsRef[[#This Row],[Unité]]="pièce", tbl_IngrédientsRef[[#This Row],[PU_effectif_g/ml]], tbl_IngrédientsRef[[#This Row],[PU_effectif_g/ml]] ) ) ), 0) -> 2 | S11: =IF(tbl_IngrédientsRef[[#This Row],[Unité]]="kg", tbl_IngrédientsRef[[#This Row],[Prix Au kg ou L]]/1000, IF(tbl_IngrédientsRef[[#This Row],[Unité]]="L", tbl_IngrédientsRef[[#This Row],[Prix Au kg ou L]]/1000, tbl_IngrédientsRef[[#This Row],[Prix/Uni Base]])) -> 2
A12: =IF(tbl_ProduitsRef[[#This Row],[Famille]]="Petits déjeuners","PDJ", IF(tbl_ProduitsRef[[#This Row],[Famille]]="À la carte","OND", IF(tbl_ProduitsRef[[#This Row],[Famille]]="Œufs & Omelettes","OME", IF(tbl_ProduitsRef[[#This Row],[Famille]]="Suppléments","SUP", IF(tbl_ProduitsRef[[#This Row],[Famille]]="Glaces & Desserts","DES", IF(tbl_ProduitsRef[[#This Row],[Famille]]="Crêpes & Gaufres","CRP", IF(tbl_ProduitsRef[[#This Row],[Famille]]="Boissons chaudes","BCH", IF(tbl_ProduitsRef[[#This Row],[Famille]]="Smoothies & Coctails","SmCk", IF(tbl_ProduitsRef[[#This Row],[Famille]]="Boissons froides","BFR", IF(tbl_ProduitsRef[[#This Row],[Famille]]="Milkshakes","MKS", IF(tbl_ProduitsRef[[#This Row],[Famille]]="Jus Frais","JUS", IF(tbl_ProduitsRef[[#This Row],[Famille]]="Poulet","PUL", IF(tbl_ProduitsRef[[#This Row],[Famille]]="Boucherie","VIA", IF(tbl_ProduitsRef[[#This Row],[Famille]]="Poissons & Fruits de mer","POI", IF(tbl_ProduitsRef[[#This Row],[Famille]]="Pâtes","PAT", IF(tbl_ProduitsRef[[#This Row],[Famille]]="Pizzas","PIZ", IF(tbl_ProduitsRef[[#This Row],[Famille]]="Entrées & Salades","ENT", IF(tbl_ProduitsRef[[#This Row],[Famille]]="Snack","SNK", IF(tbl_ProduitsRef[[#This Row],[Famille]]="Tajines & Coin marocain","TAJ"))))))))))))))))))) -> PDJ | B12: =COUNTIF(A$2:$A12,A12) -> 11 | D12: =IF(tbl_IngrédientsRef[[#This Row],[Catégorie]]="Boulangerie","BOU", IF(tbl_IngrédientsRef[[#This Row],[Catégorie]]="Féculents","FEC", IF(tbl_IngrédientsRef[[#This Row],[Catégorie]]="Préparations","PRP", IF(tbl_IngrédientsRef[[#This Row],[Catégorie]]="Viande Spécial","VSP", IF(tbl_IngrédientsRef[[#This Row],[Catégorie]]="Pâtes","PST", IF(tbl_IngrédientsRef[[#This Row],[Catégorie]]="Viande De Volaille","VOL", IF(tbl_IngrédientsRef[[#This Row],[Catégorie]]="Viande De Boeuf","BOE", IF(tbl_IngrédientsRef[[#This Row],[Catégorie]]="Viande d'Agneau","AGN", IF(tbl_IngrédientsRef[[#This Row],[Catégorie]]="Viande De Veau","VEA", IF(tbl_IngrédientsRef[[#This Row],[Catégorie]]="Charcuterie","CHA", IF(tbl_IngrédientsRef[[#This Row],[Catégorie]]="Poissons","POI", IF(tbl_IngrédientsRef[[#This Row],[Catégorie]]="Fruits de mer","FDM", IF(tbl_IngrédientsRef[[#This Row],[Catégorie]]="Produits laitiers","PRL", IF(tbl_IngrédientsRef[[#This Row],[Catégorie]]="Légumes","LEG", IF(tbl_IngrédientsRef[[#This Row],[Catégorie]]="Fruits frais","FRU", IF(tbl_IngrédientsRef[[#This Row],[Catégorie]]="Épicerie","EPI", IF(tbl_IngrédientsRef[[#This Row],[Catégorie]]="Produits Sucrés","PSU", IF(tbl_IngrédientsRef[[#This Row],[Catégorie]]="Condiments","CDM", IF(tbl_IngrédientsRef[[#This Row],[Catégorie]]="Sauces","SOS", IF(tbl_IngrédientsRef[[#This Row],[Catégorie]]="Glaces","GLA", IF(tbl_IngrédientsRef[[#This Row],[Catégorie]]="Desserts","DES", IF(tbl_IngrédientsRef[[#This Row],[Catégorie]]="Boissons chaudes & froides","BOI", "⚠️ Catégorie inconnue")))))))))))))))))))))) -> BOU | E12: =COUNTIF($D$2:D12,D12) -> 11 | G12: =Référentiels!A12&TEXT(Référentiels!B12,"000") -> PDJ011 | H12: Parisien | I12: Petits déjeuners | J12: 40 | K12: =IFERROR( SUMIFS(#REF!,#REF!, tbl_ProduitsRef[[#This Row],[Cde_Prdt]]), 0) -> 0 | M12: Pizza Base | N12: =Référentiels!D12&TEXT(Référentiels!E12,"000") -> BOU011 | O12: Boulangerie | P12: 5 | Q12: Pièce | R12: =IFERROR( IF(tbl_IngrédientsRef[[#This Row],[Unité]]="g", (tbl_IngrédientsRef[[#This Row],[PU_effectif_g/ml]]*1000), IF(tbl_IngrédientsRef[[#This Row],[Unité]]="ml", tbl_IngrédientsRef[[#This Row],[PU_effectif_g/ml]]*1000, IF(tbl_IngrédientsRef[[#This Row],[Unité]]="pièce", tbl_IngrédientsRef[[#This Row],[PU_effectif_g/ml]], tbl_IngrédientsRef[[#This Row],[PU_effectif_g/ml]] ) ) ), 0) -> 5 | S12: =IF(tbl_IngrédientsRef[[#This Row],[Unité]]="kg", tbl_IngrédientsRef[[#This Row],[Prix Au kg ou L]]/1000, IF(tbl_IngrédientsRef[[#This Row],[Unité]]="L", tbl_IngrédientsRef[[#This Row],[Prix Au kg ou L]]/1000, tbl_IngrédientsRef[[#This Row],[Prix/Uni Base]])) -> 5
A13: =IF(tbl_ProduitsRef[[#This Row],[Famille]]="Petits déjeuners","PDJ", IF(tbl_ProduitsRef[[#This Row],[Famille]]="À la carte","OND", IF(tbl_ProduitsRef[[#This Row],[Famille]]="Œufs & Omelettes","OME", IF(tbl_ProduitsRef[[#This Row],[Famille]]="Suppléments","SUP", IF(tbl_ProduitsRef[[#This Row],[Famille]]="Glaces & Desserts","DES", IF(tbl_ProduitsRef[[#This Row],[Famille]]="Crêpes & Gaufres","CRP", IF(tbl_ProduitsRef[[#This Row],[Famille]]="Boissons chaudes","BCH", IF(tbl_ProduitsRef[[#This Row],[Famille]]="Smoothies & Coctails","SmCk", IF(tbl_ProduitsRef[[#This Row],[Famille]]="Boissons froides","BFR", IF(tbl_ProduitsRef[[#This Row],[Famille]]="Milkshakes","MKS", IF(tbl_ProduitsRef[[#This Row],[Famille]]="Jus Frais","JUS", IF(tbl_ProduitsRef[[#This Row],[Famille]]="Poulet","PUL", IF(tbl_ProduitsRef[[#This Row],[Famille]]="Boucherie","VIA", IF(tbl_ProduitsRef[[#This Row],[Famille]]="Poissons & Fruits de mer","POI", IF(tbl_ProduitsRef[[#This Row],[Famille]]="Pâtes","PAT", IF(tbl_ProduitsRef[[#This Row],[Famille]]="Pizzas","PIZ", IF(tbl_ProduitsRef[[#This Row],[Famille]]="Entrées & Salades","ENT", IF(tbl_ProduitsRef[[#This Row],[Famille]]="Snack","SNK", IF(tbl_ProduitsRef[[#This Row],[Famille]]="Tajines & Coin marocain","TAJ"))))))))))))))))))) -> OME | B13: =COUNTIF(A$2:$A13,A13) -> 1 | D13: =IF(tbl_IngrédientsRef[[#This Row],[Catégorie]]="Boulangerie","BOU", IF(tbl_IngrédientsRef[[#This Row],[Catégorie]]="Féculents","FEC", IF(tbl_IngrédientsRef[[#This Row],[Catégorie]]="Préparations","PRP", IF(tbl_IngrédientsRef[[#This Row],[Catégorie]]="Viande Spécial","VSP", IF(tbl_IngrédientsRef[[#This Row],[Catégorie]]="Pâtes","PST", IF(tbl_IngrédientsRef[[#This Row],[Catégorie]]="Viande De Volaille","VOL", IF(tbl_IngrédientsRef[[#This Row],[Catégorie]]="Viande De Boeuf","BOE", IF(tbl_IngrédientsRef[[#This Row],[Catégorie]]="Viande d'Agneau","AGN", IF(tbl_IngrédientsRef[[#This Row],[Catégorie]]="Viande De Veau","VEA", IF(tbl_IngrédientsRef[[#This Row],[Catégorie]]="Charcuterie","CHA", IF(tbl_IngrédientsRef[[#This Row],[Catégorie]]="Poissons","POI", IF(tbl_IngrédientsRef[[#This Row],[Catégorie]]="Fruits de mer","FDM", IF(tbl_IngrédientsRef[[#This Row],[Catégorie]]="Produits laitiers","PRL", IF(tbl_IngrédientsRef[[#This Row],[Catégorie]]="Légumes","LEG", IF(tbl_IngrédientsRef[[#This Row],[Catégorie]]="Fruits frais","FRU", IF(tbl_IngrédientsRef[[#This Row],[Catégorie]]="Épicerie","EPI", IF(tbl_IngrédientsRef[[#This Row],[Catégorie]]="Produits Sucrés","PSU", IF(tbl_IngrédientsRef[[#This Row],[Catégorie]]="Condiments","CDM", IF(tbl_IngrédientsRef[[#This Row],[Catégorie]]="Sauces","SOS", IF(tbl_IngrédientsRef[[#This Row],[Catégorie]]="Glaces","GLA", IF(tbl_IngrédientsRef[[#This Row],[Catégorie]]="Desserts","DES", IF(tbl_IngrédientsRef[[#This Row],[Catégorie]]="Boissons chaudes & froides","BOI", "⚠️ Catégorie inconnue")))))))))))))))))))))) -> BOU | E13: =COUNTIF($D$2:D13,D13) -> 12 | G13: =Référentiels!A13&TEXT(Référentiels!B13,"000") -> OME001 | H13: Omelette aux crevettes | I13: Œufs & Omelettes | J13: 35 | K13: =IFERROR( SUMIFS(#REF!,#REF!, tbl_ProduitsRef[[#This Row],[Cde_Prdt]]), 0) -> 0 | M13: Croûtons | N13: =Référentiels!D13&TEXT(Référentiels!E13,"000") -> BOU012 | O13: Boulangerie | P13: 0.2 | Q13: g | R13: =IFERROR( IF(tbl_IngrédientsRef[[#This Row],[Unité]]="g", (tbl_IngrédientsRef[[#This Row],[PU_effectif_g/ml]]*1000), IF(tbl_IngrédientsRef[[#This Row],[Unité]]="ml", tbl_IngrédientsRef[[#This Row],[PU_effectif_g/ml]]*1000, IF(tbl_IngrédientsRef[[#This Row],[Unité]]="pièce", tbl_IngrédientsRef[[#This Row],[PU_effectif_g/ml]], tbl_IngrédientsRef[[#This Row],[PU_effectif_g/ml]] ) ) ), 0) -> 200 | S13: =IF(tbl_IngrédientsRef[[#This Row],[Unité]]="kg", tbl_IngrédientsRef[[#This Row],[Prix Au kg ou L]]/1000, IF(tbl_IngrédientsRef[[#This Row],[Unité]]="L", tbl_IngrédientsRef[[#This Row],[Prix Au kg ou L]]/1000, tbl_IngrédientsRef[[#This Row],[Prix/Uni Base]])) -> 0.2
... A96: =IF(tbl_ProduitsRef[[#This Row],[Famille]]="Petits déjeuners","PDJ", IF(tbl_ProduitsRef[[#This Row],[Famille]]="À la carte","OND", IF(tbl_ProduitsRef[[#This Row],[Famille]]="Œufs & Omelettes","OME", IF(tbl_ProduitsRef[[#This Row],[Famille]]="Suppléments","SUP", IF(tbl_ProduitsRef[[#This Row],[Famille]]="Glaces & Desserts","DES", IF(tbl_ProduitsRef[[#This Row],[Famille]]="Crêpes & Gaufres","CRP", IF(tbl_ProduitsRef[[#This Row],[Famille]]="Boissons chaudes","BCH", IF(tbl_ProduitsRef[[#This Row],[Famille]]="Smoothies & Coctails","SmCk", IF(tbl_ProduitsRef[[#This Row],[Famille]]="Boissons froides","BFR", IF(tbl_ProduitsRef[[#This Row],[Famille]]="Milkshakes","MKS", IF(tbl_ProduitsRef[[#This Row],[Famille]]="Jus Frais","JUS", IF(tbl_ProduitsRef[[#This Row],[Famille]]="Poulet","PUL", IF(tbl_ProduitsRef[[#This Row],[Famille]]="Boucherie","VIA", IF(tbl_ProduitsRef[[#This Row],[Famille]]="Poissons & Fruits de mer","POI", IF(tbl_ProduitsRef[[#This Row],[Famille]]="Pâtes","PAT", IF(tbl_ProduitsRef[[#This Row],[Famille]]="Pizzas","PIZ", IF(tbl_ProduitsRef[[#This Row],[Famille]]="Entrées & Salades","ENT", IF(tbl_ProduitsRef[[#This Row],[Famille]]="Snack","SNK", IF(tbl_ProduitsRef[[#This Row],[Famille]]="Tajines & Coin marocain","TAJ"))))))))))))))))))) -> POI | B96: =COUNTIF(A$2:$A96,A96) -> 12 | D96: =IF(tbl_IngrédientsRef[[#This Row],[Catégorie]]="Boulangerie","BOU", IF(tbl_IngrédientsRef[[#This Row],[Catégorie]]="Féculents","FEC", IF(tbl_IngrédientsRef[[#This Row],[Catégorie]]="Préparations","PRP", IF(tbl_IngrédientsRef[[#This Row],[Catégorie]]="Viande Spécial","VSP", IF(tbl_IngrédientsRef[[#This Row],[Catégorie]]="Pâtes","PST", IF(tbl_IngrédientsRef[[#This Row],[Catégorie]]="Viande De Volaille","VOL", IF(tbl_IngrédientsRef[[#This Row],[Catégorie]]="Viande De Boeuf","BOE", IF(tbl_IngrédientsRef[[#This Row],[Catégorie]]="Viande d'Agneau","AGN", IF(tbl_IngrédientsRef[[#This Row],[Catégorie]]="Viande De Veau","VEA", IF(tbl_IngrédientsRef[[#This Row],[Catégorie]]="Charcuterie","CHA", IF(tbl_IngrédientsRef[[#This Row],[Catégorie]]="Poissons","POI", IF(tbl_IngrédientsRef[[#This Row],[Catégorie]]="Fruits de mer","FDM", IF(tbl_IngrédientsRef[[#This Row],[Catégorie]]="Produits laitiers","PRL", IF(tbl_IngrédientsRef[[#This Row],[Catégorie]]="Légumes","LEG", IF(tbl_IngrédientsRef[[#This Row],[Catégorie]]="Fruits frais","FRU", IF(tbl_IngrédientsRef[[#This Row],[Catégorie]]="Épicerie","EPI", IF(tbl_IngrédientsRef[[#This Row],[Catégorie]]="Produits Sucrés","PSU", IF(tbl_IngrédientsRef[[#This Row],[Catégorie]]="Condiments","CDM", IF(tbl_IngrédientsRef[[#This Row],[Catégorie]]="Sauces","SOS", IF(tbl_IngrédientsRef[[#This Row],[Catégorie]]="Glaces","GLA", IF(tbl_IngrédientsRef[[#This Row],[Catégorie]]="Desserts","DES", IF(tbl_IngrédientsRef[[#This Row],[Catégorie]]="Boissons chaudes & froides","BOI", "⚠️ Catégorie inconnue")))))))))))))))))))))) -> PRL | E96: =COUNTIF($D$2:D96,D96) -> 1 | G96: =Référentiels!A96&TEXT(Référentiels!B96,"000") -> POI012 | H96: Filet de Saint-Pierre | I96: Poissons & Fruits de mer | J96: 115 | K96: =IFERROR( SUMIFS(#REF!,#REF!, tbl_ProduitsRef[[#This Row],[Cde_Prdt]]), 0) -> 0 | M96: Oeufs Entiers | N96: =Référentiels!D96&TEXT(Référentiels!E96,"000") -> PRL001 | O96: Produits laitiers | P96: 0.9 | Q96: Pièce | R96: =IFERROR( IF(tbl_IngrédientsRef[[#This Row],[Unité]]="g", (tbl_IngrédientsRef[[#This Row],[PU_effectif_g/ml]]*1000), IF(tbl_IngrédientsRef[[#This Row],[Unité]]="ml", tbl_IngrédientsRef[[#This Row],[PU_effectif_g/ml]]*1000, IF(tbl_IngrédientsRef[[#This Row],[Unité]]="pièce", tbl_IngrédientsRef[[#This Row],[PU_effectif_g/ml]], tbl_IngrédientsRef[[#This Row],[PU_effectif_g/ml]] ) ) ), 0) -> 0.9 | S96: =IF(tbl_IngrédientsRef[[#This Row],[Unité]]="kg", tbl_IngrédientsRef[[#This Row],[Prix Au kg ou L]]/1000, IF(tbl_IngrédientsRef[[#This Row],[Unité]]="L", tbl_IngrédientsRef[[#This Row],[Prix Au kg ou L]]/1000, tbl_IngrédientsRef[[#This Row],[Prix/Uni Base]])) -> 0.9
A97: =IF(tbl_ProduitsRef[[#This Row],[Famille]]="Petits déjeuners","PDJ", IF(tbl_ProduitsRef[[#This Row],[Famille]]="À la carte","OND", IF(tbl_ProduitsRef[[#This Row],[Famille]]="Œufs & Omelettes","OME", IF(tbl_ProduitsRef[[#This Row],[Famille]]="Suppléments","SUP", IF(tbl_ProduitsRef[[#This Row],[Famille]]="Glaces & Desserts","DES", IF(tbl_ProduitsRef[[#This Row],[Famille]]="Crêpes & Gaufres","CRP", IF(tbl_ProduitsRef[[#This Row],[Famille]]="Boissons chaudes","BCH", IF(tbl_ProduitsRef[[#This Row],[Famille]]="Smoothies & Coctails","SmCk", IF(tbl_ProduitsRef[[#This Row],[Famille]]="Boissons froides","BFR", IF(tbl_ProduitsRef[[#This Row],[Famille]]="Milkshakes","MKS", IF(tbl_ProduitsRef[[#This Row],[Famille]]="Jus Frais","JUS", IF(tbl_ProduitsRef[[#This Row],[Famille]]="Poulet","PUL", IF(tbl_ProduitsRef[[#This Row],[Famille]]="Boucherie","VIA", IF(tbl_ProduitsRef[[#This Row],[Famille]]="Poissons & Fruits de mer","POI", IF(tbl_ProduitsRef[[#This Row],[Famille]]="Pâtes","PAT", IF(tbl_ProduitsRef[[#This Row],[Famille]]="Pizzas","PIZ", IF(tbl_ProduitsRef[[#This Row],[Famille]]="Entrées & Salades","ENT", IF(tbl_ProduitsRef[[#This Row],[Famille]]="Snack","SNK", IF(tbl_ProduitsRef[[#This Row],[Famille]]="Tajines & Coin marocain","TAJ"))))))))))))))))))) -> POI | B97: =COUNTIF(A$2:$A97,A97) -> 13 | D97: =IF(tbl_IngrédientsRef[[#This Row],[Catégorie]]="Boulangerie","BOU", IF(tbl_IngrédientsRef[[#This Row],[Catégorie]]="Féculents","FEC", IF(tbl_IngrédientsRef[[#This Row],[Catégorie]]="Préparations","PRP", IF(tbl_IngrédientsRef[[#This Row],[Catégorie]]="Viande Spécial","VSP", IF(tbl_IngrédientsRef[[#This Row],[Catégorie]]="Pâtes","PST", IF(tbl_IngrédientsRef[[#This Row],[Catégorie]]="Viande De Volaille","VOL", IF(tbl_IngrédientsRef[[#This Row],[Catégorie]]="Viande De Boeuf","BOE", IF(tbl_IngrédientsRef[[#This Row],[Catégorie]]="Viande d'Agneau","AGN", IF(tbl_IngrédientsRef[[#This Row],[Catégorie]]="Viande De Veau","VEA", IF(tbl_IngrédientsRef[[#This Row],[Catégorie]]="Charcuterie","CHA", IF(tbl_IngrédientsRef[[#This Row],[Catégorie]]="Poissons","POI", IF(tbl_IngrédientsRef[[#This Row],[Catégorie]]="Fruits de mer","FDM", IF(tbl_IngrédientsRef[[#This Row],[Catégorie]]="Produits laitiers","PRL", IF(tbl_IngrédientsRef[[#This Row],[Catégorie]]="Légumes","LEG", IF(tbl_IngrédientsRef[[#This Row],[Catégorie]]="Fruits frais","FRU", IF(tbl_IngrédientsRef[[#This Row],[Catégorie]]="Épicerie","EPI", IF(tbl_IngrédientsRef[[#This Row],[Catégorie]]="Produits Sucrés","PSU", IF(tbl_IngrédientsRef[[#This Row],[Catégorie]]="Condiments","CDM", IF(tbl_IngrédientsRef[[#This Row],[Catégorie]]="Sauces","SOS", IF(tbl_IngrédientsRef[[#This Row],[Catégorie]]="Glaces","GLA", IF(tbl_IngrédientsRef[[#This Row],[Catégorie]]="Desserts","DES", IF(tbl_IngrédientsRef[[#This Row],[Catégorie]]="Boissons chaudes & froides","BOI", "⚠️ Catégorie inconnue")))))))))))))))))))))) -> PRL | E97: =COUNTIF($D$2:D97,D97) -> 2 | G97: =Référentiels!A97&TEXT(Référentiels!B97,"000") -> POI013 | H97: Filet de poisson blanc au bordelais | I97: Poissons & Fruits de mer | J97: 110 | K97: =IFERROR( SUMIFS(#REF!,#REF!, tbl_ProduitsRef[[#This Row],[Cde_Prdt]]), 0) -> 0 | M97: Oeufs Jaune | N97: =Référentiels!D97&TEXT(Référentiels!E97,"000") -> PRL002 | O97: Produits laitiers | P97: =+P96*2 -> 1.8 | Q97: Pièce | R97: =IFERROR( IF(tbl_IngrédientsRef[[#This Row],[Unité]]="g", (tbl_IngrédientsRef[[#This Row],[PU_effectif_g/ml]]*1000), IF(tbl_IngrédientsRef[[#This Row],[Unité]]="ml", tbl_IngrédientsRef[[#This Row],[PU_effectif_g/ml]]*1000, IF(tbl_IngrédientsRef[[#This Row],[Unité]]="pièce", tbl_IngrédientsRef[[#This Row],[PU_effectif_g/ml]], tbl_IngrédientsRef[[#This Row],[PU_effectif_g/ml]] ) ) ), 0) -> 1.8 | S97: =IF(tbl_IngrédientsRef[[#This Row],[Unité]]="kg", tbl_IngrédientsRef[[#This Row],[Prix Au kg ou L]]/1000, IF(tbl_IngrédientsRef[[#This Row],[Unité]]="L", tbl_IngrédientsRef[[#This Row],[Prix Au kg ou L]]/1000, tbl_IngrédientsRef[[#This Row],[Prix/Uni Base]])) -> 1.8
A98: =IF(tbl_ProduitsRef[[#This Row],[Famille]]="Petits déjeuners","PDJ", IF(tbl_ProduitsRef[[#This Row],[Famille]]="À la carte","OND", IF(tbl_ProduitsRef[[#This Row],[Famille]]="Œufs & Omelettes","OME", IF(tbl_ProduitsRef[[#This Row],[Famille]]="Suppléments","SUP", IF(tbl_ProduitsRef[[#This Row],[Famille]]="Glaces & Desserts","DES", IF(tbl_ProduitsRef[[#This Row],[Famille]]="Crêpes & Gaufres","CRP", IF(tbl_ProduitsRef[[#This Row],[Famille]]="Boissons chaudes","BCH", IF(tbl_ProduitsRef[[#This Row],[Famille]]="Smoothies & Coctails","SmCk", IF(tbl_ProduitsRef[[#This Row],[Famille]]="Boissons froides","BFR", IF(tbl_ProduitsRef[[#This Row],[Famille]]="Milkshakes","MKS", IF(tbl_ProduitsRef[[#This Row],[Famille]]="Jus Frais","JUS", IF(tbl_ProduitsRef[[#This Row],[Famille]]="Poulet","PUL", IF(tbl_ProduitsRef[[#This Row],[Famille]]="Boucherie","VIA", IF(tbl_ProduitsRef[[#This Row],[Famille]]="Poissons & Fruits de mer","POI", IF(tbl_ProduitsRef[[#This Row],[Famille]]="Pâtes","PAT", IF(tbl_ProduitsRef[[#This Row],[Famille]]="Pizzas","PIZ", IF(tbl_ProduitsRef[[#This Row],[Famille]]="Entrées & Salades","ENT", IF(tbl_ProduitsRef[[#This Row],[Famille]]="Snack","SNK", IF(tbl_ProduitsRef[[#This Row],[Famille]]="Tajines & Coin marocain","TAJ"))))))))))))))))))) -> POI | B98: =COUNTIF(A$2:$A98,A98) -> 14 | D98: =IF(tbl_IngrédientsRef[[#This Row],[Catégorie]]="Boulangerie","BOU", IF(tbl_IngrédientsRef[[#This Row],[Catégorie]]="Féculents","FEC", IF(tbl_IngrédientsRef[[#This Row],[Catégorie]]="Préparations","PRP", IF(tbl_IngrédientsRef[[#This Row],[Catégorie]]="Viande Spécial","VSP", IF(tbl_IngrédientsRef[[#This Row],[Catégorie]]="Pâtes","PST", IF(tbl_IngrédientsRef[[#This Row],[Catégorie]]="Viande De Volaille","VOL", IF(tbl_IngrédientsRef[[#This Row],[Catégorie]]="Viande De Boeuf","BOE", IF(tbl_IngrédientsRef[[#This Row],[Catégorie]]="Viande d'Agneau","AGN", IF(tbl_IngrédientsRef[[#This Row],[Catégorie]]="Viande De Veau","VEA", IF(tbl_IngrédientsRef[[#This Row],[Catégorie]]="Charcuterie","CHA", IF(tbl_IngrédientsRef[[#This Row],[Catégorie]]="Poissons","POI", IF(tbl_IngrédientsRef[[#This Row],[Catégorie]]="Fruits de mer","FDM", IF(tbl_IngrédientsRef[[#This Row],[Catégorie]]="Produits laitiers","PRL", IF(tbl_IngrédientsRef[[#This Row],[Catégorie]]="Légumes","LEG", IF(tbl_IngrédientsRef[[#This Row],[Catégorie]]="Fruits frais","FRU", IF(tbl_IngrédientsRef[[#This Row],[Catégorie]]="Épicerie","EPI", IF(tbl_IngrédientsRef[[#This Row],[Catégorie]]="Produits Sucrés","PSU", IF(tbl_IngrédientsRef[[#This Row],[Catégorie]]="Condiments","CDM", IF(tbl_IngrédientsRef[[#This Row],[Catégorie]]="Sauces","SOS", IF(tbl_IngrédientsRef[[#This Row],[Catégorie]]="Glaces","GLA", IF(tbl_IngrédientsRef[[#This Row],[Catégorie]]="Desserts","DES", IF(tbl_IngrédientsRef[[#This Row],[Catégorie]]="Boissons chaudes & froides","BOI", "⚠️ Catégorie inconnue")))))))))))))))))))))) -> PRL | E98: =COUNTIF($D$2:D98,D98) -> 3 | G98: =Référentiels!A98&TEXT(Référentiels!B98,"000") -> POI014 | H98: Crevette calamar à la chermoula | I98: Poissons & Fruits de mer | J98: 70 | K98: =IFERROR( SUMIFS(#REF!,#REF!, tbl_ProduitsRef[[#This Row],[Cde_Prdt]]), 0) -> 0 | M98: Yaourt | N98: =Référentiels!D98&TEXT(Référentiels!E98,"000") -> PRL003 | O98: Produits laitiers | P98: 2.5 | Q98: Pièce | R98: =IFERROR( IF(tbl_IngrédientsRef[[#This Row],[Unité]]="g", (tbl_IngrédientsRef[[#This Row],[PU_effectif_g/ml]]*1000), IF(tbl_IngrédientsRef[[#This Row],[Unité]]="ml", tbl_IngrédientsRef[[#This Row],[PU_effectif_g/ml]]*1000, IF(tbl_IngrédientsRef[[#This Row],[Unité]]="pièce", tbl_IngrédientsRef[[#This Row],[PU_effectif_g/ml]], tbl_IngrédientsRef[[#This Row],[PU_effectif_g/ml]] ) ) ), 0) -> 2.5 | S98: =IF(tbl_IngrédientsRef[[#This Row],[Unité]]="kg", tbl_IngrédientsRef[[#This Row],[Prix Au kg ou L]]/1000, IF(tbl_IngrédientsRef[[#This Row],[Unité]]="L", tbl_IngrédientsRef[[#This Row],[Prix Au kg ou L]]/1000, tbl_IngrédientsRef[[#This Row],[Prix/Uni Base]])) -> 2.5
A99: =IF(tbl_ProduitsRef[[#This Row],[Famille]]="Petits déjeuners","PDJ", IF(tbl_ProduitsRef[[#This Row],[Famille]]="À la carte","OND", IF(tbl_ProduitsRef[[#This Row],[Famille]]="Œufs & Omelettes","OME", IF(tbl_ProduitsRef[[#This Row],[Famille]]="Suppléments","SUP", IF(tbl_ProduitsRef[[#This Row],[Famille]]="Glaces & Desserts","DES", IF(tbl_ProduitsRef[[#This Row],[Famille]]="Crêpes & Gaufres","CRP", IF(tbl_ProduitsRef[[#This Row],[Famille]]="Boissons chaudes","BCH", IF(tbl_ProduitsRef[[#This Row],[Famille]]="Smoothies & Coctails","SmCk", IF(tbl_ProduitsRef[[#This Row],[Famille]]="Boissons froides","BFR", IF(tbl_ProduitsRef[[#This Row],[Famille]]="Milkshakes","MKS", IF(tbl_ProduitsRef[[#This Row],[Famille]]="Jus Frais","JUS", IF(tbl_ProduitsRef[[#This Row],[Famille]]="Poulet","PUL", IF(tbl_ProduitsRef[[#This Row],[Famille]]="Boucherie","VIA", IF(tbl_ProduitsRef[[#This Row],[Famille]]="Poissons & Fruits de mer","POI", IF(tbl_ProduitsRef[[#This Row],[Famille]]="Pâtes","PAT", IF(tbl_ProduitsRef[[#This Row],[Famille]]="Pizzas","PIZ", IF(tbl_ProduitsRef[[#This Row],[Famille]]="Entrées & Salades","ENT", IF(tbl_ProduitsRef[[#This Row],[Famille]]="Snack","SNK", IF(tbl_ProduitsRef[[#This Row],[Famille]]="Tajines & Coin marocain","TAJ"))))))))))))))))))) -> POI | B99: =COUNTIF(A$2:$A99,A99) -> 15 | D99: =IF(tbl_IngrédientsRef[[#This Row],[Catégorie]]="Boulangerie","BOU", IF(tbl_IngrédientsRef[[#This Row],[Catégorie]]="Féculents","FEC", IF(tbl_IngrédientsRef[[#This Row],[Catégorie]]="Préparations","PRP", IF(tbl_IngrédientsRef[[#This Row],[Catégorie]]="Viande Spécial","VSP", IF(tbl_IngrédientsRef[[#This Row],[Catégorie]]="Pâtes","PST", IF(tbl_IngrédientsRef[[#This Row],[Catégorie]]="Viande De Volaille","VOL", IF(tbl_IngrédientsRef[[#This Row],[Catégorie]]="Viande De Boeuf","BOE", IF(tbl_IngrédientsRef[[#This Row],[Catégorie]]="Viande d'Agneau","AGN", IF(tbl_IngrédientsRef[[#This Row],[Catégorie]]="Viande De Veau","VEA", IF(tbl_IngrédientsRef[[#This Row],[Catégorie]]="Charcuterie","CHA", IF(tbl_IngrédientsRef[[#This Row],[Catégorie]]="Poissons","POI", IF(tbl_IngrédientsRef[[#This Row],[Catégorie]]="Fruits de mer","FDM", IF(tbl_IngrédientsRef[[#This Row],[Catégorie]]="Produits laitiers","PRL", IF(tbl_IngrédientsRef[[#This Row],[Catégorie]]="Légumes","LEG", IF(tbl_IngrédientsRef[[#This Row],[Catégorie]]="Fruits frais","FRU", IF(tbl_IngrédientsRef[[#This Row],[Catégorie]]="Épicerie","EPI", IF(tbl_IngrédientsRef[[#This Row],[Catégorie]]="Produits Sucrés","PSU", IF(tbl_IngrédientsRef[[#This Row],[Catégorie]]="Condiments","CDM", IF(tbl_IngrédientsRef[[#This Row],[Catégorie]]="Sauces","SOS", IF(tbl_IngrédientsRef[[#This Row],[Catégorie]]="Glaces","GLA", IF(tbl_IngrédientsRef[[#This Row],[Catégorie]]="Desserts","DES", IF(tbl_IngrédientsRef[[#This Row],[Catégorie]]="Boissons chaudes & froides","BOI", "⚠️ Catégorie inconnue")))))))))))))))))))))) -> PRL | E99: =COUNTIF($D$2:D99,D99) -> 4 | G99: =Référentiels!A99&TEXT(Référentiels!B99,"000") -> POI015 | H99: Briouates de fruits de mer | I99: Poissons & Fruits de mer | J99: 55 | K99: =IFERROR( SUMIFS(#REF!,#REF!, tbl_ProduitsRef[[#This Row],[Cde_Prdt]]), 0) -> 0 | M99: Oeufs Blanc | N99: =Référentiels!D99&TEXT(Référentiels!E99,"000") -> PRL004 | O99: Produits laitiers | P99: =+P97 -> 1.8 | Q99: Pièce | R99: =IFERROR( IF(tbl_IngrédientsRef[[#This Row],[Unité]]="g", (tbl_IngrédientsRef[[#This Row],[PU_effectif_g/ml]]*1000), IF(tbl_IngrédientsRef[[#This Row],[Unité]]="ml", tbl_IngrédientsRef[[#This Row],[PU_effectif_g/ml]]*1000, IF(tbl_IngrédientsRef[[#This Row],[Unité]]="pièce", tbl_IngrédientsRef[[#This Row],[PU_effectif_g/ml]], tbl_IngrédientsRef[[#This Row],[PU_effectif_g/ml]] ) ) ), 0) -> 1.8 | S99: =IF(tbl_IngrédientsRef[[#This Row],[Unité]]="kg", tbl_IngrédientsRef[[#This Row],[Prix Au kg ou L]]/1000, IF(tbl_IngrédientsRef[[#This Row],[Unité]]="L", tbl_IngrédientsRef[[#This Row],[Prix Au kg ou L]]/1000, tbl_IngrédientsRef[[#This Row],[Prix/Uni Base]])) -> 1.8
